Workbook

Sheet Dashboard
A1: Barrister Source of Truth — Authoritative Master | Verified Through Event 84
A3: Events 1–84 verified as the locked chronology; 79 payment records confirmed and 5 payment breakdowns remain pending.
A5: Completed Events | C5: Unique Clients | E5: Unique Work Orders | G5: Confirmed Revenue | I5: Pending Breakdown | K5: Pending ACH | M5: Open Exceptions
A6: 84 | C6: 31 | E6: 85 | G6: 9474.41 | I6: 5 | K6: 15 | M6: 5
A9: Financial Performance
A10: Avg / Eligible Event | C10: Avg / Workweek | E10: Worked Days | G10: Avg / Worked Day | I10: Breakdown Completion | K10: ACH Completion | M10: Outstanding Confirmed
A11: 119.92924 | C11: 676.74357 | E11: 54 | G11: 175.45204 | I11: 0.94047619 | K11: 0.8358209 | M11: 2150.39
A14: Operational Performance
A15: Current Workweek | C15: Current MY_MONTH | E15: Workday Utilization | G15: Events / Week | I15: Revenue / Week | K15: Mapping Holds | M15: Variance Exposure
A16: 14 | C16: MY_MONTH 4 — ACTIVE | E16: 0.77142857 | G16: 6 | I16: 676.74357 | K16: 0 | M16: 0
A18: Financial-Scope Events: 84 | Breakdown Confirmed: 79 | Breakdown Pending: 5 | Self-Healing: ACTIVE
A19: Weekday Performance | I19: Top Clients by Confirmed Revenue
A20: Weekday | B20: Confirmed Revenue | C20: Eligible Events | D20: Avg / Event | E20: Active Weeks | F20: Activity Rate | G20: Revenue Rank | I20: Rank | J20: Client | K20: Revenue | L20: Events | M20: Avg / Event | N20: Repeat
A21: =Analytics!J43 | B21: =Analytics!K43 | C21: =Analytics!L43 | D21: =Analytics!M43 | E21: =Analytics!N43 | F21: =Analytics!O43 | G21: =Analytics!R43 | I21: 1 | J21: =INDEX(tblClientSummary[Client Name],MATCH(LARGE(tblClientSummary[Confirmed Revenue],I21),tblClientSummary[Confirmed Revenue],0)) | K21: =LARGE(tblClientSummary[Confirmed Revenue],I21) | L21: =INDEX(tblClientSummary[Total Events],MATCH(K21,tblClientSummary[Confirmed Revenue],0)) | M21: =INDEX(tblClientSummary[Avg Revenue / Event],MATCH(K21,tblClientSummary[Confirmed Revenue],0)) | N21: =INDEX(tblClientSummary[Repeat Client],MATCH(K21,tblClientSummary[Confirmed Revenue],0))
A22: =Analytics!J44 | B22: =Analytics!K44 | C22: =Analytics!L44 | D22: =Analytics!M44 | E22: =Analytics!N44 | F22: =Analytics!O44 | G22: =Analytics!R44 | I22: 2 | J22: =INDEX(tblClientSummary[Client Name],MATCH(LARGE(tblClientSummary[Confirmed Revenue],I22),tblClientSummary[Confirmed Revenue],0)) | K22: =LARGE(tblClientSummary[Confirmed Revenue],I22) | L22: =INDEX(tblClientSummary[Total Events],MATCH(K22,tblClientSummary[Confirmed Revenue],0)) | M22: =INDEX(tblClientSummary[Avg Revenue / Event],MATCH(K22,tblClientSummary[Confirmed Revenue],0)) | N22: =INDEX(tblClientSummary[Repeat Client],MATCH(K22,tblClientSummary[Confirmed Revenue],0))
A23: =Analytics!J45 | B23: =Analytics!K45 | C23: =Analytics!L45 | D23: =Analytics!M45 | E23: =Analytics!N45 | F23: =Analytics!O45 | G23: =Analytics!R45 | I23: 3 | J23: =INDEX(tblClientSummary[Client Name],MATCH(LARGE(tblClientSummary[Confirmed Revenue],I23),tblClientSummary[Confirmed Revenue],0)) | K23: =LARGE(tblClientSummary[Confirmed Revenue],I23) | L23: =INDEX(tblClientSummary[Total Events],MATCH(K23,tblClientSummary[Confirmed Revenue],0)) | M23: =INDEX(tblClientSummary[Avg Revenue / Event],MATCH(K23,tblClientSummary[Confirmed Revenue],0)) | N23: =INDEX(tblClientSummary[Repeat Client],MATCH(K23,tblClientSummary[Confirmed Revenue],0))
A24: =Analytics!J46 | B24: =Analytics!K46 | C24: =Analytics!L46 | D24: =Analytics!M46 | E24: =Analytics!N46 | F24: =Analytics!O46 | G24: =Analytics!R46 | I24: 4 | J24: =INDEX(tblClientSummary[Client Name],MATCH(LARGE(tblClientSummary[Confirmed Revenue],I24),tblClientSummary[Confirmed Revenue],0)) | K24: =LARGE(tblClientSummary[Confirmed Revenue],I24) | L24: =INDEX(tblClientSummary[Total Events],MATCH(K24,tblClientSummary[Confirmed Revenue],0)) | M24: =INDEX(tblClientSummary[Avg Revenue / Event],MATCH(K24,tblClientSummary[Confirmed Revenue],0)) | N24: =INDEX(tblClientSummary[Repeat Client],MATCH(K24,tblClientSummary[Confirmed Revenue],0))
A25: =Analytics!J47 | B25: =Analytics!K47 | C25: =Analytics!L47 | D25: =Analytics!M47 | E25: =Analytics!N47 | F25: =Analytics!O47 | G25: =Analytics!R47 | I25: 5 | J25: =INDEX(tblClientSummary[Client Name],MATCH(LARGE(tblClientSummary[Confirmed Revenue],I25),tblClientSummary[Confirmed Revenue],0)) | K25: =LARGE(tblClientSummary[Confirmed Revenue],I25) | L25: =INDEX(tblClientSummary[Total Events],MATCH(K25,tblClientSummary[Confirmed Revenue],0)) | M25: =INDEX(tblClientSummary[Avg Revenue / Event],MATCH(K25,tblClientSummary[Confirmed Revenue],0)) | N25: =INDEX(tblClientSummary[Repeat Client],MATCH(K25,tblClientSummary[Confirmed Revenue],0))
A28: Jurisdiction Snapshot | H28: MY_MONTH Snapshot
A29: Jurisdiction | B29: Events | C29: Clients | D29: Revenue | E29: Avg / Event | F29: Revenue Share | H29: MY_MONTH | I29: Events | J29: Eligible | K29: Clients | L29: Jurisdictions | M29: Revenue | N29: Avg / Event
A30: =Analytics!A43 | B30: =Analytics!B43 | C30: =Analytics!D43 | D30: =Analytics!E43 | E30: =Analytics!F43 | F30: =Analytics!G43 | H30: =Analytics!A52 | I30: =Analytics!B52 | J30: =Analytics!C52 | K30: =Analytics!D52 | L30: =Analytics!E52 | M30: =Analytics!F52 | N30: =Analytics!G52
A31: =Analytics!A44 | B31: =Analytics!B44 | C31: =Analytics!D44 | D31: =Analytics!E44 | E31: =Analytics!F44 | F31: =Analytics!G44 | H31: =Analytics!A53 | I31: =Analytics!B53 | J31: =Analytics!C53 | K31: =Analytics!D53 | L31: =Analytics!E53 | M31: =Analytics!F53 | N31: =Analytics!G53
A32: =Analytics!A45 | B32: =Analytics!B45 | C32: =Analytics!D45 | D32: =Analytics!E45 | E32: =Analytics!F45 | F32: =Analytics!G45 | H32: =Analytics!A54 | I32: =Analytics!B54 | J32: =Analytics!C54 | K32: =Analytics!D54 | L32: =Analytics!E54 | M32: =Analytics!F54 | N32: =Analytics!G54
A33: =Analytics!A46 | B33: =Analytics!B46 | C33: =Analytics!D46 | D33: =Analytics!E46 | E33: =Analytics!F46 | F33: =Analytics!G46
A34: =Analytics!A47 | B34: =Analytics!B47 | C34: =Analytics!D47 | D34: =Analytics!E47 | E34: =Analytics!F47 | F34: =Analytics!G47
A37: Most Recent Completed Events
A38: Event # | B38: Date | C38: Weekday | D38: Client | E38: City | F38: Jurisdiction | G38: Status | H38: Work Orders | I38: Revenue | J38: Eligibility | K38: Visit Type | L38: Mapping / Financial Note | M38: Source | N38: Record ID
A39: 84 | B39: 46227 | C39: Friday | D39: Giant Food Stores | E39: Wheaton | F39: MD | G39: Completed | H39: 5922604 | J39: Pending | K39: Physical Service Visit | L39: Cradlepoint and PoE injector replaced; site restored. Payment breakdown pending. | M39: User completion + Gmail WO assignment and closeout correspondence | N39: EVT-0084
A40: 83 | B40: 46227 | C40: Friday | D40: Carvana | E40: Baltimore | F40: MD | G40: Completed | H40: 5919318 | I40: 65 | J40: Eligible | K40: Physical Service Visit | L40: HP fuser replacement completed; payment breakdown confirmed at $65.00. | M40: User completion + Gmail WO assignment and payment breakdown | N40: EVT-0083
A41: 82 | B41: 46226 | C41: Thursday | D41: TJ Maxx | E41: Alexandria | F41: VA | G41: Completed | H41: 5922683 | I41: 110 | J41: Eligible | K41: Physical Service Visit | L41: BERG adapter service completed; payment breakdown confirmed at $110.00. | M41: User chronology + Gmail ETA and payment breakdown | N41: EVT-0082
A42: 81 | B42: 46226 | C42: Thursday | D42: HomeGoods | E42: Fairfax | F42: VA | G42: Completed | H42: 5922660 | I42: 125 | J42: Eligible | K42: Physical Service Visit | L42: Power USB cable service completed; payment breakdown confirmed at $125.00. | M42: User chronology + Gmail ETA and payment breakdown | N42: EVT-0081
A43: 80 | B43: 46226 | C43: Thursday | D43: Marshalls | E43: Westminster | F43: MD | G43: Completed | H43: 5906863 | I43: 163.33 | J43: Eligible | K43: Physical Service Visit | L43: TJX server-refresh work completed; payment breakdown confirmed at $163.33. | M43: User chronology + Gmail WO assignment and payment breakdown | N43: EVT-0080
A44: Visual Analytics

Sheet Service Events
A1: Event # | B1: Physical Visit ID | C1: Service Date | D1: Weekday | E1: Workweek # | F1: MY_MONTH | G1: Client ID | H1: Client | I1: Site Name | J1: Address | K1: City | L1: State | M1: ZIP | N1: Jurisdiction | O1: Location Key | P1: Status | Q1: Visit Type | R1: Work Order Count | S1: Work Orders | T1: Confirmed Revenue | U1: Revenue Eligibility | V1: Notes | W1: Source / Evidence | X1: Financial Scope | Y1: Financial Exclusion Reason | Z1: Breakdown Expected
A2: 1 | B2: EVT-0001 | C2: 46132 | D2: Monday | E2: 1 | F2: MY_MONTH 1 | G2: CL-001 | H2: Macy's | I2: Macy's | K2: Fairfax | L2: Virginia | N2: VA | O2: Fairfax|VA | P2: Completed | Q2: Physical Service Visit | R2: 1 | S2: 5847113 | T2: 90 | U2: Eligible | V2: VA model from prior approved calculation. | W2: Timeline + Service Calendar + Canonical Ledger | X2: Included | Z2: Yes
A3: 2 | B3: EVT-0002 | C3: 46133 | D3: Tuesday | E3: 1 | F3: MY_MONTH 1 | G3: CL-002 | H3: Bloomingdale's | I3: Bloomingdale's | K3: Tysons | L3: Virginia | N3: VA | O3: Tysons|VA | P3: Completed | Q3: Physical Service Visit | R3: 1 | S3: 5860365 | T3: 344 | U3: Eligible | V3: 8-hour assist tech; effective $43/hr. | W3: Timeline + Service Calendar + Canonical Ledger | X3: Included | Z3: Yes
A4: 3 | B4: EVT-0003 | C4: 46134 | D4: Wednesday | E4: 1 | F4: MY_MONTH 1 | G4: CL-002 | H4: Bloomingdale's | I4: Bloomingdale's | K4: Tysons | L4: Virginia | N4: VA | O4: Tysons|VA | P4: Completed | Q4: Physical Service Visit | R4: 1 | S4: 5860393 | T4: 344 | U4: Eligible | V4: 8-hour assist tech; effective $43/hr. | W4: Timeline + Service Calendar + Canonical Ledger | X4: Included | Z4: Yes
A5: 4 | B5: EVT-0004 | C5: 46135 | D5: Thursday | E5: 1 | F5: MY_MONTH 1 | G5: CL-001 | H5: Macy's | I5: Macy's | K5: Frederick | L5: Maryland | N5: MD | O5: Frederick|MD | P5: Completed | Q5: Physical Service Visit | R5: 1 | S5: 5874484 | T5: 180 | U5: Eligible | V5: Maryland revenue included; hours inferred at $45/hr. | W5: Timeline + Service Calendar + Canonical Ledger | X5: Included | Z5: Yes
A6: 5 | B6: EVT-0005 | C6: 46136 | D6: Friday | E6: 1 | F6: MY_MONTH 1 | G6: CL-003 | H6: Hampton Inn & Suites | I6: Hampton Inn & Suites | K6: Washington | L6: Washington, DC | N6: DC | O6: Washington|DC | P6: Completed | Q6: Physical Service Visit | R6: 1 | S6: 5876589 | T6: 50 | U6: Eligible | V6: DC flat/equivalent event. | W6: Timeline + Service Calendar + Canonical Ledger | X6: Included | Z6: Yes
A7: 6 | B7: EVT-0006 | C7: 46139 | D7: Monday | E7: 2 | F7: MY_MONTH 1 | G7: CL-001 | H7: Macy's | I7: Macy's | K7: Frederick | L7: Maryland | N7: MD | O7: Frederick|MD | P7: Completed | Q7: Physical Service Visit | R7: 1 | S7: 5874982 | T7: 180 | U7: Eligible | V7: Maryland revenue included; hours inferred at $45/hr. | W7: Timeline + Service Calendar + Canonical Ledger | X7: Included | Z7: Yes
A8: 7 | B8: EVT-0007 | C8: 46141 | D8: Wednesday | E8: 2 | F8: MY_MONTH 1 | G8: CL-004 | H8: Davis Polk & Wardwell | I8: Davis Polk & Wardwell | K8: Washington | L8: Washington, DC | N8: DC | O8: Washington|DC | P8: Completed | Q8: Physical Service Visit | R8: 1 | S8: 5876638 | T8: 50 | U8: Eligible | V8: DC flat/equivalent event. | W8: Timeline + Service Calendar + Canonical Ledger | X8: Included | Z8: Yes
A9: 8 | B9: EVT-0008 | C9: 46141 | D9: Wednesday | E9: 2 | F9: MY_MONTH 1 | G9: CL-005 | H9: Hebrew Home of Greater Washington | I9: Hebrew Home of Greater Washington | K9: North Bethesda | L9: Maryland | N9: MD | O9: North Bethesda|MD | P9: Completed | Q9: Physical Service Visit | R9: 1 | S9: 5878985 | T9: 45 | U9: Eligible | V9: Maryland revenue included. | W9: Timeline + Service Calendar + Canonical Ledger | X9: Included | Z9: Yes
A10: 9 | B10: EVT-0009 | C10: 46142 | D10: Thursday | E10: 2 | F10: MY_MONTH 1 | G10: CL-006 | H10: 7-Eleven | I10: 7-Eleven | K10: Baltimore | L10: Maryland | N10: MD | O10: Baltimore|MD | P10: Completed | Q10: Physical Service Visit | R10: 1 | S10: UNRESOLVED-E009 | T10: 135 | U10: Eligible | V10: User-authoritative financial correction: 3 hours × $45 = $135.00. | W10: User-authoritative correction 2026-07-26 | X10: Included | Z10: Yes
A11: 10 | B11: EVT-0010 | C11: 46147 | D11: Tuesday | E11: 3 | F11: MY_MONTH 1 | G11: CL-007 | H11: Giant Food Stores | I11: Giant Food Stores | K11: Hanover | L11: Pennsylvania | N11: PA | O11: Hanover|PA | P11: Completed | Q11: Physical Service Visit | R11: 1 | S11: 5882097 | T11: 212.5 | U11: Eligible | V11: Corrected: Hanover PA WO 5882097. | W11: Timeline + Service Calendar + Canonical Ledger | X11: Included | Z11: Yes
A12: 11 | B12: EVT-0011 | C12: 46153 | D12: Monday | E12: 4 | F12: MY_MONTH 1 | G12: CL-008 | H12: Food Lion | I12: Food Lion | K12: Leesburg | L12: Virginia | N12: VA | O12: Leesburg|VA | P12: Completed | Q12: Physical Service Visit | R12: 1 | S12: 5884987 | T12: 157.5 | U12: Eligible | V12: VA model uses payment breakdown amount. | W12: Timeline + Service Calendar + Canonical Ledger | X12: Included | Z12: Yes
A13: 12 | B13: EVT-0012 | C13: 46154 | D13: Tuesday | E13: 4 | F13: MY_MONTH 1 | G13: CL-009 | H13: Weis Markets | I13: Weis Markets | K13: Chambersburg | L13: Pennsylvania | N13: PA | O13: Chambersburg|PA | P13: Completed | Q13: Physical Service Visit | R13: 1 | S13: 5884369 | T13: 85 | U13: Eligible | V13: User approved 2-hour $42.50/hr equivalent. | W13: Timeline + Service Calendar + Canonical Ledger | X13: Included | Z13: Yes
... A60: 59 | B60: EVT-0059 | C60: 46210 | D60: Tuesday | E60: 12 | F60: MY_MONTH 3 | G60: CL-026 | H60: Dunkin | I60: Dunkin | K60: Aberdeen | L60: Maryland | N60: MD | O60: Aberdeen|MD | P60: Completed | Q60: Physical Service Visit | R60: 1 | S60: 5900830 | T60: 250 | U60: Eligible | V60: Dunkin Aberdeen completed; 3 lanes + K27 kiosk; extended Verifone validation call; payment breakdown $250.00; ACH pending. | W60: Timeline + Service Calendar + Canonical Ledger | X60: Included | Z60: Yes
A61: 60 | B61: EVT-0060 | C61: 46211 | D61: Wednesday | E61: 12 | F61: MY_MONTH 3 | G61: CL-027 | H61: Carvana | I61: Carvana | K61: Baltimore | L61: Maryland | N61: MD | O61: Baltimore|MD | P61: Completed | Q61: Same-site multi-WO visit | R61: 2 | S61: 5912364 / 5914049 | U61: Excluded | V61: One physical Carvana visit with two work orders: 5914049 firmware resolved 98.00.0C; 5912364 cyan cleanup/blank-page escalation documented. One event, two WOs, $130 total. | W61: Timeline + Service Calendar + Canonical Ledger | X61: Included | Z61: Yes
A62: 61 | B62: EVT-0061 | C62: 46212 | D62: Thursday | E62: 12 | F62: MY_MONTH 3 | G62: CL-020 | H62: TJ Maxx | I62: TJ Maxx | K62: Germantown | L62: Maryland | N62: MD | O62: Germantown|MD | P62: Completed | Q62: Physical Service Visit | R62: 1 | S62: 5909344 | T62: 194.99 | U62: Eligible | V62: TJ Maxx Germantown server refresh completed 2026-07-09. Payment breakdown confirmed at $194.99 with no deductions; expected payment 2026-07-23; ACH pending. | W62: Gmail payment breakdown 2026-07-11 + Timeline + Service Calendar | X62: Included | Z62: Yes
A63: 62 | B63: EVT-0062 | C63: 46212 | D63: Thursday | E63: 12 | F63: MY_MONTH 3 | G63: CL-020 | H63: TJ Maxx | I63: TJ Maxx | K63: Martinsburg | L63: West Virginia | N63: WV | O63: Martinsburg|WV | P63: Completed | Q63: Physical Service Visit | R63: 1 | S63: 5913868 | T63: 100.83 | U63: Eligible | V63: TJ Maxx Martinsburg completed 2026-07-09. Negotiated $150; payment breakdown received for $100.83; variance -$49.17; expected payment 2026-07-23. | W63: Timeline + Service Calendar + Canonical Ledger | X63: Included | Z63: Yes
A64: 63 | B64: EVT-0063 | C64: 46216 | D64: Monday | E64: 13 | F64: MY_MONTH 3 | G64: CL-022 | H64: Marshalls | I64: Marshalls — Hunt Valley Town Center | J64: 118 Shawan Rd Ste W | K64: Cockeysville | L64: Maryland | M64: 21030 | N64: MD | O64: Cockeysville|MD | P64: Completed | Q64: Physical Service Visit | R64: 1 | S64: 5909368 | U64: Excluded | V64: Marshalls Cockeysville server refresh completed. Replacement store server installed and validated; front-left sliding rail was corrected during installation. Hourly rate $40; final breakdown pending. | W64: 5909368_MarshallsCockeysville.pdf + user-authoritative completion 2026-07-13 | X64: Included | Z64: Yes
A65: 64 | B65: EVT-0064 | C65: 46216 | D65: Monday | E65: 13 | F65: MY_MONTH 3 | G65: CL-022 | H65: Marshalls | I65: Marshalls 0764 | J65: 17646 Garland Groh Blvd | K65: Hagerstown | L65: Maryland | M65: 21740 | N65: MD | O65: Hagerstown|MD | P65: Completed | Q65: Physical Service Visit | R65: 1 | S65: 5916961 | U65: Excluded | V65: Marshalls Hagerstown Register 2 M440 replacement completed. Arrived 12:55 PM; extended onsite time was caused by support unavailability and incorrect IP/gateway values in the ticket. Barrister confirmed documented onsite hours would be paid at $55/hour. Final breakdown pending. | W65: 5916961_MarshallsHagerstown.pdf + user-authoritative completion and onsite timeline 2026-07-13 | X65: Included | Z65: Yes
A66: 65 | B66: EVT-0065 | C66: 46216 | D66: Monday | E66: 13 | F66: MY_MONTH 3 | G66: CL-016 | H66: HomeGoods | I66: HomeGoods 0652 | J66: 606 Quince Orchard Road | K66: Gaithersburg | L66: Maryland | M66: 20878 | N66: MD | O66: Gaithersburg|MD | P66: Completed | Q66: Physical Service Visit | R66: 1 | S66: 5917407 | T66: 129.16 | U66: Eligible | V66: Payment breakdown confirmed at $129.16. | W66: User-verified payment breakdown record | X66: Included | Z66: Yes
A67: 66 | B67: EVT-0066 | C67: 46217 | D67: Tuesday | E67: 13 | F67: MY_MONTH 3 | G67: CL-020 | H67: TJ Maxx | I67: TJ Maxx — Tollgate Mall | J67: 615 Bel Air Road | K67: Bel Air | L67: Maryland | M67: 21014 | N67: MD | O67: Bel Air|MD | P67: Completed | Q67: Physical Service Visit | R67: 1 | S67: 5909385 | U67: Excluded | V67: TJ Maxx Bel Air server refresh completed. Installed the NextGen 11 server in available rack space after labeling the VH1 and VH2 cabling. NCR completed the HDD/data migration and the replacement server came online successfully. All required functions were validated. VH1 was decommissioned, boxed, labeled, and prepared for return with shipping labels. No Mood Media, Tripplite, or Frontline equipment was installed. New server S/N 2M2D3000F3; asset tag A929164. MOD Lori Fox. Hourly rate $45; final payment breakdown pending. | W67: WO 5909385 RFS + FastField/photo evidence + user-authoritative completion 2026-07-14 | X67: Included | Z67: Yes
A68: 67 | B68: EVT-0067 | C68: 46217 | D68: Tuesday | E68: 13 | F68: MY_MONTH 3 | G68: CL-026 | H68: Dunkin | I68: Dunkin Donuts #342406 | J68: 645 S. Philadelphia Blvd | K68: Aberdeen | L68: Maryland | M68: 21001 | N68: MD | O68: Aberdeen|MD | P68: Completed | Q68: Physical Service Visit | R68: 1 | S68: 5914898 | T68: 183.74 | U68: Eligible | V68: Dunkin Aberdeen return visit completed. Continued troubleshooting the K27 kiosk issue. Verifone kept the technician on an extended support call and contacted the third-party kiosk provider, which advised that no technician was available and the issue required escalation to the United Service Desk. At the United Service Desk's direction, additional troubleshooting was completed, including rebooting POS 1 despite the issue remaining isolated to Kiosk 1. The unresolved kiosk issue was escalated for additional follow-up/dispatch, and support formally released the technician from site. Payment breakdown confirmed at $183.74 with no deductions; expected payment 2026-07-28; ACH pending. | W68: WO 5914898 RFS + user-authoritative completion + Gmail payment breakdown 2026-07-14 | X68: Included | Z68: Yes
A69: 68 | B69: EVT-0068 | C69: 46218 | D69: Wednesday | E69: 13 | F69: MY_MONTH 3 | G69: CL-026 | H69: Dunkin | I69: Dunkin — Fallston | K69: Fallston | L69: Maryland | N69: MD | O69: Fallston|MD | P69: Completed | Q69: Physical Service Visit | R69: 1 | S69: 5900854 | T69: 350 | U69: Eligible | V69: Dunkin Fallston visit completed. Payment breakdown confirmed at $350.00; Speed ACH expected 2026-07-29. | W69: User-authoritative completion + Gmail payment breakdown | X69: Included | Z69: Yes
A70: 69 | B70: EVT-0069 | C70: 46219 | D70: Thursday | E70: 13 | F70: MY_MONTH 3 | G70: CL-020 | H70: TJ Maxx | I70: TJ Maxx — Columbia | K70: Columbia | L70: Maryland | N70: MD | O70: Columbia|MD | P70: Completed | Q70: Physical Service Visit | R70: 1 | S70: 5909418 | T70: 180 | U70: Eligible | V70: TJ Maxx Columbia visit completed. Hourly rate $40.00; final payment breakdown pending. Payment breakdown confirmed at $180.00 with no deductions; expected payment 2026-07-30. | W70: User-authoritative completion + ticket details + Gmail payment breakdown | X70: Included | Z70: Yes
A71: 70 | B71: EVT-0070 | C71: 46219 | D71: Thursday | E71: 13 | F71: MY_MONTH 3 | G71: CL-007 | H71: Giant Food Stores | I71: Giant Food — Olney | K71: Olney | L71: Maryland | N71: MD | O71: Olney|MD | P71: Completed | Q71: Physical Service Visit | R71: 1 | S71: 5918899 | T71: 103.33 | U71: Eligible | V71: Giant Food Olney HCL network troubleshooting completed and technician released. Roof and server-room cabling were traced and tested; final payment breakdown pending. Payment breakdown confirmed at $103.33 with no deductions; expected payment 2026-07-30. | W71: User-authoritative completion + onsite troubleshooting notes + Gmail payment breakdown | X71: Included | Z71: Yes
A72: 71 | B72: EVT-0071 | C72: 46220 | D72: Friday | E72: 13 | F72: MY_MONTH 3 | G72: CL-028 | H72: WeWork | I72: WeWork DC18 | J72: 200 Massachusetts Ave NW | K72: Washington | L72: Washington, DC | M72: 20001 | N72: DC | O72: Washington|DC | P72: Completed | Q72: Physical Service Visit | R72: 1 | S72: 5918348 | T72: 90 | U72: Eligible | V72: User-authoritative confirmed amount: 2 hours × $45 = $90.00. | W72: User-authoritative correction 2026-07-26 | X72: Included | Z72: Yes
A73: 72 | B73: EVT-0072 | C73: 46220 | D73: Friday | E73: 13 | F73: MY_MONTH 3 | G73: CL-029 | H73: Miramar | I73: Hebrew Home of Greater Washington | K73: North Bethesda | L73: Maryland | N73: MD | O73: North Bethesda|MD | P73: Completed | Q73: Physical Service Visit | R73: 1 | S73: 5913115 | T73: 50 | U73: Eligible | V73: Miramar ticket at Hebrew Home closed by the client system after technician arrival and escalation. Promised flat rate $50.00 Speed ACH; completed chronology, but compensation classification and payment breakdown remain unresolved. Payment breakdown confirmed at $50.00 with no deductions; expected payment 2026-07-31. | W73: WO 5913115 + user-authoritative closed-ticket completion + Omnicare/Eric call notes + Gmail payment breakdown | X73: Included | Z73: Yes
A74: 73 | B74: EVT-0073 | C74: 46223 | D74: Monday | E74: 14 | F74: MY_MONTH 4 | G74: CL-030 | H74: Homesense | I74: Homesense TJH0030 | J74: 10220 Mill Run Cir | K74: Owings Mills | L74: Maryland | M74: 21117 | N74: MD | O74: Owings Mills|MD | P74: Completed | Q74: Physical Service Visit | R74: 1 | S74: 5906821 | T74: 180 | U74: Eligible | V74: VH2 server deinstall completed. Arrived 5:30 AM; store opened 7:00 AM. Delay joining NCR Bridgeline/Teams support. NCR confirmed additional Music Mood Media and Lounge Mood Media replacement scope, but the box onsite did not contain the replacement players and store management could not locate them. Additional delay obtaining the FedEx waybill and MOD signature. VH2 was removed, packaged, documented, and prepared for return. Payment breakdown confirmed at $180.00; expected payment 2026-08-03. | W74: WO 5906821 RFS + onsite completion notes + Gmail payment breakdown | X74: Included | Z74: Yes
A75: 74 | B75: EVT-0074 | C75: 46223 | D75: Monday | E75: 14 | F75: MY_MONTH 4 | G75: CL-031 | H75: Autumn Lake Healthcare | I75: Autumn Lake at Baltimore Washington | J75: 313 Hospital Dr | K75: Glen Burnie | L75: Maryland | M75: 21061 | N75: MD | O75: Glen Burnie|MD | P75: Completed | Q75: Physical Service Visit | R75: 1 | S75: 5919707 | T75: 50 | U75: Eligible | V75: Customer/site no-show. Technician called both listed numbers and spoke with front desk; staff did not recognize Nina or the reported fax issue. Equipment could not be identified or accessed. Payment breakdown confirmed at $50.00 with no deductions. | W75: WO 5919707 RFS + user-authoritative completion/no-show notes + Gmail payment breakdown received 2026-07-21 | X75: Included | Z75: Yes
A76: 75 | B76: EVT-0075 | C76: 46223 | D76: Monday | E76: 14 | F76: MY_MONTH 4 | G76: CL-031 | H76: Autumn Lake Healthcare | I76: Autumn Lake at Glen Burnie — Rosemary Unit | J76: 7355 E Furnace Branch Rd | K76: Glen Burnie | L76: Maryland | M76: 21060 | N76: MD | O76: Glen Burnie|MD | P76: Completed | Q76: Physical Service Visit | R76: 1 | S76: 5920784 | T76: 50 | U76: Eligible | V76: New Sharp MX-B427W installed in the Rosemary Unit. Fax testing failed because of a facility fax-line issue. Technician contacted Omnicare and troubleshot with Wade, who confirmed the line requires repair and will coordinate next steps. Printer/fax installation was completed, work area and packaging were cleaned, and required form was completed and signed. Payment breakdown confirmed at $50.00; expected payment 2026-08-03. | W76: WO 5920784 RFS + signed installation form/photo + user completion + Gmail payment breakdown | X76: Included | Z76: Yes
A77: 76 | B77: EVT-0076 | C77: 46224 | D77: Tuesday | E77: 14 | F77: MY_MONTH 4 | G77: CL-022 | H77: Marshalls | I77: Marshalls — Owings Mills | K77: Owings Mills | L77: Maryland | N77: MD | O77: Owings Mills|MD | P77: Completed | Q77: Physical Service Visit | R77: 1 | S77: 5906834 | T77: 120 | U77: Eligible | V77: Payment breakdown confirmed at $120.00. | W77: User-verified payment breakdown record | X77: Included | Z77: Yes
A78: 77 | B78: EVT-0077 | C78: 46225 | D78: Wednesday | E78: 14 | F78: MY_MONTH 4 | G78: CL-022 | H78: Marshalls | I78: Marshalls — Towson | K78: Towson | L78: Maryland | N78: MD | O78: Towson|MD | P78: Completed | Q78: Physical Service Visit | R78: 1 | S78: UNRESOLVED-E077 | U78: Pending | V78: Completed visit; work-order and payment breakdown mapping pending. | W78: User-authoritative chronology correction | X78: Included | Z78: Yes
A79: 78 | B79: EVT-0078 | C79: 46225 | D79: Wednesday | E79: 14 | F79: MY_MONTH 4 | G79: CL-026 | H79: Dunkin | I79: Dunkin — Owings Mills | K79: Owings Mills | L79: Maryland | N79: MD | O79: Owings Mills|MD | P79: Completed | Q79: Physical Service Visit | R79: 1 | S79: 5900769 | T79: 160.29 | U79: Eligible | V79: Payment breakdown confirmed at $160.29. | W79: User-verified payment breakdown record | X79: Included | Z79: Yes
A80: 79 | B80: EVT-0079 | C80: 46225 | D80: Wednesday | E80: 14 | F80: MY_MONTH 4 | G80: CL-006 | H80: 7-Eleven | I80: 7-Eleven — Fallston | J80: 2400 Pleasantville Rd | K80: Fallston | L80: Maryland | M80: 21047 | N80: MD | O80: Fallston|MD | P80: Completed | Q80: Physical Service Visit | R80: 1 | S80: 5921549 | T80: 168.75 | U80: Eligible | V80: Digital menu board service completed. Payment breakdown confirmed at $168.75; no deductions. | W80: User chronology + Gmail WO assignment and payment breakdown | X80: Included | Z80: Yes
A81: 80 | B81: EVT-0080 | C81: 46226 | D81: Thursday | E81: 14 | F81: MY_MONTH 4 | G81: CL-022 | H81: Marshalls | I81: Marshalls — Westminster | J81: 200 Clifton Blvd, Suite C | K81: Westminster | L81: Maryland | M81: 21157 | N81: MD | O81: Westminster|MD | P81: Completed | Q81: Physical Service Visit | R81: 1 | S81: 5906863 | T81: 163.33 | U81: Eligible | V81: TJX server-refresh work completed. Payment breakdown confirmed at $163.33; no deductions. | W81: User chronology + Gmail WO assignment and payment breakdown | X81: Included | Z81: Yes
A82: 81 | B82: EVT-0081 | C82: 46226 | D82: Thursday | E82: 14 | F82: MY_MONTH 4 | G82: CL-016 | H82: HomeGoods | I82: HomeGoods — Fairfax | K82: Fairfax | L82: Virginia | N82: VA | O82: Fairfax|VA | P82: Completed | Q82: Physical Service Visit | R82: 1 | S82: 5922660 | T82: 125 | U82: Eligible | V82: Power USB cable service completed. Payment breakdown confirmed at $125.00; no deductions. | W82: User chronology + Gmail ETA and payment breakdown | X82: Included | Z82: Yes
A83: 82 | B83: EVT-0082 | C83: 46226 | D83: Thursday | E83: 14 | F83: MY_MONTH 4 | G83: CL-020 | H83: TJ Maxx | I83: TJ Maxx — Alexandria | K83: Alexandria | L83: Virginia | N83: VA | O83: Alexandria|VA | P83: Completed | Q83: Physical Service Visit | R83: 1 | S83: 5922683 | T83: 110 | U83: Eligible | V83: BERG adapter service completed. Payment breakdown confirmed at $110.00; no deductions. | W83: User chronology + Gmail ETA and payment breakdown | X83: Included | Z83: Yes
A84: 83 | B84: EVT-0083 | C84: 46227 | D84: Friday | E84: 14 | F84: MY_MONTH 4 | G84: CL-027 | H84: Carvana | I84: Carvana — Baltimore | J84: 4901 Holabird Ave | K84: Baltimore | L84: Maryland | M84: 21224 | N84: MD | O84: Baltimore|MD | P84: Completed | Q84: Physical Service Visit | R84: 1 | S84: 5919318 | T84: 65 | U84: Eligible | V84: HP Color LaserJet Managed MFP fuser replaced and ticket completed. Payment breakdown confirmed at $65.00; no deductions. | W84: User completion + Gmail WO assignment and payment breakdown | X84: Included | Z84: Yes
A85: 84 | B85: EVT-0084 | C85: 46227 | D85: Friday | E85: 14 | F85: MY_MONTH 4 | G85: CL-007 | H85: Giant Food Stores | I85: Giant Food — Wheaton | J85: 2900 University Boulevard West | K85: Wheaton | L85: Maryland | M85: 20902 | N85: MD | O85: Wheaton|MD | P85: Completed | Q85: Physical Service Visit | R85: 1 | S85: 5922604 | U85: Pending | V85: Cradlepoint outage resolved after replacing the rooftop unit and PoE injector; Port 42 restored and site operational. Payment breakdown pending. | W85: User-authoritative completion + Gmail WO assignment and closeout correspondence | X85: Included | Z85: Yes
A86: 85 | C86: 46230 | H86: Dunkin | K86: Bel Air | L86: Maryland | N86: MD | P86: Completed
A87: 86 | C87: 46231 | H87: Marshalls | K87: Hyattsville | L87: Maryland | N87: MD | P87: Completed
A88: 87 | C88: 46231 | H88: WeWork | K88: Washington | L88: Washington, DC | N88: DC | P88: Completed
A89: 88 | C89: 46232 | H89: Dunkin | K89: Reisterstown | L89: Maryland | N89: MD | P89: Completed

Sheet Work Orders & Ledger
A1: Ledger Record ID | B1: Work Order # | C1: Event # | D1: Candidate Event(s) | E1: Client ID | F1: Client | G1: Service Date | H1: Weekday | I1: Site Name | J1: Address | K1: City | L1: State | M1: ZIP | N1: Jurisdiction | O1: Location Key | P1: Agreed Amount | Q1: Pay Type | R1: Breakdown Confirmed | S1: Breakdown Amount | T1: Breakdown Date | U1: Expected Payment Date | V1: ACH Confirmed | W1: ACH Amount | X1: ACH Date | Y1: Variance | Z1: Reconciliation Status | AA1: Mapping Status | AB1: Alias / Related WO | AC1: Notes | AD1: Source / Evidence
A2: LED-0001 | B2: 5847113 | C2: 1 | E2: CL-001 | F2: Macy's | G2: 46132 | H2: Monday | I2: Macy's | K2: Fairfax | L2: Virginia | N2: VA | O2: Fairfax|VA | R2: Yes | S2: 90 | V2: Yes | W2: 90 | Z2: Complete with note | AA2: Unique | AC2: VA model from prior approved calculation. | AD2: WO Alias Index + Canonical Ledger
A3: LED-0002 | B3: 5860365 | C3: 2 | E3: CL-002 | F3: Bloomingdale's | G3: 46133 | H3: Tuesday | I3: Bloomingdale's | K3: Tysons | L3: Virginia | N3: VA | O3: Tysons|VA | R3: Yes | S3: 344 | V3: Yes | W3: 344 | Z3: Complete | AA3: Unique | AC3: 8-hour assist tech; effective $43/hr. | AD3: WO Alias Index + Canonical Ledger
A4: LED-0003 | B4: 5860393 | C4: 3 | E4: CL-002 | F4: Bloomingdale's | G4: 46134 | H4: Wednesday | I4: Bloomingdale's | K4: Tysons | L4: Virginia | N4: VA | O4: Tysons|VA | R4: Yes | S4: 344 | V4: Yes | W4: 344 | Z4: Complete | AA4: Unique | AC4: 8-hour assist tech; effective $43/hr. | AD4: WO Alias Index + Canonical Ledger
A5: LED-0004 | B5: 5874484 | C5: 4 | E5: CL-001 | F5: Macy's | G5: 46135 | H5: Thursday | I5: Macy's | K5: Frederick | L5: Maryland | N5: MD | O5: Frederick|MD | R5: Yes | S5: 180 | V5: Yes | W5: 180 | Z5: Complete | AA5: Unique | AC5: Maryland revenue included; hours inferred at $45/hr. | AD5: WO Alias Index + Canonical Ledger
A6: LED-0005 | B6: 5876589 | C6: 5 | E6: CL-003 | F6: Hampton Inn & Suites | G6: 46136 | H6: Friday | I6: Hampton Inn & Suites | K6: Washington | L6: Washington, DC | N6: DC | O6: Washington|DC | R6: Yes | S6: 50 | V6: Yes | W6: 50 | Z6: Complete | AA6: Unique | AC6: DC flat/equivalent event. | AD6: WO Alias Index + Canonical Ledger
A7: LED-0006 | B7: 5874982 | C7: 6 | E7: CL-001 | F7: Macy's | G7: 46139 | H7: Monday | I7: Macy's | K7: Frederick | L7: Maryland | N7: MD | O7: Frederick|MD | R7: Yes | S7: 180 | V7: Yes | W7: 180 | Z7: Complete | AA7: Unique | AC7: Maryland revenue included; hours inferred at $45/hr. | AD7: WO Alias Index + Canonical Ledger
A8: LED-0007 | B8: 5876638 | C8: 7 | E8: CL-004 | F8: Davis Polk & Wardwell | G8: 46141 | H8: Wednesday | I8: Davis Polk & Wardwell | K8: Washington | L8: Washington, DC | N8: DC | O8: Washington|DC | R8: Yes | S8: 50 | V8: Yes | W8: 50 | Z8: Complete | AA8: Unique | AC8: DC flat/equivalent event. | AD8: WO Alias Index + Canonical Ledger
A9: LED-0008 | B9: 5878985 | C9: 8 | E9: CL-005 | F9: Hebrew Home of Greater Washington | G9: 46141 | H9: Wednesday | I9: Hebrew Home of Greater Washington | K9: North Bethesda | L9: Maryland | N9: MD | O9: North Bethesda|MD | R9: Yes | S9: 45 | V9: Yes | W9: 45 | Z9: Complete | AA9: Unique | AC9: Maryland revenue included. | AD9: WO Alias Index + Canonical Ledger
A10: LED-0009 | B10: UNRESOLVED-E009 | C10: 9 | E10: CL-006 | F10: 7-Eleven | G10: 46142 | H10: Thursday | I10: 7-Eleven | K10: Baltimore | L10: Maryland | N10: MD | O10: Baltimore|MD | Q10: User-confirmed compensation | R10: Yes | S10: 135 | T10: 46229 | V10: No | Y10: 0 | Z10: ACH missing | AA10: Unique | AC10: User-authoritative financial correction: 3 hours × $45 = $135.00. | AD10: User-authoritative correction 2026-07-26
A11: LED-0010 | B11: 5882097 | C11: 10 | E11: CL-007 | F11: Giant Food Stores | G11: 46147 | H11: Tuesday | I11: Giant Food Stores | K11: Hanover | L11: Pennsylvania | N11: PA | O11: Hanover|PA | R11: Yes | S11: 212.5 | V11: Yes | W11: 212.5 | Z11: Complete | AA11: Unique | AC11: Corrected: Hanover PA WO 5882097. | AD11: WO Alias Index + Canonical Ledger
A12: LED-0011 | B12: 5884987 | C12: 11 | E12: CL-008 | F12: Food Lion | G12: 46153 | H12: Monday | I12: Food Lion | K12: Leesburg | L12: Virginia | N12: VA | O12: Leesburg|VA | R12: Yes | S12: 157.5 | V12: Yes | W12: 157.5 | Z12: Complete with note | AA12: Unique | AC12: VA model uses payment breakdown amount. | AD12: WO Alias Index + Canonical Ledger
A13: LED-0012 | B13: 5884369 | C13: 12 | E13: CL-009 | F13: Weis Markets | G13: 46154 | H13: Tuesday | I13: Weis Markets | K13: Chambersburg | L13: Pennsylvania | N13: PA | O13: Chambersburg|PA | R13: Yes | S13: 85 | V13: Yes | W13: 85 | Z13: Complete | AA13: Unique | AC13: User approved 2-hour $42.50/hr equivalent. | AD13: WO Alias Index + Canonical Ledger
A14: LED-0013 | B14: 5885429 | C14: 13 | E14: CL-010 | F14: Office of MD Senator Chris Van Hollen | G14: 46155 | H14: Wednesday | I14: Office of MD Senator Chris Van Hollen | K14: Rockville | L14: Maryland | N14: MD | O14: Rockville|MD | R14: Yes | S14: 50 | V14: Yes | W14: 50 | Z14: Complete | AA14: Unique | AC14: Maryland revenue included; Senate model estimated at $40/hr. | AD14: WO Alias Index + Canonical Ledger
A15: LED-0014 | B15: UNRESOLVED-E014 | C15: 14 | E15: CL-011 | F15: Residential – Annapolis Neck, MD | G15: 46155 | H15: Wednesday | I15: Residential | K15: Annapolis Neck | L15: Maryland | N15: MD | O15: Annapolis Neck|MD | Q15: User-confirmed compensation | R15: Yes | S15: 25 | T15: 46229 | V15: No | Y15: 0 | Z15: ACH missing | AA15: Unique | AC15: User-authoritative no-show compensation: $25.00. | AD15: User-authoritative correction 2026-07-26
A16: LED-0015 | B16: 5886658 | C16: 15 | E16: CL-012 | F16: Verizon | G16: 46156 | H16: Thursday | I16: Verizon | K16: College Park | L16: Maryland | N16: MD | O16: College Park|MD | R16: Yes | S16: 75 | V16: Yes | W16: 75 | Z16: Complete | AA16: Unique | AC16: Maryland revenue included; hours inferred. | AD16: WO Alias Index + Canonical Ledger
A17: LED-0016 | B17: 5887090 | C17: 16 | E17: CL-013 | F17: Atrium Village | G17: 46157 | H17: Friday | I17: Atrium Village | K17: Owings Mills | L17: Maryland | N17: MD | O17: Owings Mills|MD | R17: Yes | S17: 45 | V17: Yes | W17: 45 | Z17: Complete | AA17: Unique | AC17: Maryland revenue included. | AD17: WO Alias Index + Canonical Ledger
A18: LED-0017 | B18: 5887094 | C18: 17 | E18: CL-014 | F18: Maryland Baptist Age Home | G18: 46161 | H18: Tuesday | I18: Maryland Baptist Age Home | K18: Baltimore | L18: Maryland | N18: MD | O18: Baltimore|MD | R18: Yes | S18: 50 | V18: Yes | W18: 50 | Z18: Complete | AA18: Unique | AC18: Maryland revenue included. | AD18: WO Alias Index + Canonical Ledger
A19: LED-0018 | B19: 5889356 | C19: 18 | E19: CL-015 | F19: Under Armour | G19: 46162 | H19: Wednesday | I19: Under Armour Day 1 | K19: Hanover | L19: Maryland | N19: MD | O19: Hanover|MD | R19: Yes | S19: 106.67 | V19: Yes | W19: 106.67 | Z19: Complete | AA19: Unique | AC19: Under Armour Day 1 split; total UA rounded to $260 with Day 2. | AD19: WO Alias Index + Canonical Ledger
A20: LED-0019 | B20: 5889356-D2 | C20: 19 | E20: CL-015 | F20: Under Armour | G20: 46163 | H20: Thursday | I20: Under Armour Day 2 | K20: Hanover | L20: Maryland | N20: MD | O20: Hanover|MD | R20: Yes | S20: 153.33 | V20: Yes | W20: 153.33 | Z20: Complete | AA20: Unique | AC20: Under Armour Day 2 split; total UA rounded to $260 with Day 1. | AD20: WO Alias Index + Canonical Ledger
A21: LED-0020 | B21: 5890220 | C21: 20 | E21: CL-007 | F21: Giant Food Stores | G21: 46163 | H21: Thursday | I21: Giant / Martin's | K21: Red Lion | L21: Pennsylvania | N21: PA | O21: Red Lion|PA | R21: Yes | S21: 112.5 | V21: Yes | W21: 112.5 | Z21: Complete | AA21: Unique | AC21: Corrected: Red Lion PA WO 5890220. | AD21: WO Alias Index + Canonical Ledger
A22: LED-0021 | B22: 5892123 | C22: 21 | E22: CL-008 | F22: Food Lion | G22: 46168 | H22: Tuesday | I22: Food Lion | K22: Middle River | L22: Maryland | N22: MD | O22: Middle River|MD | R22: Yes | S22: 97.91 | V22: Yes | W22: 97.91 | Z22: Complete | AA22: Unique | AC22: Maryland revenue included; hours inferred. | AD22: WO Alias Index + Canonical Ledger
A23: LED-0022 | B23: 5889718 | C23: 22 | E23: CL-016 | F23: HomeGoods | G23: 46168 | H23: Tuesday | I23: HomeGoods | K23: Gaithersburg | L23: Maryland | N23: MD | O23: Gaithersburg|MD | R23: Yes | S23: 50 | V23: Yes | W23: 50 | Z23: Complete | AA23: Unique | AC23: Maryland revenue included; hours inferred. | AD23: WO Alias Index + Canonical Ledger
A24: LED-0023 | B24: UNRESOLVED-E023 | C24: 23 | E24: CL-017 | F24: Joint Base Andrews | G24: 46169 | H24: Wednesday | I24: Joint Base Andrews | K24: Andrews AFB | L24: Maryland | N24: MD | O24: Andrews AFB|MD | Q24: User-confirmed compensation | R24: Yes | S24: 50 | T24: 46229 | V24: No | Y24: 0 | Z24: ACH missing | AA24: Unique | AC24: User-authoritative first-hour no-show compensation: $50.00. | AD24: User-authoritative correction 2026-07-26
A25: LED-0024 | B25: USDA-SPECIAL-E024 | C25: 24 | E25: CL-018 | F25: USDA | G25: 46169 | H25: Wednesday | I25: USDA Day 1 | K25: Washington | L25: Washington, DC | N25: DC | O25: Washington|DC | R25: Yes | S25: 200 | V25: Yes | W25: 200 | Z25: Complete | AA25: DUPLICATE / REVIEW | AC25: USDA corrected day allocation: $200 / 5 hrs @ $40/hr. | AD25: WO Alias Index + Canonical Ledger
A26: LED-0025 | B26: UNRESOLVED-E025 | C26: 25 | E26: CL-019 | F26: PepsiCo | G26: 46170 | H26: Thursday | I26: PepsiCo | K26: Cheverly | L26: Maryland | N26: MD | O26: Cheverly|MD | Q26: User-confirmed compensation | R26: Yes | S26: 50 | T26: 46229 | V26: No | Y26: 0 | Z26: ACH missing | AA26: Unique | AC26: User-authoritative first-hour no-show compensation: $50.00. | AD26: User-authoritative correction 2026-07-26
A27: LED-0026 | B27: USDA-SPECIAL-E026 | C27: 26 | E27: CL-018 | F27: USDA | G27: 46170 | H27: Thursday | I27: USDA Day 2 | K27: Washington | L27: Washington, DC | N27: DC | O27: Washington|DC | R27: Yes | S27: 175 | V27: Yes | W27: 175 | Z27: Complete | AA27: DUPLICATE / REVIEW | AC27: USDA corrected day allocation: $175 / 4.375 hrs @ $40/hr. | AD27: WO Alias Index + Canonical Ledger
A28: LED-0027 | B28: USDA-SPECIAL-E027 | C28: 27 | E28: CL-018 | F28: USDA | G28: 46174 | H28: Monday | I28: USDA Day 3 | K28: Washington | L28: Washington, DC | N28: DC | O28: Washington|DC | R28: Yes | S28: 320 | V28: Yes | W28: 320 | Z28: Complete | AA28: DUPLICATE / REVIEW | AC28: USDA corrected day allocation: $320 / 8 hrs @ $40/hr. | AD28: WO Alias Index + Canonical Ledger
A29: LED-0028 | B29: USDA-SPECIAL-E028 | C29: 28 | E29: CL-018 | F29: USDA | G29: 46175 | H29: Tuesday | I29: USDA Day 4 | K29: Washington | L29: Washington, DC | N29: DC | O29: Washington|DC | R29: Yes | S29: 320 | V29: Yes | W29: 320 | Z29: Complete | AA29: DUPLICATE / REVIEW | AC29: USDA corrected day allocation: $320 / 8 hrs @ $40/hr. | AD29: WO Alias Index + Canonical Ledger
A30: LED-0029 | B30: USDA-SPECIAL-E029 | C30: 29 | E30: CL-018 | F30: USDA | G30: 46176 | H30: Wednesday | I30: USDA Day 5 | K30: Washington | L30: Washington, DC | N30: DC | O30: Washington|DC | R30: Yes | S30: 200 | V30: Yes | W30: 200 | Z30: Complete | AA30: DUPLICATE / REVIEW | AC30: USDA corrected day allocation: $200 / 5 hrs @ $40/hr. | AD30: WO Alias Index + Canonical Ledger
A31: LED-0030 | B31: 5896733 | C31: 30 | E31: CL-020 | F31: TJ Maxx | G31: 46176 | H31: Wednesday | I31: TJ Maxx | K31: Rockville | L31: Maryland | N31: MD | O31: Rockville|MD | R31: Yes | S31: 96.66 | V31: Yes | W31: 96.66 | Z31: Complete | AA31: Unique | AC31: Event #30 TJ Maxx Rockville verified at $96.66. | AD31: WO Alias Index + Canonical Ledger
A32: LED-0031 | B32: USDA-SPECIAL-E031 | C32: 31 | E32: CL-018 | F32: USDA | G32: 46177 | H32: Thursday | I32: USDA Day 6 | K32: Washington | L32: Washington, DC | N32: DC | O32: Washington|DC | R32: Yes | S32: 140 | V32: Yes | W32: 140 | Z32: Complete | AA32: DUPLICATE / REVIEW | AC32: USDA corrected day allocation: $140 / 3.5 hrs @ $40/hr. | AD32: WO Alias Index + Canonical Ledger
A33: LED-0032 | B33: 5898007 | C33: 32 | E33: CL-021 | F33: Hilton Garden Inn | G33: 46178 | H33: Friday | I33: Hilton Garden Inn | K33: Fairfax | L33: Virginia | N33: VA | O33: Fairfax|VA | R33: Yes | S33: 25 | V33: Yes | W33: 25 | Z33: Complete | AA33: Unique | AC33: VA Hilton Garden Inn historical row. | AD33: WO Alias Index + Canonical Ledger
A34: LED-0033 | B34: 5896039 | C34: 33 | E34: CL-005 | F34: Hebrew Home of Greater Washington | G34: 46178 | H34: Friday | I34: Hebrew Home of Greater Washington | K34: North Bethesda | L34: Maryland | N34: MD | O34: North Bethesda|MD | R34: Yes | S34: 50 | V34: Yes | W34: 50 | Z34: Complete | AA34: Unique | AC34: Maryland revenue included. | AD34: WO Alias Index + Canonical Ledger
A35: LED-0034 | B35: 5898904 | C35: 34 | E35: CL-020 | F35: TJ Maxx | G35: 46178 | H35: Friday | I35: TJ Maxx | K35: Annapolis | L35: Maryland | N35: MD | O35: Annapolis|MD | R35: Yes | S35: 70 | V35: Yes | W35: 70 | Z35: Complete | AA35: Unique | AC35: Maryland revenue included. | AD35: WO Alias Index + Canonical Ledger
A36: LED-0035 | B36: 5899056 | C36: 35 | E36: CL-022 | F36: Marshalls | G36: 46181 | H36: Monday | I36: Marshalls | K36: Dunkirk | L36: Maryland | N36: MD | O36: Dunkirk|MD | R36: Yes | S36: 70 | V36: Yes | W36: 70 | Z36: Complete | AA36: Unique | AC36: Payment breakdown reissued/verified; no financial change. | AD36: WO Alias Index + Canonical Ledger
A37: LED-0036 | B37: 5899295 | C37: 36 | E37: CL-003 | F37: Hampton Inn & Suites | G37: 46182 | H37: Tuesday | I37: Hampton Inn & Suites | K37: Edgewood | L37: Maryland | N37: MD | O37: Edgewood|MD | R37: Yes | S37: 65 | V37: Yes | W37: 65 | Z37: Complete | AA37: Unique | AC37: Maryland revenue included. | AD37: WO Alias Index + Canonical Ledger
A38: LED-0037 | B38: 5899715 | C38: 37 | E38: CL-016 | F38: HomeGoods | G38: 46182 | H38: Tuesday | I38: HomeGoods | K38: Sterling | L38: Virginia | N38: VA | O38: Sterling|VA | R38: Yes | S38: 90 | V38: Yes | W38: 90 | Z38: Complete | AA38: Unique | AC38: VA revenue included. | AD38: WO Alias Index + Canonical Ledger
... A48: LED-0047 | B48: 5898644 | C48: 47 | E48: CL-025 | F48: Office of MD Senator Angela Alsobrooks | G48: 46191 | H48: Thursday | I48: Office of MD Senator Angela Alsobrooks | K48: Bowie | L48: Maryland | N48: MD | O48: Bowie|MD | R48: Yes | S48: 130 | V48: Yes | W48: 130 | Z48: Complete | AA48: Unique | AC48: Office of MD Senator Angela Alsobrooks Bowie WO 5898644; breakdown $130 and ACH confirmed July 2. | AD48: WO Alias Index + Canonical Ledger
A49: LED-0048 | B49: 5905576 | C49: 48 | E49: CL-005 | F49: Hebrew Home of Greater Washington | G49: 46191 | H49: Thursday | I49: Hebrew Home of Greater Washington | K49: North Bethesda | L49: Maryland | N49: MD | O49: North Bethesda|MD | R49: Yes | S49: 70 | V49: Mapping Review | Z49: Companion WO mapping review | AA49: Unique | AB49: 5905576 / 5905579 | AC49: Companion WO issue 5905576 / 5905579 remains under ACH mapping review; $35 ACH for 5905579 may relate to companion split or later no-show row. | AD49: WO Alias Index + Canonical Ledger
A50: LED-0049 | B50: 5899546 | C50: 49 | E50: CL-009 | F50: Weis Markets | G50: 46192 | H50: Friday | I50: Weis Markets | K50: Callaway | L50: Maryland | N50: MD | O50: Callaway|MD | R50: Yes | S50: 90 | V50: Yes | W50: 90 | Z50: Complete | AA50: Unique | AC50: Weis Markets Callaway WO 5899546; breakdown $90 and ACH confirmed July 2. | AD50: WO Alias Index + Canonical Ledger
A51: LED-0050 | B51: 5903036 | C51: 50 | E51: CL-007 | F51: Giant Food Stores | G51: 46192 | H51: Friday | I51: Giant Food Stores | K51: Washington | L51: Washington, DC | N51: DC | O51: Washington|DC | R51: Yes | S51: 50 | V51: Yes | W51: 50 | Z51: Complete | AA51: Unique | AC51: Giant Food Stores DC/Wisconsin Ave WO 5903036; breakdown $50 and ACH confirmed July 2. Corrected from prior TBD/missing state. | AD51: WO Alias Index + Canonical Ledger
A52: LED-0051 | B52: 5906380 | C52: 52 | E52: CL-008 | F52: Food Lion | G52: 46196 | H52: Tuesday | I52: Food Lion | K52: Upper Marlboro | L52: Maryland | N52: MD | O52: Upper Marlboro|MD | R52: Yes | S52: 116.24 | U52: 2026-07-07 | V52: No | Z52: ACH missing | AA52: Unique | AC52: Food Lion payment breakdown confirmed. | AD52: WO Alias Index + Canonical Ledger
A53: LED-0052 | B53: 5907571 | C53: 53 | E53: CL-021 | F53: Hilton Garden Inn | G53: 46197 | H53: Wednesday | I53: Hilton Garden Inn DC | K53: Washington | L53: Washington, DC | N53: DC | O53: Washington|DC | R53: Yes | S53: 132.03 | U53: 2026-07-08 | V53: Yes | W53: 132.03 | Z53: Complete | AA53: Unique | AC53: ACH B5907571T1 processed $132.03 on 2026-07-08. | AD53: WO Alias Index + Canonical Ledger
A54: LED-0053 | B54: 5910094 | C54: 54 | E54: CL-006 | F54: 7-Eleven | G54: 46203 | H54: Tuesday | I54: 7-Eleven | K54: Owings Mills | L54: Maryland | N54: MD | O54: Owings Mills|MD | R54: Yes | S54: 120 | U54: 2026-07-14 | V54: Yes | W54: 120 | X54: 46217 | Z54: Complete | AA54: Unique | AC54: ACH B5910094T1 processed $120.00 on 2026-07-14; deposit expected within 1–3 business days. | AD54: Gmail ACH confirmation 2026-07-14 + Canonical Ledger
A55: LED-0054 | B55: 5898645 | C55: 55 | E55: CL-025 | F55: Office of MD Senator Angela Alsobrooks | G55: 46204 | H55: Wednesday | I55: Office of MD Senator Angela Alsobrooks | K55: Largo | L55: Maryland | N55: MD | O55: Largo|MD | R55: Yes | S55: 120 | U55: 2026-07-15 | V55: No | Z55: ACH missing | AA55: Unique | AC55: Payment breakdown $120 received; ACH pending. | AD55: WO Alias Index + Canonical Ledger
A56: LED-0055 | B56: 5900784 | C56: 56 | E56: CL-026 | F56: Dunkin | G56: 46205 | H56: Thursday | I56: Dunkin | K56: Reisterstown | L56: Maryland | N56: MD | O56: Reisterstown|MD | R56: Yes | S56: 170.66 | U56: 2026-07-16 | V56: Yes | W56: 170.66 | X56: 46219 | Z56: Complete | AA56: Unique | AC56: ACH processed $170.66 on 2026-07-16. | AD56: Gmail ACH confirmation 2026-07-16 + Canonical Ledger
A57: LED-0056 | B57: 5911577 | C57: 57 | E57: CL-024 | F57: Montpelier Liquors | G57: 46209 | H57: Monday | I57: Montpelier Liquors | K57: Laurel | L57: Maryland | N57: MD | O57: Laurel|MD | R57: Yes | S57: 66.74 | U57: 2026-07-20 | V57: Yes | W57: 66.74 | X57: 46223 | Z57: Complete | AA57: Unique | AC57: No-access visit paid breakdown. ACH mapped to 2026-07-20 processed deposit. | AD57: WO Alias Index + Canonical Ledger + Gmail ACH 2026-07-20
A58: LED-0057 | B58: 5900780 | C58: 58 | E58: CL-026 | F58: Dunkin | G58: 46209 | H58: Monday | I58: Dunkin | K58: Lutherville | L58: Maryland | N58: MD | O58: Lutherville|MD | R58: Yes | S58: 202.5 | U58: 2026-07-20 | V58: Yes | W58: 202.5 | X58: 46223 | Z58: Complete | AA58: Unique | AC58: Dunkin Lutherville payment breakdown confirmed. ACH mapped to 2026-07-20 processed deposit. | AD58: WO Alias Index + Canonical Ledger + Gmail ACH 2026-07-20
A59: LED-0058 | B59: 5900830 | C59: 59 | E59: CL-026 | F59: Dunkin | G59: 46210 | H59: Tuesday | I59: Dunkin | K59: Aberdeen | L59: Maryland | N59: MD | O59: Aberdeen|MD | R59: Yes | S59: 250 | U59: 2026-07-21 | V59: No | Z59: ACH missing | AA59: Unique | AC59: Dunkin Aberdeen payment breakdown confirmed. | AD59: WO Alias Index + Canonical Ledger
A60: LED-0059 | B60: 5912364 | C60: 60 | E60: CL-027 | F60: Carvana | G60: 46211 | H60: Wednesday | I60: Carvana | K60: Baltimore | L60: Maryland | N60: MD | O60: Baltimore|MD | R60: Pending | U60: 2026-07-22 / pending | V60: No | Z60: Combined visit / partial breakdown | AA60: MULTI-WO VISIT | AB60: 5914049 / 5912364 | AC60: Alias maps to combined one-visit Carvana event; 5912364 closed by user, breakdown pending. | AD60: WO Alias Index + Canonical Ledger
A61: LED-0060 | B61: 5914049 | C61: 60 | E61: CL-027 | F61: Carvana | G61: 46211 | H61: Wednesday | I61: Carvana | K61: Baltimore | L61: Maryland | N61: MD | O61: Baltimore|MD | R61: Partial | S61: 65 | U61: 2026-07-22 / pending | V61: No | Z61: Combined visit / partial breakdown | AA61: MULTI-WO VISIT | AB61: 5914049 / 5912364 | AC61: Alias maps to combined one-visit Carvana event; 5914049 breakdown $65 received. | AD61: WO Alias Index + Canonical Ledger
A62: LED-0061 | B62: 5909344 | C62: 61 | E62: CL-020 | F62: TJ Maxx | G62: 46212 | H62: Thursday | I62: TJ Maxx | K62: Germantown | L62: Maryland | N62: MD | O62: Germantown|MD | R62: Yes | S62: 194.99 | T62: 46214 | U62: 46226 | V62: Yes | W62: 194.99 | X62: 46226 | Z62: Complete | AA62: Unique | AC62: ACH confirmed 2026-07-23 for $194.99. | AD62: Gmail ACH processed notice 2026-07-23, Bill B5909344T1
A63: LED-0062 | B63: 5913868 | C63: 62 | E63: CL-020 | F63: TJ Maxx | G63: 46212 | H63: Thursday | I63: TJ Maxx | K63: Martinsburg | L63: West Virginia | N63: WV | O63: Martinsburg|WV | P63: 150 | R63: Yes | S63: 100.83 | U63: 2026-07-23 | V63: Yes | W63: 100.83 | X63: 46226 | Y63: -49.17 | Z63: Complete with variance | AA63: Unique | AC63: ACH confirmed 2026-07-23 for $100.83; remains $49.17 below negotiated $150.00. | AD63: Gmail ACH processed notice 2026-07-23, Bill B5913868T1
A64: LED-0063 | B64: 5905579 | D64: 48 / 51 | E64: CL-005 | F64: Hebrew Home of Greater Washington | I64: Hebrew Home of Greater Washington | K64: North Bethesda | L64: Maryland | N64: MD | O64: North Bethesda|MD | R64: Mapping Hold | V64: Partial | W64: 35 | Z64: MAPPING_HOLD | AA64: MAPPING_HOLD | AB64: Candidate Events 48 / 51; companion WO 5905576 | AC64: Duplicate WO collision preserved without guessing. Event 48 legacy breakdown $70; Event 51 legacy breakdown $60; ACH $35. Human mapping required before assigning this WO. | AD64: Phase 1 duplicate rows consolidated
A65: LED-0064 | B65: 5909368 | C65: 63 | E65: CL-022 | F65: Marshalls | G65: 46216 | H65: Monday | I65: Marshalls — Hunt Valley Town Center | J65: 118 Shawan Rd Ste W | K65: Cockeysville | L65: Maryland | M65: 21030 | N65: MD | O65: Cockeysville|MD | Q65: Hourly | R65: Pending | U65: 2026-07-27 / pending breakdown | V65: No | Z65: Breakdown pending | AA65: Unique | AC65: Hourly rate $40.00. Server refresh completed; final payable hours and breakdown pending. | AD65: 5909368_MarshallsCockeysville.pdf + user-authoritative completion 2026-07-13
A66: LED-0065 | B66: 5916961 | C66: 64 | E66: CL-022 | F66: Marshalls | G66: 46216 | H66: Monday | I66: Marshalls 0764 | J66: 17646 Garland Groh Blvd | K66: Hagerstown | L66: Maryland | M66: 21740 | N66: MD | O66: Hagerstown|MD | Q66: Hourly | R66: Pending | U66: 2026-07-27 / pending breakdown | V66: No | Z66: Breakdown pending | AA66: Unique | AC66: Hourly rate $55.00. Documented onsite window began 12:55 PM. Extended time was heavily communicated and documented; delay resulted from support unavailability and incorrect ticket network information. Barrister guaranteed documented onsite hours would be paid. Final breakdown pending. | AD66: 5916961_MarshallsHagerstown.pdf + onsite notes + user-authoritative completion 2026-07-13
A67: LED-0066 | B67: 5917407 | C67: 65 | E67: CL-016 | F67: HomeGoods | G67: 46216 | H67: Monday | I67: HomeGoods 0652 | J67: 606 Quince Orchard Road | K67: Gaithersburg | L67: Maryland | M67: 20878 | N67: MD | O67: Gaithersburg|MD | Q67: Hourly | R67: Yes | S67: 129.16 | T67: 46229 | U67: 2026-07-27 / pending breakdown | V67: No | Y67: 0 | Z67: ACH missing | AA67: Unique | AC67: Payment breakdown confirmed at $129.16. | AD67: User-verified payment breakdown record
A68: LED-0067 | B68: 5909385 | C68: 66 | E68: CL-020 | F68: TJ Maxx | G68: 46217 | H68: Tuesday | I68: TJ Maxx — Tollgate Mall | J68: 615 Bel Air Road | K68: Bel Air | L68: Maryland | M68: 21014 | N68: MD | O68: Bel Air|MD | Q68: Hourly | R68: Pending | U68: 2026-07-28 / pending breakdown | V68: No | Z68: Breakdown pending | AA68: Unique | AC68: Hourly rate $45.00. NextGen 11 server installed and validated; VH1 decommissioned, boxed, and labeled for return. Final payable hours and payment breakdown pending. | AD68: WO 5909385 RFS + FastField/photo evidence + user-authoritative completion 2026-07-14
A69: LED-0068 | B69: 5914898 | C69: 67 | E69: CL-026 | F69: Dunkin | G69: 46217 | H69: Tuesday | I69: Dunkin Donuts #342406 | J69: 645 S. Philadelphia Blvd | K69: Aberdeen | L69: Maryland | M69: 21001 | N69: MD | O69: Aberdeen|MD | Q69: Hourly | R69: Yes | S69: 183.74 | T69: 46217 | U69: 46231 | V69: No | Z69: ACH missing | AA69: Unique | AC69: Return visit completed after extended Verifone, kiosk-vendor, and United Service Desk troubleshooting. Support released the technician after escalation. Payment breakdown $183.74, deductions $0.00, expected payment 2026-07-28; ACH pending. | AD69: WO 5914898 RFS + user-authoritative completion + Gmail payment breakdown received 2026-07-14
A70: LED-0069 | B70: 5900854 | C70: 68 | E70: CL-026 | F70: Dunkin | G70: 46218 | H70: Wednesday | I70: Dunkin — Fallston | K70: Fallston | L70: Maryland | N70: MD | O70: Fallston|MD | P70: 350 | Q70: Speed ACH | R70: Yes | S70: 350 | T70: 46218 | U70: 46232 | V70: No | Y70: 0 | Z70: ACH missing | AA70: Unique | AC70: Payment breakdown confirmed at $350.00; Speed ACH expected 2026-07-29. | AD70: User-authoritative completion + Gmail payment breakdown
A71: LED-0070 | B71: 5909418 | C71: 69 | E71: CL-020 | F71: TJ Maxx | G71: 46219 | H71: Thursday | I71: TJ Maxx — Columbia | K71: Columbia | L71: Maryland | N71: MD | O71: Columbia|MD | Q71: Hourly | R71: Yes | S71: 180 | T71: 46223 | U71: 46233 | V71: No | Y71: 0 | Z71: ACH missing | AA71: Unique | AC71: Hourly rate $40.00; final payment breakdown pending. Payment breakdown confirmed at $180.00; no deductions; expected payment 2026-07-30. | AD71: User-authoritative completion + ticket details + Gmail payment breakdown
A72: LED-0071 | B72: 5918899 | C72: 70 | E72: CL-007 | F72: Giant Food Stores | G72: 46219 | H72: Thursday | I72: Giant Food — Olney | K72: Olney | L72: Maryland | N72: MD | O72: Olney|MD | R72: Yes | S72: 103.33 | T72: 46223 | U72: 46233 | V72: No | Y72: 0 | Z72: ACH missing | AA72: Unique | AC72: HCL network troubleshooting completed; final payment breakdown pending. Payment breakdown confirmed at $103.33; no deductions; expected payment 2026-07-30. | AD72: User-authoritative completion + onsite notes + Gmail payment breakdown
A73: LED-0072 | B73: 5918348 | C73: 71 | E73: CL-028 | F73: WeWork | G73: 46220 | H73: Friday | I73: WeWork DC18 | J73: 200 Massachusetts Ave NW | K73: Washington | L73: Washington, DC | M73: 20001 | N73: DC | O73: Washington|DC | Q73: User-confirmed compensation | R73: Yes | S73: 90 | T73: 46229 | U73: Pending breakdown | V73: No | Y73: 0 | Z73: ACH missing | AA73: Unique | AC73: User-authoritative confirmed amount: 2 hours × $45 = $90.00. | AD73: User-authoritative correction 2026-07-26
A74: LED-0074 | B74: 5906821 | C74: 73 | E74: CL-030 | F74: Homesense | G74: 46223 | H74: Monday | I74: Homesense TJH0030 | J74: 10220 Mill Run Cir | K74: Owings Mills | L74: Maryland | M74: 21117 | N74: MD | O74: Owings Mills|MD | P74: 40 | Q74: Hourly / Speed ACH | R74: Yes | S74: 180 | T74: 46223 | U74: 46237 | V74: No | Y74: 0 | Z74: ACH missing | AA74: Unique | AC74: VH2 deinstall completed after support/coordination delays. Payment breakdown confirmed at $180.00; no deductions; expected payment 2026-08-03. | AD74: WO 5906821 RFS + completion notes + Gmail payment breakdown
A75: LED-0075 | B75: 5919707 | C75: 74 | E75: CL-031 | F75: Autumn Lake Healthcare | G75: 46223 | H75: Monday | I75: Autumn Lake at Baltimore Washington | J75: 313 Hospital Dr | K75: Glen Burnie | L75: Maryland | M75: 21061 | N75: MD | O75: Glen Burnie|MD | P75: 50 | Q75: Per Trip / Speed ACH | R75: Yes | S75: 50 | T75: 46224 | V75: No | Y75: 0 | Z75: ACH missing | AA75: Unique | AC75: Customer/site no-show compensation confirmed at $50.00; no deductions. ACH pending. | AD75: WO 5919707 RFS + user-authoritative no-show completion notes + Gmail payment breakdown 2026-07-21
A76: LED-0076 | B76: 5920784 | C76: 75 | E76: CL-031 | F76: Autumn Lake Healthcare | G76: 46223 | H76: Monday | I76: Autumn Lake at Glen Burnie — Rosemary Unit | J76: 7355 E Furnace Branch Rd | K76: Glen Burnie | L76: Maryland | M76: 21060 | N76: MD | O76: Glen Burnie|MD | P76: 50 | Q76: Per Trip / Speed ACH | R76: Yes | S76: 50 | T76: 46223 | U76: 46237 | V76: No | Y76: 0 | Z76: ACH missing | AA76: Unique | AC76: Sharp MX-B427W installation completed. Facility fax line failed testing; Omnicare Wade confirmed line repair is required and will coordinate next steps. Payment breakdown confirmed at $50.00; no deductions; expected payment 2026-08-03. | AD76: WO 5920784 RFS + signed form/photo + Omnicare call + Gmail payment breakdown
A77: LED-0077 | B77: UNRESOLVED-E076 | C77: 76 | E77: CL-022 | F77: Marshalls | G77: 46224 | H77: Tuesday | I77: Marshalls — Owings Mills | K77: Owings Mills | L77: Maryland | N77: MD | O77: Owings Mills|MD | R77: Pending | U77: Pending breakdown | V77: No | Z77: Breakdown pending | AA77: Unique | AC77: Completed visit; exact WO mapping pending. | AD77: User-authoritative chronology correction
A78: LED-0078 | B78: 5906834 | C78: 77 | E78: CL-022 | F78: Marshalls | G78: 46225 | H78: Wednesday | I78: Marshalls — Towson | K78: Towson | L78: Maryland | N78: MD | O78: Towson|MD | R78: Yes | S78: 120 | T78: 46229 | U78: Pending breakdown | V78: No | Y78: 0 | Z78: ACH missing | AA78: Unique | AC78: Payment breakdown confirmed at $120.00. | AD78: User-verified payment breakdown record
A79: LED-0079 | B79: UNRESOLVED-E078 | C79: 78 | E79: CL-026 | F79: Dunkin | G79: 46225 | H79: Wednesday | I79: Dunkin — Owings Mills | K79: Owings Mills | L79: Maryland | N79: MD | O79: Owings Mills|MD | R79: Pending | U79: Pending breakdown | V79: No | Z79: Breakdown pending | AA79: Unique | AC79: Completed visit; exact WO mapping pending. | AD79: User-authoritative chronology correction
A80: LED-0080 | B80: 5900769 | C80: 79 | E80: CL-006 | F80: 7-Eleven | G80: 46225 | H80: Wednesday | I80: 7-Eleven — Fallston | J80: 2400 Pleasantville Rd | K80: Fallston | L80: Maryland | M80: 21047 | N80: MD | O80: Fallston|MD | R80: Yes | S80: 160.29 | T80: 46229 | V80: No | Y80: 0 | Z80: ACH missing | AA80: Unique | AC80: Payment breakdown confirmed at $160.29. | AD80: User-verified payment breakdown record
A81: LED-0081 | B81: 5906863 | C81: 80 | E81: CL-022 | F81: Marshalls | G81: 46226 | H81: Thursday | I81: Marshalls — Westminster | J81: 200 Clifton Blvd, Suite C | K81: Westminster | L81: Maryland | M81: 21157 | N81: MD | O81: Westminster|MD | R81: Yes | S81: 163.33 | T81: 46226 | V81: No | Y81: 0 | Z81: ACH missing | AA81: Unique | AC81: Payment breakdown confirmed at $163.33; no deductions. | AD81: Gmail WO assignment + payment breakdown
A82: LED-0082 | B82: 5922660 | C82: 81 | E82: CL-016 | F82: HomeGoods | G82: 46226 | H82: Thursday | I82: HomeGoods — Fairfax | K82: Fairfax | L82: Virginia | N82: VA | O82: Fairfax|VA | R82: Yes | S82: 125 | T82: 46226 | V82: No | Y82: 0 | Z82: ACH missing | AA82: Unique | AC82: Power USB cable service; payment breakdown confirmed at $125.00. | AD82: User chronology + Gmail ETA and payment breakdown
A83: LED-0083 | B83: 5922683 | C83: 82 | E83: CL-020 | F83: TJ Maxx | G83: 46226 | H83: Thursday | I83: TJ Maxx — Alexandria | K83: Alexandria | L83: Virginia | N83: VA | O83: Alexandria|VA | R83: Yes | S83: 110 | T83: 46226 | V83: No | Y83: 0 | Z83: ACH missing | AA83: Unique | AC83: BERG adapter service; payment breakdown confirmed at $110.00. | AD83: User chronology + Gmail ETA and payment breakdown
A84: LED-0084 | B84: 5919318 | C84: 83 | E84: CL-027 | F84: Carvana | G84: 46227 | H84: Friday | I84: Carvana — Baltimore | J84: 4901 Holabird Ave | K84: Baltimore | L84: Maryland | M84: 21224 | N84: MD | O84: Baltimore|MD | R84: Yes | S84: 65 | T84: 46227 | V84: No | Y84: 0 | Z84: ACH missing | AA84: Unique | AC84: HP fuser replacement completed; payment breakdown confirmed at $65.00. | AD84: User completion + Gmail WO assignment and payment breakdown
A85: LED-0085 | B85: 5922604 | C85: 84 | E85: CL-007 | F85: Giant Food Stores | G85: 46227 | H85: Friday | I85: Giant Food — Wheaton | J85: 2900 University Boulevard West | K85: Wheaton | L85: Maryland | M85: 20902 | N85: MD | O85: Wheaton|MD | R85: Pending | U85: Pending breakdown | V85: No | Z85: Breakdown pending | AA85: Unique | AC85: Cradlepoint and PoE injector replaced; site restored. Payment breakdown pending. | AD85: User completion + Gmail WO assignment and closeout correspondence

Sheet Analytics
A1: Barrister Analytics Engine — Phase 3F | V1: Client ID | W1: Client | X1: Events | Y1: Work Orders | Z1: Revenue | AA1: Avg/Event | AB1: Avg/WO | AC1: Repeat | AD1: First Event | AE1: Revenue Key | AF1: Repeat Key | AG1: Avg Key | AI1: Service Date | AJ1: Events | AK1: Eligible Events | AL1: Daily Revenue | AM1: Running Revenue | AN1: Rolling 5-Day Avg
V2: =A12 | W2: =B12 | X2: =E12 | Y2: =F12 | Z2: =G12 | AA2: =H12 | AB2: =I12 | AC2: =L12 | AD2: =C12 | AE2: =G12+(1000-C12)/1000000000 | AF2: =E12+G12/1000000000 | AG2: =IF(E12>1,H12+G12/1000000000,0) | AI2: 46132 | AJ2: 1 | AK2: 1 | AL2: 90 | AM2: 90 | AN2: 90
V3: =A13 | W3: =B13 | X3: =E13 | Y3: =F13 | Z3: =G13 | AA3: =H13 | AB3: =I13 | AC3: =L13 | AD3: =C13 | AE3: =G13+(1000-C13)/1000000000 | AF3: =E13+G13/1000000000 | AG3: =IF(E13>1,H13+G13/1000000000,0) | AI3: 46133 | AJ3: 1 | AK3: 1 | AL3: 344 | AM3: 434 | AN3: 217
A4: Analytics Controls | V4: =A14 | W4: =B14 | X4: =E14 | Y4: =F14 | Z4: =G14 | AA4: =H14 | AB4: =I14 | AC4: =L14 | AD4: =C14 | AE4: =G14+(1000-C14)/1000000000 | AF4: =E14+G14/1000000000 | AG4: =IF(E14>1,H14+G14/1000000000,0) | AI4: 46134 | AJ4: 1 | AK4: 1 | AL4: 344 | AM4: 778 | AN4: 259.33
A5: Complete Workweeks | B5: 12 | V5: =A15 | W5: =B15 | X5: =E15 | Y5: =F15 | Z5: =G15 | AA5: =H15 | AB5: =I15 | AC5: =L15 | AD5: =C15 | AE5: =G15+(1000-C15)/1000000000 | AF5: =E15+G15/1000000000 | AG5: =IF(E15>1,H15+G15/1000000000,0) | AI5: 46135 | AJ5: 1 | AK5: 1 | AL5: 180 | AM5: 958 | AN5: 239.5
A6: Completed Events | B6: 72 | V6: =A16 | W6: =B16 | X6: =E16 | Y6: =F16 | Z6: =G16 | AA6: =H16 | AB6: =I16 | AC6: =L16 | AD6: =C16 | AE6: =G16+(1000-C16)/1000000000 | AF6: =E16+G16/1000000000 | AG6: =IF(E16>1,H16+G16/1000000000,0) | AI6: 46136 | AJ6: 1 | AK6: 1 | AL6: 50 | AM6: 1008 | AN6: 201.6
A7: Eligible Confirmed Revenue | B7: 7584.55 | V7: =A17 | W7: =B17 | X7: =E17 | Y7: =F17 | Z7: =G17 | AA7: =H17 | AB7: =I17 | AC7: =L17 | AD7: =C17 | AE7: =G17+(1000-C17)/1000000000 | AF7: =E17+G17/1000000000 | AG7: =IF(E17>1,H17+G17/1000000000,0) | AI7: 46139 | AJ7: 1 | AK7: 1 | AL7: 180 | AM7: 1188 | AN7: 219.6
A8: Eligible Events | B8: =COUNTIFS(tblServiceEvents[Revenue Eligibility],"Eligible") | V8: =A18 | W8: =B18 | X8: =E18 | Y8: =F18 | Z8: =G18 | AA8: =H18 | AB8: =I18 | AC8: =L18 | AD8: =C18 | AE8: =G18+(1000-C18)/1000000000 | AF8: =E18+G18/1000000000 | AG8: =IF(E18>1,H18+G18/1000000000,0) | AI8: 46141 | AJ8: 2 | AK8: 2 | AL8: 95 | AM8: 1283 | AN8: 169.8
A9: Financial-Scope Events | B9: 68 | D9: Chronology-Only Events | E9: 4 | V9: =A19 | W9: =B19 | X9: =E19 | Y9: =F19 | Z9: =G19 | AA9: =H19 | AB9: =I19 | AC9: =L19 | AD9: =C19 | AE9: =G19+(1000-C19)/1000000000 | AF9: =E19+G19/1000000000 | AG9: =IF(E19>1,H19+G19/1000000000,0) | AI9: 46142 | AJ9: 1 | AK9: 0 | AL9: 0 | AM9: 1283 | AN9: 101
A10: Client Summary | V10: =A20 | W10: =B20 | X10: =E20 | Y10: =F20 | Z10: =G20 | AA10: =H20 | AB10: =I20 | AC10: =L20 | AD10: =C20 | AE10: =G20+(1000-C20)/1000000000 | AF10: =E20+G20/1000000000 | AG10: =IF(E20>1,H20+G20/1000000000,0) | AI10: 46147 | AJ10: 1 | AK10: 1 | AL10: 212.5 | AM10: 1495.5 | AN10: 107.5
A11: Client ID | B11: Client Name | C11: First Event | D11: Latest Event | E11: Total Events | F11: Total Work Orders | G11: Confirmed Revenue | H11: Avg Revenue / Event | I11: Avg Revenue / WO | J11: States Worked | K11: Cities Worked | L11: Repeat Client | V11: =A21 | W11: =B21 | X11: =E21 | Y11: =F21 | Z11: =G21 | AA11: =H21 | AB11: =I21 | AC11: =L21 | AD11: =C21 | AE11: =G21+(1000-C21)/1000000000 | AF11: =E21+G21/1000000000 | AG11: =IF(E21>1,H21+G21/1000000000,0) | AI11: 46153 | AJ11: 1 | AK11: 1 | AL11: 157.5 | AM11: 1653 | AN11: 129
A12: CL-001 | B12: Macy's | C12: =MINIFS(tblServiceEvents[Event #],tblServiceEvents[Client],B12) | D12: =MAXIFS(tblServiceEvents[Event #],tblServiceEvents[Client],B12) | E12: =COUNTIFS(tblServiceEvents[Client],B12,tblServiceEvents[Status],"Completed") | F12: =COUNTIF(tblLedger[Client],B12) | G12: =SUMIFS(tblServiceEvents[Confirmed Revenue],tblServiceEvents[Client],B12,tblServiceEvents[Revenue Eligibility],"Eligible") | H12: =IFERROR(G12/COUNTIFS(tblServiceEvents[Client],B12,tblServiceEvents[Revenue Eligibility],"Eligible"),0) | I12: =IFERROR(SUMIFS(tblLedger[Breakdown Amount],tblLedger[Client],B12,tblLedger[Breakdown Confirmed],"Yes")/COUNTIFS(tblLedger[Client],B12,tblLedger[Breakdown Confirmed],"Yes"),0) | J12: 2 | K12: 2 | L12: =IF(E12>1,"Yes","No") | V12: =A22 | W12: =B22 | X12: =E22 | Y12: =F22 | Z12: =G22 | AA12: =H22 | AB12: =I22 | AC12: =L22 | AD12: =C22 | AE12: =G22+(1000-C22)/1000000000 | AF12: =E22+G22/1000000000 | AG12: =IF(E22>1,H22+G22/1000000000,0) | AI12: 46154 | AJ12: 1 | AK12: 1 | AL12: 85 | AM12: 1738 | AN12: 110
A13: CL-002 | B13: Bloomingdale's | C13: =MINIFS(tblServiceEvents[Event #],tblServiceEvents[Client],B13) | D13: =MAXIFS(tblServiceEvents[Event #],tblServiceEvents[Client],B13) | E13: =COUNTIFS(tblServiceEvents[Client],B13,tblServiceEvents[Status],"Completed") | F13: =COUNTIF(tblLedger[Client],B13) | G13: =SUMIFS(tblServiceEvents[Confirmed Revenue],tblServiceEvents[Client],B13,tblServiceEvents[Revenue Eligibility],"Eligible") | H13: =IFERROR(G13/COUNTIFS(tblServiceEvents[Client],B13,tblServiceEvents[Revenue Eligibility],"Eligible"),0) | I13: =IFERROR(SUMIFS(tblLedger[Breakdown Amount],tblLedger[Client],B13,tblLedger[Breakdown Confirmed],"Yes")/COUNTIFS(tblLedger[Client],B13,tblLedger[Breakdown Confirmed],"Yes"),0) | J13: 1 | K13: 1 | L13: =IF(E13>1,"Yes","No") | V13: =A23 | W13: =B23 | X13: =E23 | Y13: =F23 | Z13: =G23 | AA13: =H23 | AB13: =I23 | AC13: =L23 | AD13: =C23 | AE13: =G23+(1000-C23)/1000000000 | AF13: =E23+G23/1000000000 | AG13: =IF(E23>1,H23+G23/1000000000,0) | AI13: 46155 | AJ13: 2 | AK13: 1 | AL13: 50 | AM13: 1788 | AN13: 101
A14: CL-003 | B14: Hampton Inn & Suites | C14: =MINIFS(tblServiceEvents[Event #],tblServiceEvents[Client],B14) | D14: =MAXIFS(tblServiceEvents[Event #],tblServiceEvents[Client],B14) | E14: =COUNTIFS(tblServiceEvents[Client],B14,tblServiceEvents[Status],"Completed") | F14: =COUNTIF(tblLedger[Client],B14) | G14: =SUMIFS(tblServiceEvents[Confirmed Revenue],tblServiceEvents[Client],B14,tblServiceEvents[Revenue Eligibility],"Eligible") | H14: =IFERROR(G14/COUNTIFS(tblServiceEvents[Client],B14,tblServiceEvents[Revenue Eligibility],"Eligible"),0) | I14: =IFERROR(SUMIFS(tblLedger[Breakdown Amount],tblLedger[Client],B14,tblLedger[Breakdown Confirmed],"Yes")/COUNTIFS(tblLedger[Client],B14,tblLedger[Breakdown Confirmed],"Yes"),0) | J14: 2 | K14: 2 | L14: =IF(E14>1,"Yes","No") | V14: =A24 | W14: =B24 | X14: =E24 | Y14: =F24 | Z14: =G24 | AA14: =H24 | AB14: =I24 | AC14: =L24 | AD14: =C24 | AE14: =G24+(1000-C24)/1000000000 | AF14: =E24+G24/1000000000 | AG14: =IF(E24>1,H24+G24/1000000000,0) | AI14: 46156 | AJ14: 1 | AK14: 1 | AL14: 75 | AM14: 1863 | AN14: 116
A15: CL-004 | B15: Davis Polk & Wardwell | C15: =MINIFS(tblServiceEvents[Event #],tblServiceEvents[Client],B15) | D15: =MAXIFS(tblServiceEvents[Event #],tblServiceEvents[Client],B15) | E15: =COUNTIFS(tblServiceEvents[Client],B15,tblServiceEvents[Status],"Completed") | F15: =COUNTIF(tblLedger[Client],B15) | G15: =SUMIFS(tblServiceEvents[Confirmed Revenue],tblServiceEvents[Client],B15,tblServiceEvents[Revenue Eligibility],"Eligible") | H15: =IFERROR(G15/COUNTIFS(tblServiceEvents[Client],B15,tblServiceEvents[Revenue Eligibility],"Eligible"),0) | I15: =IFERROR(SUMIFS(tblLedger[Breakdown Amount],tblLedger[Client],B15,tblLedger[Breakdown Confirmed],"Yes")/COUNTIFS(tblLedger[Client],B15,tblLedger[Breakdown Confirmed],"Yes"),0) | J15: 1 | K15: 1 | L15: =IF(E15>1,"Yes","No") | V15: =A25 | W15: =B25 | X15: =E25 | Y15: =F25 | Z15: =G25 | AA15: =H25 | AB15: =I25 | AC15: =L25 | AD15: =C25 | AE15: =G25+(1000-C25)/1000000000 | AF15: =E25+G25/1000000000 | AG15: =IF(E25>1,H25+G25/1000000000,0) | AI15: 46157 | AJ15: 1 | AK15: 1 | AL15: 45 | AM15: 1908 | AN15: 82.5
A16: CL-005 | B16: Hebrew Home of Greater Washington | C16: =MINIFS(tblServiceEvents[Event #],tblServiceEvents[Client],B16) | D16: =MAXIFS(tblServiceEvents[Event #],tblServiceEvents[Client],B16) | E16: =COUNTIFS(tblServiceEvents[Client],B16,tblServiceEvents[Status],"Completed") | F16: =COUNTIF(tblLedger[Client],B16) | G16: =SUMIFS(tblServiceEvents[Confirmed Revenue],tblServiceEvents[Client],B16,tblServiceEvents[Revenue Eligibility],"Eligible") | H16: =IFERROR(G16/COUNTIFS(tblServiceEvents[Client],B16,tblServiceEvents[Revenue Eligibility],"Eligible"),0) | I16: =IFERROR(SUMIFS(tblLedger[Breakdown Amount],tblLedger[Client],B16,tblLedger[Breakdown Confirmed],"Yes")/COUNTIFS(tblLedger[Client],B16,tblLedger[Breakdown Confirmed],"Yes"),0) | J16: 1 | K16: 1 | L16: =IF(E16>1,"Yes","No") | V16: =A26 | W16: =B26 | X16: =E26 | Y16: =F26 | Z16: =G26 | AA16: =H26 | AB16: =I26 | AC16: =L26 | AD16: =C26 | AE16: =G26+(1000-C26)/1000000000 | AF16: =E26+G26/1000000000 | AG16: =IF(E26>1,H26+G26/1000000000,0) | AI16: 46161 | AJ16: 1 | AK16: 1 | AL16: 50 | AM16: 1958 | AN16: 61
A17: CL-006 | B17: 7-Eleven | C17: =MINIFS(tblServiceEvents[Event #],tblServiceEvents[Client],B17) | D17: =MAXIFS(tblServiceEvents[Event #],tblServiceEvents[Client],B17) | E17: =COUNTIFS(tblServiceEvents[Client],B17,tblServiceEvents[Status],"Completed") | F17: =COUNTIF(tblLedger[Client],B17) | G17: =SUMIFS(tblServiceEvents[Confirmed Revenue],tblServiceEvents[Client],B17,tblServiceEvents[Revenue Eligibility],"Eligible") | H17: =IFERROR(G17/COUNTIFS(tblServiceEvents[Client],B17,tblServiceEvents[Revenue Eligibility],"Eligible"),0) | I17: =IFERROR(SUMIFS(tblLedger[Breakdown Amount],tblLedger[Client],B17,tblLedger[Breakdown Confirmed],"Yes")/COUNTIFS(tblLedger[Client],B17,tblLedger[Breakdown Confirmed],"Yes"),0) | J17: 1 | K17: 3 | L17: =IF(E17>1,"Yes","No") | V17: =A27 | W17: =B27 | X17: =E27 | Y17: =F27 | Z17: =G27 | AA17: =H27 | AB17: =I27 | AC17: =L27 | AD17: =C27 | AE17: =G27+(1000-C27)/1000000000 | AF17: =E27+G27/1000000000 | AG17: =IF(E27>1,H27+G27/1000000000,0) | AI17: 46162 | AJ17: 1 | AK17: 1 | AL17: 106.67 | AM17: 2064.67 | AN17: 65.33
A18: CL-007 | B18: Giant Food Stores | C18: =MINIFS(tblServiceEvents[Event #],tblServiceEvents[Client],B18) | D18: =MAXIFS(tblServiceEvents[Event #],tblServiceEvents[Client],B18) | E18: =COUNTIFS(tblServiceEvents[Client],B18,tblServiceEvents[Status],"Completed") | F18: =COUNTIF(tblLedger[Client],B18) | G18: =SUMIFS(tblServiceEvents[Confirmed Revenue],tblServiceEvents[Client],B18,tblServiceEvents[Revenue Eligibility],"Eligible") | H18: =IFERROR(G18/COUNTIFS(tblServiceEvents[Client],B18,tblServiceEvents[Revenue Eligibility],"Eligible"),0) | I18: =IFERROR(SUMIFS(tblLedger[Breakdown Amount],tblLedger[Client],B18,tblLedger[Breakdown Confirmed],"Yes")/COUNTIFS(tblLedger[Client],B18,tblLedger[Breakdown Confirmed],"Yes"),0) | J18: 2 | K18: 3 | L18: =IF(E18>1,"Yes","No") | V18: =A28 | W18: =B28 | X18: =E28 | Y18: =F28 | Z18: =G28 | AA18: =H28 | AB18: =I28 | AC18: =L28 | AD18: =C28 | AE18: =G28+(1000-C28)/1000000000 | AF18: =E28+G28/1000000000 | AG18: =IF(E28>1,H28+G28/1000000000,0) | AI18: 46163 | AJ18: 2 | AK18: 2 | AL18: 265.83 | AM18: 2330.5 | AN18: 108.5
A19: CL-008 | B19: Food Lion | C19: =MINIFS(tblServiceEvents[Event #],tblServiceEvents[Client],B19) | D19: =MAXIFS(tblServiceEvents[Event #],tblServiceEvents[Client],B19) | E19: =COUNTIFS(tblServiceEvents[Client],B19,tblServiceEvents[Status],"Completed") | F19: =COUNTIF(tblLedger[Client],B19) | G19: =SUMIFS(tblServiceEvents[Confirmed Revenue],tblServiceEvents[Client],B19,tblServiceEvents[Revenue Eligibility],"Eligible") | H19: =IFERROR(G19/COUNTIFS(tblServiceEvents[Client],B19,tblServiceEvents[Revenue Eligibility],"Eligible"),0) | I19: =IFERROR(SUMIFS(tblLedger[Breakdown Amount],tblLedger[Client],B19,tblLedger[Breakdown Confirmed],"Yes")/COUNTIFS(tblLedger[Client],B19,tblLedger[Breakdown Confirmed],"Yes"),0) | J19: 2 | K19: 3 | L19: =IF(E19>1,"Yes","No") | V19: =A29 | W19: =B29 | X19: =E29 | Y19: =F29 | Z19: =G29 | AA19: =H29 | AB19: =I29 | AC19: =L29 | AD19: =C29 | AE19: =G29+(1000-C29)/1000000000 | AF19: =E29+G29/1000000000 | AG19: =IF(E29>1,H29+G29/1000000000,0) | AI19: 46168 | AJ19: 2 | AK19: 2 | AL19: 147.91 | AM19: 2478.41 | AN19: 123.08
A20: CL-009 | B20: Weis Markets | C20: =MINIFS(tblServiceEvents[Event #],tblServiceEvents[Client],B20) | D20: =MAXIFS(tblServiceEvents[Event #],tblServiceEvents[Client],B20) | E20: =COUNTIFS(tblServiceEvents[Client],B20,tblServiceEvents[Status],"Completed") | F20: =COUNTIF(tblLedger[Client],B20) | G20: =SUMIFS(tblServiceEvents[Confirmed Revenue],tblServiceEvents[Client],B20,tblServiceEvents[Revenue Eligibility],"Eligible") | H20: =IFERROR(G20/COUNTIFS(tblServiceEvents[Client],B20,tblServiceEvents[Revenue Eligibility],"Eligible"),0) | I20: =IFERROR(SUMIFS(tblLedger[Breakdown Amount],tblLedger[Client],B20,tblLedger[Breakdown Confirmed],"Yes")/COUNTIFS(tblLedger[Client],B20,tblLedger[Breakdown Confirmed],"Yes"),0) | J20: 2 | K20: 2 | L20: =IF(E20>1,"Yes","No") | V20: =A30 | W20: =B30 | X20: =E30 | Y20: =F30 | Z20: =G30 | AA20: =H30 | AB20: =I30 | AC20: =L30 | AD20: =C30 | AE20: =G30+(1000-C30)/1000000000 | AF20: =E30+G30/1000000000 | AG20: =IF(E30>1,H30+G30/1000000000,0) | AI20: 46169 | AJ20: 2 | AK20: 1 | AL20: 200 | AM20: 2678.41 | AN20: 154.08
A21: CL-010 | B21: Office of MD Senator Chris Van Hollen | C21: =MINIFS(tblServiceEvents[Event #],tblServiceEvents[Client],B21) | D21: =MAXIFS(tblServiceEvents[Event #],tblServiceEvents[Client],B21) | E21: =COUNTIFS(tblServiceEvents[Client],B21,tblServiceEvents[Status],"Completed") | F21: =COUNTIF(tblLedger[Client],B21) | G21: =SUMIFS(tblServiceEvents[Confirmed Revenue],tblServiceEvents[Client],B21,tblServiceEvents[Revenue Eligibility],"Eligible") | H21: =IFERROR(G21/COUNTIFS(tblServiceEvents[Client],B21,tblServiceEvents[Revenue Eligibility],"Eligible"),0) | I21: =IFERROR(SUMIFS(tblLedger[Breakdown Amount],tblLedger[Client],B21,tblLedger[Breakdown Confirmed],"Yes")/COUNTIFS(tblLedger[Client],B21,tblLedger[Breakdown Confirmed],"Yes"),0) | J21: 1 | K21: 1 | L21: =IF(E21>1,"Yes","No") | V21: =A31 | W21: =B31 | X21: =E31 | Y21: =F31 | Z21: =G31 | AA21: =H31 | AB21: =I31 | AC21: =L31 | AD21: =C31 | AE21: =G31+(1000-C31)/1000000000 | AF21: =E31+G31/1000000000 | AG21: =IF(E31>1,H31+G31/1000000000,0) | AI21: 46170 | AJ21: 2 | AK21: 1 | AL21: 175 | AM21: 2853.41 | AN21: 179.08
A22: CL-011 | B22: Residential – Annapolis Neck, MD | C22: =MINIFS(tblServiceEvents[Event #],tblServiceEvents[Client],B22) | D22: =MAXIFS(tblServiceEvents[Event #],tblServiceEvents[Client],B22) | E22: =COUNTIFS(tblServiceEvents[Client],B22,tblServiceEvents[Status],"Completed") | F22: =COUNTIF(tblLedger[Client],B22) | G22: =SUMIFS(tblServiceEvents[Confirmed Revenue],tblServiceEvents[Client],B22,tblServiceEvents[Revenue Eligibility],"Eligible") | H22: =IFERROR(G22/COUNTIFS(tblServiceEvents[Client],B22,tblServiceEvents[Revenue Eligibility],"Eligible"),0) | I22: =IFERROR(SUMIFS(tblLedger[Breakdown Amount],tblLedger[Client],B22,tblLedger[Breakdown Confirmed],"Yes")/COUNTIFS(tblLedger[Client],B22,tblLedger[Breakdown Confirmed],"Yes"),0) | J22: 1 | K22: 1 | L22: =IF(E22>1,"Yes","No") | V22: =A32 | W22: =B32 | X22: =E32 | Y22: =F32 | Z22: =G32 | AA22: =H32 | AB22: =I32 | AC22: =L32 | AD22: =C32 | AE22: =G32+(1000-C32)/1000000000 | AF22: =E32+G32/1000000000 | AG22: =IF(E32>1,H32+G32/1000000000,0) | AI22: 46174 | AJ22: 1 | AK22: 1 | AL22: 320 | AM22: 3173.41 | AN22: 221.75
A23: CL-012 | B23: Verizon | C23: =MINIFS(tblServiceEvents[Event #],tblServiceEvents[Client],B23) | D23: =MAXIFS(tblServiceEvents[Event #],tblServiceEvents[Client],B23) | E23: =COUNTIFS(tblServiceEvents[Client],B23,tblServiceEvents[Status],"Completed") | F23: =COUNTIF(tblLedger[Client],B23) | G23: =SUMIFS(tblServiceEvents[Confirmed Revenue],tblServiceEvents[Client],B23,tblServiceEvents[Revenue Eligibility],"Eligible") | H23: =IFERROR(G23/COUNTIFS(tblServiceEvents[Client],B23,tblServiceEvents[Revenue Eligibility],"Eligible"),0) | I23: =IFERROR(SUMIFS(tblLedger[Breakdown Amount],tblLedger[Client],B23,tblLedger[Breakdown Confirmed],"Yes")/COUNTIFS(tblLedger[Client],B23,tblLedger[Breakdown Confirmed],"Yes"),0) | J23: 1 | K23: 3 | L23: =IF(E23>1,"Yes","No") | V23: =A33 | W23: =B33 | X23: =E33 | Y23: =F33 | Z23: =G33 | AA23: =H33 | AB23: =I33 | AC23: =L33 | AD23: =C33 | AE23: =G33+(1000-C33)/1000000000 | AF23: =E33+G33/1000000000 | AG23: =IF(E33>1,H33+G33/1000000000,0) | AI23: 46175 | AJ23: 1 | AK23: 1 | AL23: 320 | AM23: 3493.41 | AN23: 232.58
... A28: CL-017 | B28: Joint Base Andrews | C28: =MINIFS(tblServiceEvents[Event #],tblServiceEvents[Client],B28) | D28: =MAXIFS(tblServiceEvents[Event #],tblServiceEvents[Client],B28) | E28: =COUNTIFS(tblServiceEvents[Client],B28,tblServiceEvents[Status],"Completed") | F28: =COUNTIF(tblLedger[Client],B28) | G28: =SUMIFS(tblServiceEvents[Confirmed Revenue],tblServiceEvents[Client],B28,tblServiceEvents[Revenue Eligibility],"Eligible") | H28: =IFERROR(G28/COUNTIFS(tblServiceEvents[Client],B28,tblServiceEvents[Revenue Eligibility],"Eligible"),0) | I28: =IFERROR(SUMIFS(tblLedger[Breakdown Amount],tblLedger[Client],B28,tblLedger[Breakdown Confirmed],"Yes")/COUNTIFS(tblLedger[Client],B28,tblLedger[Breakdown Confirmed],"Yes"),0) | J28: 1 | K28: 1 | L28: =IF(E28>1,"Yes","No") | V28: =A38 | W28: =B38 | X28: =E38 | Y28: =F38 | Z28: =G38 | AA28: =H38 | AB28: =I38 | AC28: =L38 | AD28: =C38 | AE28: =G38+(1000-C38)/1000000000 | AF28: =E38+G38/1000000000 | AG28: =IF(E38>1,H38+G38/1000000000,0) | AI28: 46182 | AJ28: 2 | AK28: 2 | AL28: 155 | AM28: 4300.07 | AN28: 161.33
A29: CL-018 | B29: USDA | C29: =MINIFS(tblServiceEvents[Event #],tblServiceEvents[Client],B29) | D29: =MAXIFS(tblServiceEvents[Event #],tblServiceEvents[Client],B29) | E29: =COUNTIFS(tblServiceEvents[Client],B29,tblServiceEvents[Status],"Completed") | F29: =COUNTIF(tblLedger[Client],B29) | G29: =SUMIFS(tblServiceEvents[Confirmed Revenue],tblServiceEvents[Client],B29,tblServiceEvents[Revenue Eligibility],"Eligible") | H29: =IFERROR(G29/COUNTIFS(tblServiceEvents[Client],B29,tblServiceEvents[Revenue Eligibility],"Eligible"),0) | I29: =IFERROR(SUMIFS(tblLedger[Breakdown Amount],tblLedger[Client],B29,tblLedger[Breakdown Confirmed],"Yes")/COUNTIFS(tblLedger[Client],B29,tblLedger[Breakdown Confirmed],"Yes"),0) | J29: 1 | K29: 1 | L29: =IF(E29>1,"Yes","No") | AI29: 46183 | AJ29: 3 | AK29: 3 | AL29: 390 | AM29: 4690.07 | AN29: 180
A30: CL-019 | B30: PepsiCo | C30: =MINIFS(tblServiceEvents[Event #],tblServiceEvents[Client],B30) | D30: =MAXIFS(tblServiceEvents[Event #],tblServiceEvents[Client],B30) | E30: =COUNTIFS(tblServiceEvents[Client],B30,tblServiceEvents[Status],"Completed") | F30: =COUNTIF(tblLedger[Client],B30) | G30: =SUMIFS(tblServiceEvents[Confirmed Revenue],tblServiceEvents[Client],B30,tblServiceEvents[Revenue Eligibility],"Eligible") | H30: =IFERROR(G30/COUNTIFS(tblServiceEvents[Client],B30,tblServiceEvents[Revenue Eligibility],"Eligible"),0) | I30: =IFERROR(SUMIFS(tblLedger[Breakdown Amount],tblLedger[Client],B30,tblLedger[Breakdown Confirmed],"Yes")/COUNTIFS(tblLedger[Client],B30,tblLedger[Breakdown Confirmed],"Yes"),0) | J30: 1 | K30: 1 | L30: =IF(E30>1,"Yes","No") | AI30: 46184 | AJ30: 2 | AK30: 2 | AL30: 95 | AM30: 4785.07 | AN30: 171
A31: CL-020 | B31: TJ Maxx | C31: =MINIFS(tblServiceEvents[Event #],tblServiceEvents[Client],B31) | D31: =MAXIFS(tblServiceEvents[Event #],tblServiceEvents[Client],B31) | E31: =COUNTIFS(tblServiceEvents[Client],B31,tblServiceEvents[Status],"Completed") | F31: =COUNTIF(tblLedger[Client],B31) | G31: =SUMIFS(tblServiceEvents[Confirmed Revenue],tblServiceEvents[Client],B31,tblServiceEvents[Revenue Eligibility],"Eligible") | H31: =IFERROR(G31/COUNTIFS(tblServiceEvents[Client],B31,tblServiceEvents[Revenue Eligibility],"Eligible"),0) | I31: =IFERROR(SUMIFS(tblLedger[Breakdown Amount],tblLedger[Client],B31,tblLedger[Breakdown Confirmed],"Yes")/COUNTIFS(tblLedger[Client],B31,tblLedger[Breakdown Confirmed],"Yes"),0) | J31: 2 | K31: 4 | L31: =IF(E31>1,"Yes","No") | V31: City | W31: Jurisdiction | X31: Events | Y31: Eligible Events | Z31: Revenue | AA31: Avg/Event | AB31: Rank Key | AI31: 46185 | AJ31: 1 | AK31: 1 | AL31: 50 | AM31: 4835.07 | AN31: 152
A32: CL-021 | B32: Hilton Garden Inn | C32: =MINIFS(tblServiceEvents[Event #],tblServiceEvents[Client],B32) | D32: =MAXIFS(tblServiceEvents[Event #],tblServiceEvents[Client],B32) | E32: =COUNTIFS(tblServiceEvents[Client],B32,tblServiceEvents[Status],"Completed") | F32: =COUNTIF(tblLedger[Client],B32) | G32: =SUMIFS(tblServiceEvents[Confirmed Revenue],tblServiceEvents[Client],B32,tblServiceEvents[Revenue Eligibility],"Eligible") | H32: =IFERROR(G32/COUNTIFS(tblServiceEvents[Client],B32,tblServiceEvents[Revenue Eligibility],"Eligible"),0) | I32: =IFERROR(SUMIFS(tblLedger[Breakdown Amount],tblLedger[Client],B32,tblLedger[Breakdown Confirmed],"Yes")/COUNTIFS(tblLedger[Client],B32,tblLedger[Breakdown Confirmed],"Yes"),0) | J32: 2 | K32: 2 | L32: =IF(E32>1,"Yes","No") | V32: Fairfax | W32: VA | X32: 2 | Y32: 2 | Z32: 115 | AA32: 57.5 | AB32: 115 | AI32: 46188 | AJ32: 1 | AK32: 1 | AL32: 123.75 | AM32: 4958.82 | AN32: 162.75
A33: CL-022 | B33: Marshalls | C33: =MINIFS(tblServiceEvents[Event #],tblServiceEvents[Client],B33) | D33: =MAXIFS(tblServiceEvents[Event #],tblServiceEvents[Client],B33) | E33: =COUNTIFS(tblServiceEvents[Client],B33,tblServiceEvents[Status],"Completed") | F33: =COUNTIF(tblLedger[Client],B33) | G33: =SUMIFS(tblServiceEvents[Confirmed Revenue],tblServiceEvents[Client],B33,tblServiceEvents[Revenue Eligibility],"Eligible") | H33: =IFERROR(G33/COUNTIFS(tblServiceEvents[Client],B33,tblServiceEvents[Revenue Eligibility],"Eligible"),0) | I33: =IFERROR(SUMIFS(tblLedger[Breakdown Amount],tblLedger[Client],B33,tblLedger[Breakdown Confirmed],"Yes")/COUNTIFS(tblLedger[Client],B33,tblLedger[Breakdown Confirmed],"Yes"),0) | J33: 1 | K33: 3 | L33: =IF(E33>1,"Yes","No") | V33: Tysons | W33: VA | X33: 2 | Y33: 2 | Z33: 688 | AA33: 344 | AB33: 688 | AI33: 46190 | AJ33: 2 | AK33: 2 | AL33: 218 | AM33: 5176.82 | AN33: 175.35
A34: CL-023 | B34: Baskin-Robbins | C34: =MINIFS(tblServiceEvents[Event #],tblServiceEvents[Client],B34) | D34: =MAXIFS(tblServiceEvents[Event #],tblServiceEvents[Client],B34) | E34: =COUNTIFS(tblServiceEvents[Client],B34,tblServiceEvents[Status],"Completed") | F34: =COUNTIF(tblLedger[Client],B34) | G34: =SUMIFS(tblServiceEvents[Confirmed Revenue],tblServiceEvents[Client],B34,tblServiceEvents[Revenue Eligibility],"Eligible") | H34: =IFERROR(G34/COUNTIFS(tblServiceEvents[Client],B34,tblServiceEvents[Revenue Eligibility],"Eligible"),0) | I34: =IFERROR(SUMIFS(tblLedger[Breakdown Amount],tblLedger[Client],B34,tblLedger[Breakdown Confirmed],"Yes")/COUNTIFS(tblLedger[Client],B34,tblLedger[Breakdown Confirmed],"Yes"),0) | J34: 1 | K34: 1 | L34: =IF(E34>1,"Yes","No") | V34: Frederick | W34: MD | X34: 3 | Y34: 3 | Z34: 483.75 | AA34: 161.25 | AB34: 483.75 | AI34: 46191 | AJ34: 2 | AK34: 2 | AL34: 200 | AM34: 5376.82 | AN34: 137.35
A35: CL-024 | B35: Montpelier Liquors | C35: =MINIFS(tblServiceEvents[Event #],tblServiceEvents[Client],B35) | D35: =MAXIFS(tblServiceEvents[Event #],tblServiceEvents[Client],B35) | E35: =COUNTIFS(tblServiceEvents[Client],B35,tblServiceEvents[Status],"Completed") | F35: =COUNTIF(tblLedger[Client],B35) | G35: =SUMIFS(tblServiceEvents[Confirmed Revenue],tblServiceEvents[Client],B35,tblServiceEvents[Revenue Eligibility],"Eligible") | H35: =IFERROR(G35/COUNTIFS(tblServiceEvents[Client],B35,tblServiceEvents[Revenue Eligibility],"Eligible"),0) | I35: =IFERROR(SUMIFS(tblLedger[Breakdown Amount],tblLedger[Client],B35,tblLedger[Breakdown Confirmed],"Yes")/COUNTIFS(tblLedger[Client],B35,tblLedger[Breakdown Confirmed],"Yes"),0) | J35: 1 | K35: 1 | L35: =IF(E35>1,"Yes","No") | V35: Washington | W35: DC | X35: 10 | Y35: 10 | Z35: 1637.03 | AA35: 163.703 | AB35: 1637.03 | AI35: 46192 | AJ35: 2 | AK35: 2 | AL35: 140 | AM35: 5516.82 | AN35: 146.35
A36: CL-025 | B36: Office of MD Senator Angela Alsobrooks | C36: =MINIFS(tblServiceEvents[Event #],tblServiceEvents[Client],B36) | D36: =MAXIFS(tblServiceEvents[Event #],tblServiceEvents[Client],B36) | E36: =COUNTIFS(tblServiceEvents[Client],B36,tblServiceEvents[Status],"Completed") | F36: =COUNTIF(tblLedger[Client],B36) | G36: =SUMIFS(tblServiceEvents[Confirmed Revenue],tblServiceEvents[Client],B36,tblServiceEvents[Revenue Eligibility],"Eligible") | H36: =IFERROR(G36/COUNTIFS(tblServiceEvents[Client],B36,tblServiceEvents[Revenue Eligibility],"Eligible"),0) | I36: =IFERROR(SUMIFS(tblLedger[Breakdown Amount],tblLedger[Client],B36,tblLedger[Breakdown Confirmed],"Yes")/COUNTIFS(tblLedger[Client],B36,tblLedger[Breakdown Confirmed],"Yes"),0) | J36: 1 | K36: 2 | L36: =IF(E36>1,"Yes","No") | V36: North Bethesda | W36: MD | X36: 4 | Y36: 4 | Z36: 225 | AA36: 56.25 | AB36: 225 | AI36: 46195 | AJ36: 1 | AK36: 1 | AL36: 60 | AM36: 5576.82 | AN36: 148.35
A37: CL-026 | B37: Dunkin | C37: =MINIFS(tblServiceEvents[Event #],tblServiceEvents[Client],B37) | D37: =MAXIFS(tblServiceEvents[Event #],tblServiceEvents[Client],B37) | E37: =COUNTIFS(tblServiceEvents[Client],B37,tblServiceEvents[Status],"Completed") | F37: =COUNTIF(tblLedger[Client],B37) | G37: =SUMIFS(tblServiceEvents[Confirmed Revenue],tblServiceEvents[Client],B37,tblServiceEvents[Revenue Eligibility],"Eligible") | H37: =IFERROR(G37/COUNTIFS(tblServiceEvents[Client],B37,tblServiceEvents[Revenue Eligibility],"Eligible"),0) | I37: =IFERROR(SUMIFS(tblLedger[Breakdown Amount],tblLedger[Client],B37,tblLedger[Breakdown Confirmed],"Yes")/COUNTIFS(tblLedger[Client],B37,tblLedger[Breakdown Confirmed],"Yes"),0) | J37: 1 | K37: 3 | L37: =IF(E37>1,"Yes","No") | V37: Baltimore | W37: MD | X37: 3 | Y37: 1 | Z37: 50 | AA37: 50 | AB37: 50.000003 | AI37: 46196 | AJ37: 1 | AK37: 1 | AL37: 116.24 | AM37: 5693.06 | AN37: 146.85
A38: CL-027 | B38: Carvana | C38: =MINIFS(tblServiceEvents[Event #],tblServiceEvents[Client],B38) | D38: =MAXIFS(tblServiceEvents[Event #],tblServiceEvents[Client],B38) | E38: =COUNTIFS(tblServiceEvents[Client],B38,tblServiceEvents[Status],"Completed") | F38: =COUNTIF(tblLedger[Client],B38) | G38: =SUMIFS(tblServiceEvents[Confirmed Revenue],tblServiceEvents[Client],B38,tblServiceEvents[Revenue Eligibility],"Eligible") | H38: =IFERROR(G38/COUNTIFS(tblServiceEvents[Client],B38,tblServiceEvents[Revenue Eligibility],"Eligible"),0) | I38: =IFERROR(SUMIFS(tblLedger[Breakdown Amount],tblLedger[Client],B38,tblLedger[Breakdown Confirmed],"Yes")/COUNTIFS(tblLedger[Client],B38,tblLedger[Breakdown Confirmed],"Yes"),0) | J38: 1 | K38: 1 | L38: =IF(E38>1,"Yes","No") | V38: Hanover | W38: PA | X38: 1 | Y38: 1 | Z38: 212.5 | AA38: 212.5 | AB38: 212.5 | AI38: 46197 | AJ38: 1 | AK38: 1 | AL38: 132.03 | AM38: 5825.09 | AN38: 129.65
V39: Leesburg | W39: VA | X39: 1 | Y39: 1 | Z39: 157.5 | AA39: 157.5 | AB39: 157.5 | AI39: 46203 | AJ39: 1 | AK39: 1 | AL39: 120 | AM39: 5945.09 | AN39: 113.65
V40: Chambersburg | W40: PA | X40: 1 | Y40: 1 | Z40: 85 | AA40: 85 | AB40: 85.000001 | AI40: 46204 | AJ40: 1 | AK40: 1 | AL40: 120 | AM40: 6065.09 | AN40: 109.65
A41: State / Jurisdiction Summary | J41: Weekday Summary | V41: Rockville | W41: MD | X41: 2 | Y41: 2 | Z41: 146.66 | AA41: 73.33 | AB41: 146.66 | AI41: 46205 | AJ41: 1 | AK41: 1 | AL41: 170.66 | AM41: 6235.75 | AN41: 131.79
A42: Jurisdiction | B42: Events | C42: Eligible Events | D42: Clients | E42: Confirmed Revenue | F42: Avg Revenue / Eligible Event | G42: Revenue Share | H42: Event Share | J42: Weekday | K42: Confirmed Revenue | L42: Eligible Events | M42: Avg Revenue / Event | N42: Active Weeks | O42: Activity Rate | P42: Highest Revenue Event | Q42: Lowest Revenue Event | R42: Rank | V42: Annapolis Neck | W42: MD | X42: 2 | Y42: 1 | Z42: 60 | AA42: 60 | AB42: 60.000002 | AI42: 46209 | AJ42: 2 | AK42: 2 | AL42: 269.24 | AM42: 6504.99 | AN42: 162.39
A43: VA | B43: =COUNTIFS(tblServiceEvents[Jurisdiction],A43,tblServiceEvents[Status],"Completed") | C43: =COUNTIFS(tblServiceEvents[Jurisdiction],A43,tblServiceEvents[Revenue Eligibility],"Eligible") | D43: 6 | E43: =SUMIFS(tblServiceEvents[Confirmed Revenue],tblServiceEvents[Jurisdiction],A43,tblServiceEvents[Revenue Eligibility],"Eligible") | F43: =IFERROR(E43/C43,0) | G43: =IFERROR(E43/$B$7,0) | H43: =IFERROR(B43/$B$6,0) | J43: Monday | K43: =SUMIFS(tblServiceEvents[Confirmed Revenue],tblServiceEvents[Weekday],J43,tblServiceEvents[Revenue Eligibility],"Eligible") | L43: =COUNTIFS(tblServiceEvents[Weekday],J43,tblServiceEvents[Revenue Eligibility],"Eligible") | M43: =IFERROR(K43/L43,0) | N43: 9 | O43: =IFERROR(N43/($B$5+IF(WEEKDAY(MAXIFS(tblServiceEvents[Service Date],tblServiceEvents[Status],"Completed"),2)>=1,1,0)),0) | P43: =MAXIFS(tblServiceEvents[Confirmed Revenue],tblServiceEvents[Weekday],J43,tblServiceEvents[Revenue Eligibility],"Eligible") | Q43: =MINIFS(tblServiceEvents[Confirmed Revenue],tblServiceEvents[Weekday],J43,tblServiceEvents[Revenue Eligibility],"Eligible") | R43: =RANK(K43,$K$43:$K$47,0) | V43: College Park | W43: MD | X43: 1 | Y43: 1 | Z43: 75 | AA43: 75 | AB43: 75.000001 | AI43: 46210 | AJ43: 1 | AK43: 1 | AL43: 250 | AM43: 6754.99 | AN43: 185.98
A44: MD | B44: =COUNTIFS(tblServiceEvents[Jurisdiction],A44,tblServiceEvents[Status],"Completed") | C44: =COUNTIFS(tblServiceEvents[Jurisdiction],A44,tblServiceEvents[Revenue Eligibility],"Eligible") | D44: 21 | E44: =SUMIFS(tblServiceEvents[Confirmed Revenue],tblServiceEvents[Jurisdiction],A44,tblServiceEvents[Revenue Eligibility],"Eligible") | F44: =IFERROR(E44/C44,0) | G44: =IFERROR(E44/$B$7,0) | H44: =IFERROR(B44/$B$6,0) | J44: Tuesday | K44: =SUMIFS(tblServiceEvents[Confirmed Revenue],tblServiceEvents[Weekday],J44,tblServiceEvents[Revenue Eligibility],"Eligible") | L44: =COUNTIFS(tblServiceEvents[Weekday],J44,tblServiceEvents[Revenue Eligibility],"Eligible") | M44: =IFERROR(K44/L44,0) | N44: 11 | O44: =IFERROR(N44/($B$5+IF(WEEKDAY(MAXIFS(tblServiceEvents[Service Date],tblServiceEvents[Status],"Completed"),2)>=2,1,0)),0) | P44: =MAXIFS(tblServiceEvents[Confirmed Revenue],tblServiceEvents[Weekday],J44,tblServiceEvents[Revenue Eligibility],"Eligible") | Q44: =MINIFS(tblServiceEvents[Confirmed Revenue],tblServiceEvents[Weekday],J44,tblServiceEvents[Revenue Eligibility],"Eligible") | R44: =RANK(K44,$K$43:$K$47,0) | V44: Owings Mills | W44: MD | X44: 2 | Y44: 2 | Z44: 165 | AA44: 82.5 | AB44: 165 | AI44: 46211 | AJ44: 1 | AK44: 0 | AL44: 0 | AM44: 6754.99 | AN44: 161.98
A45: DC | B45: =COUNTIFS(tblServiceEvents[Jurisdiction],A45,tblServiceEvents[Status],"Completed") | C45: =COUNTIFS(tblServiceEvents[Jurisdiction],A45,tblServiceEvents[Revenue Eligibility],"Eligible") | D45: 5 | E45: =SUMIFS(tblServiceEvents[Confirmed Revenue],tblServiceEvents[Jurisdiction],A45,tblServiceEvents[Revenue Eligibility],"Eligible") | F45: =IFERROR(E45/C45,0) | G45: =IFERROR(E45/$B$7,0) | H45: =IFERROR(B45/$B$6,0) | J45: Wednesday | K45: =SUMIFS(tblServiceEvents[Confirmed Revenue],tblServiceEvents[Weekday],J45,tblServiceEvents[Revenue Eligibility],"Eligible") | L45: =COUNTIFS(tblServiceEvents[Weekday],J45,tblServiceEvents[Revenue Eligibility],"Eligible") | M45: =IFERROR(K45/L45,0) | N45: 11 | O45: =IFERROR(N45/($B$5+IF(WEEKDAY(MAXIFS(tblServiceEvents[Service Date],tblServiceEvents[Status],"Completed"),2)>=3,1,0)),0) | P45: =MAXIFS(tblServiceEvents[Confirmed Revenue],tblServiceEvents[Weekday],J45,tblServiceEvents[Revenue Eligibility],"Eligible") | Q45: =MINIFS(tblServiceEvents[Confirmed Revenue],tblServiceEvents[Weekday],J45,tblServiceEvents[Revenue Eligibility],"Eligible") | R45: =RANK(K45,$K$43:$K$47,0) | V45: Red Lion | W45: PA | X45: 1 | Y45: 1 | Z45: 112.5 | AA45: 112.5 | AB45: 112.5 | AI45: 46212 | AJ45: 2 | AK45: 2 | AL45: 295.82 | AM45: 7050.81 | AN45: 197.14
A46: PA | B46: =COUNTIFS(tblServiceEvents[Jurisdiction],A46,tblServiceEvents[Status],"Completed") | C46: =COUNTIFS(tblServiceEvents[Jurisdiction],A46,tblServiceEvents[Revenue Eligibility],"Eligible") | D46: 2 | E46: =SUMIFS(tblServiceEvents[Confirmed Revenue],tblServiceEvents[Jurisdiction],A46,tblServiceEvents[Revenue Eligibility],"Eligible") | F46: =IFERROR(E46/C46,0) | G46: =IFERROR(E46/$B$7,0) | H46: =IFERROR(B46/$B$6,0) | J46: Thursday | K46: =SUMIFS(tblServiceEvents[Confirmed Revenue],tblServiceEvents[Weekday],J46,tblServiceEvents[Revenue Eligibility],"Eligible") | L46: =COUNTIFS(tblServiceEvents[Weekday],J46,tblServiceEvents[Revenue Eligibility],"Eligible") | M46: =IFERROR(K46/L46,0) | N46: 10 | O46: =IFERROR(N46/($B$5+IF(WEEKDAY(MAXIFS(tblServiceEvents[Service Date],tblServiceEvents[Status],"Completed"),2)>=4,1,0)),0) | P46: =MAXIFS(tblServiceEvents[Confirmed Revenue],tblServiceEvents[Weekday],J46,tblServiceEvents[Revenue Eligibility],"Eligible") | Q46: =MINIFS(tblServiceEvents[Confirmed Revenue],tblServiceEvents[Weekday],J46,tblServiceEvents[Revenue Eligibility],"Eligible") | R46: =RANK(K46,$K$43:$K$47,0) | V46: Middle River | W46: MD | X46: 1 | Y46: 1 | Z46: 97.91 | AA46: 97.91 | AB46: 97.910001 | AI46: 46216 | AJ46: 3 | AK46: 0 | AL46: 0 | AM46: 7050.81 | AN46: 163.01
A47: WV | B47: =COUNTIFS(tblServiceEvents[Jurisdiction],A47,tblServiceEvents[Status],"Completed") | C47: =COUNTIFS(tblServiceEvents[Jurisdiction],A47,tblServiceEvents[Revenue Eligibility],"Eligible") | D47: 1 | E47: =SUMIFS(tblServiceEvents[Confirmed Revenue],tblServiceEvents[Jurisdiction],A47,tblServiceEvents[Revenue Eligibility],"Eligible") | F47: =IFERROR(E47/C47,0) | G47: =IFERROR(E47/$B$7,0) | H47: =IFERROR(B47/$B$6,0) | J47: Friday | K47: =SUMIFS(tblServiceEvents[Confirmed Revenue],tblServiceEvents[Weekday],J47,tblServiceEvents[Revenue Eligibility],"Eligible") | L47: =COUNTIFS(tblServiceEvents[Weekday],J47,tblServiceEvents[Revenue Eligibility],"Eligible") | M47: =IFERROR(K47/L47,0) | N47: 5 | O47: =IFERROR(N47/($B$5+IF(WEEKDAY(MAXIFS(tblServiceEvents[Service Date],tblServiceEvents[Status],"Completed"),2)>=5,1,0)),0) | P47: =MAXIFS(tblServiceEvents[Confirmed Revenue],tblServiceEvents[Weekday],J47,tblServiceEvents[Revenue Eligibility],"Eligible") | Q47: =MINIFS(tblServiceEvents[Confirmed Revenue],tblServiceEvents[Weekday],J47,tblServiceEvents[Revenue Eligibility],"Eligible") | R47: =RANK(K47,$K$43:$K$47,0) | V47: Gaithersburg | W47: MD | X47: 2 | Y47: 1 | Z47: 50 | AA47: 50 | AB47: 50.000002 | AI47: 46217 | AJ47: 2 | AK47: 1 | AL47: 183.74 | AM47: 7234.55 | AN47: 145.91
V48: Andrews AFB | W48: MD | X48: 1 | Y48: 0 | Z48: 0 | AA48: 0 | AB48: 1e-06 | AI48: Workweek | AJ48: Events | AK48: Eligible Events | AL48: Weekly Revenue | AM48: Running Revenue
V49: Cheverly | W49: MD | X49: 1 | Y49: 0 | Z49: 0 | AA49: 0 | AB49: 1e-06 | AI49: 1 | AJ49: 5 | AK49: 5 | AL49: 1008 | AM49: 1008
A50: MY_MONTH Summary | V50: Annapolis | W50: MD | X50: 2 | Y50: 2 | Z50: 160 | AA50: 80 | AB50: 160 | AI50: 2 | AJ50: 4 | AK50: 3 | AL50: 275 | AM50: 1283
A51: MY_MONTH | B51: Events | C51: Eligible Events | D51: Clients | E51: Jurisdictions | F51: Confirmed Revenue | G51: Avg Revenue / Eligible Event | V51: Dunkirk | W51: MD | X51: 1 | Y51: 1 | Z51: 70 | AA51: 70 | AB51: 70.000001 | AI51: 3 | AJ51: 1 | AK51: 1 | AL51: 212.5 | AM51: 1495.5
A52: MY_MONTH 1 | B52: =COUNTIFS(tblServiceEvents[MY_MONTH],A52,tblServiceEvents[Status],"Completed") | C52: =COUNTIFS(tblServiceEvents[MY_MONTH],A52,tblServiceEvents[Revenue Eligibility],"Eligible") | D52: 15 | E52: 4 | F52: =SUMIFS(tblServiceEvents[Confirmed Revenue],tblServiceEvents[MY_MONTH],A52,tblServiceEvents[Revenue Eligibility],"Eligible") | G52: =IFERROR(F52/C52,0) | V52: Edgewood | W52: MD | X52: 1 | Y52: 1 | Z52: 65 | AA52: 65 | AB52: 65.000001 | AI52: 4 | AJ52: 6 | AK52: 5 | AL52: 412.5 | AM52: 1908
A53: MY_MONTH 2 | B53: =COUNTIFS(tblServiceEvents[MY_MONTH],A53,tblServiceEvents[Status],"Completed") | C53: =COUNTIFS(tblServiceEvents[MY_MONTH],A53,tblServiceEvents[Revenue Eligibility],"Eligible") | D53: 18 | E53: 3 | F53: =SUMIFS(tblServiceEvents[Confirmed Revenue],tblServiceEvents[MY_MONTH],A53,tblServiceEvents[Revenue Eligibility],"Eligible") | G53: =IFERROR(F53/C53,0) | V53: Sterling | W53: VA | X53: 1 | Y53: 1 | Z53: 90 | AA53: 90 | AB53: 90.000001 | AI53: 5 | AJ53: 4 | AK53: 4 | AL53: 422.5 | AM53: 2330.5
A54: MY_MONTH 3 | B54: =COUNTIFS(tblServiceEvents[MY_MONTH],A54,tblServiceEvents[Status],"Completed") | C54: =COUNTIFS(tblServiceEvents[MY_MONTH],A54,tblServiceEvents[Revenue Eligibility],"Eligible") | D54: 9 | E54: 3 | F54: =SUMIFS(tblServiceEvents[Confirmed Revenue],tblServiceEvents[MY_MONTH],A54,tblServiceEvents[Revenue Eligibility],"Eligible") | G54: =IFERROR(F54/C54,0) | V54: Lanham | W54: MD | X54: 2 | Y54: 2 | Z54: 290 | AA54: 145 | AB54: 290 | AI54: 6 | AJ54: 6 | AK54: 4 | AL54: 522.91 | AM54: 2853.41
V55: Falls Church | W55: VA | X55: 1 | Y55: 1 | Z55: 45 | AA55: 45 | AB55: 45.000001 | AI55: 7 | AJ55: 8 | AK55: 8 | AL55: 1221.66 | AM55: 4075.07
V56: Ellicott City | W56: MD | X56: 1 | Y56: 1 | Z56: 50 | AA56: 50 | AB56: 50.000001 | AI56: 8 | AJ56: 9 | AK56: 9 | AL56: 760 | AM56: 4835.07
A57: Barrister Leaderboards | V57: Laurel | W57: MD | X57: 3 | Y57: 3 | Z57: 284.74 | AA57: 94.913333 | AB57: 284.74 | AI57: 9 | AJ57: 7 | AK57: 7 | AL57: 681.75 | AM57: 5516.82
V58: Bowie | W58: MD | X58: 1 | Y58: 1 | Z58: 130 | AA58: 130 | AB58: 130 | AI58: 10 | AJ58: 3 | AK58: 3 | AL58: 308.27 | AM58: 5825.09
V59: Callaway | W59: MD | X59: 1 | Y59: 1 | Z59: 90 | AA59: 90 | AB59: 90.000001 | AI59: 11 | AJ59: 3 | AK59: 3 | AL59: 410.66 | AM59: 6235.75
A60: Top Clients — Confirmed Revenue | H60: Most Repeat Clients | O60: Best Client Average / Event (2+ Events) | V60: Upper Marlboro | W60: MD | X60: 1 | Y60: 1 | Z60: 116.24 | AA60: 116.24 | AB60: 116.24 | AI60: 12 | AJ60: 6 | AK60: 5 | AL60: 815.06 | AM60: 7050.81
A61: Rank | B61: Client | C61: Revenue | D61: Events | E61: Avg/Event | F61: Work Orders | H61: Rank | I61: Client | J61: Events | K61: Revenue | L61: Avg/Event | M61: First Event | O61: Rank | P61: Client | Q61: Avg/Event | R61: Events | S61: Revenue | T61: Avg/WO | V61: Largo | W61: MD | X61: 1 | Y61: 1 | Z61: 120 | AA61: 120 | AB61: 120 | AI61: 13 | AJ61: 5 | AK61: 1 | AL61: 183.74 | AM61: 7234.55
A62: 1 | B62: =INDEX(tblLeaderboardClients[Client],MATCH(LARGE(tblLeaderboardClients[Revenue Key],A62),tblLeaderboardClients[Revenue Key],0)) | C62: =INDEX(tblLeaderboardClients[Revenue],MATCH(LARGE(tblLeaderboardClients[Revenue Key],A62),tblLeaderboardClients[Revenue Key],0)) | D62: =INDEX(tblLeaderboardClients[Events],MATCH(LARGE(tblLeaderboardClients[Revenue Key],A62),tblLeaderboardClients[Revenue Key],0)) | E62: =INDEX(tblLeaderboardClients[Avg/Event],MATCH(LARGE(tblLeaderboardClients[Revenue Key],A62),tblLeaderboardClients[Revenue Key],0)) | F62: =INDEX(tblLeaderboardClients[Work Orders],MATCH(LARGE(tblLeaderboardClients[Revenue Key],A62),tblLeaderboardClients[Revenue Key],0)) | H62: 1 | I62: =INDEX(tblLeaderboardClients[Client],MATCH(LARGE(tblLeaderboardClients[Repeat Key],H62),tblLeaderboardClients[Repeat Key],0)) | J62: =INDEX(tblLeaderboardClients[Events],MATCH(LARGE(tblLeaderboardClients[Repeat Key],H62),tblLeaderboardClients[Repeat Key],0)) | K62: =INDEX(tblLeaderboardClients[Revenue],MATCH(LARGE(tblLeaderboardClients[Repeat Key],H62),tblLeaderboardClients[Repeat Key],0)) | L62: =INDEX(tblLeaderboardClients[Avg/Event],MATCH(LARGE(tblLeaderboardClients[Repeat Key],H62),tblLeaderboardClients[Repeat Key],0)) | M62: =INDEX(tblLeaderboardClients[First Event],MATCH(LARGE(tblLeaderboardClients[Repeat Key],H62),tblLeaderboardClients[Repeat Key],0)) | O62: 1 | P62: =INDEX(tblLeaderboardClients[Client],MATCH(LARGE(tblLeaderboardClients[Avg Key],O62),tblLeaderboardClients[Avg Key],0)) | Q62: =INDEX(tblLeaderboardClients[Avg/Event],MATCH(LARGE(tblLeaderboardClients[Avg Key],O62),tblLeaderboardClients[Avg Key],0)) | R62: =INDEX(tblLeaderboardClients[Events],MATCH(LARGE(tblLeaderboardClients[Avg Key],O62),tblLeaderboardClients[Avg Key],0)) | S62: =INDEX(tblLeaderboardClients[Revenue],MATCH(LARGE(tblLeaderboardClients[Avg Key],O62),tblLeaderboardClients[Avg Key],0)) | T62: =INDEX(tblLeaderboardClients[Avg/WO],MATCH(LARGE(tblLeaderboardClients[Avg Key],O62),tblLeaderboardClients[Avg Key],0)) | V62: Reisterstown | W62: MD | X62: 1 | Y62: 1 | Z62: 170.66 | AA62: 170.66 | AB62: 170.66
A63: 2 | B63: =INDEX(tblLeaderboardClients[Client],MATCH(LARGE(tblLeaderboardClients[Revenue Key],A63),tblLeaderboardClients[Revenue Key],0)) | C63: =INDEX(tblLeaderboardClients[Revenue],MATCH(LARGE(tblLeaderboardClients[Revenue Key],A63),tblLeaderboardClients[Revenue Key],0)) | D63: =INDEX(tblLeaderboardClients[Events],MATCH(LARGE(tblLeaderboardClients[Revenue Key],A63),tblLeaderboardClients[Revenue Key],0)) | E63: =INDEX(tblLeaderboardClients[Avg/Event],MATCH(LARGE(tblLeaderboardClients[Revenue Key],A63),tblLeaderboardClients[Revenue Key],0)) | F63: =INDEX(tblLeaderboardClients[Work Orders],MATCH(LARGE(tblLeaderboardClients[Revenue Key],A63),tblLeaderboardClients[Revenue Key],0)) | H63: 2 | I63: =INDEX(tblLeaderboardClients[Client],MATCH(LARGE(tblLeaderboardClients[Repeat Key],H63),tblLeaderboardClients[Repeat Key],0)) | J63: =INDEX(tblLeaderboardClients[Events],MATCH(LARGE(tblLeaderboardClients[Repeat Key],H63),tblLeaderboardClients[Repeat Key],0)) | K63: =INDEX(tblLeaderboardClients[Revenue],MATCH(LARGE(tblLeaderboardClients[Repeat Key],H63),tblLeaderboardClients[Repeat Key],0)) | L63: =INDEX(tblLeaderboardClients[Avg/Event],MATCH(LARGE(tblLeaderboardClients[Repeat Key],H63),tblLeaderboardClients[Repeat Key],0)) | M63: =INDEX(tblLeaderboardClients[First Event],MATCH(LARGE(tblLeaderboardClients[Repeat Key],H63),tblLeaderboardClients[Repeat Key],0)) | O63: 2 | P63: =INDEX(tblLeaderboardClients[Client],MATCH(LARGE(tblLeaderboardClients[Avg Key],O63),tblLeaderboardClients[Avg Key],0)) | Q63: =INDEX(tblLeaderboardClients[Avg/Event],MATCH(LARGE(tblLeaderboardClients[Avg Key],O63),tblLeaderboardClients[Avg Key],0)) | R63: =INDEX(tblLeaderboardClients[Events],MATCH(LARGE(tblLeaderboardClients[Avg Key],O63),tblLeaderboardClients[Avg Key],0)) | S63: =INDEX(tblLeaderboardClients[Revenue],MATCH(LARGE(tblLeaderboardClients[Avg Key],O63),tblLeaderboardClients[Avg Key],0)) | T63: =INDEX(tblLeaderboardClients[Avg/WO],MATCH(LARGE(tblLeaderboardClients[Avg Key],O63),tblLeaderboardClients[Avg Key],0)) | V63: Lutherville | W63: MD | X63: 1 | Y63: 1 | Z63: 202.5 | AA63: 202.5 | AB63: 202.5 | AI63: Client Type | AJ63: Clients
A64: 3 | B64: =INDEX(tblLeaderboardClients[Client],MATCH(LARGE(tblLeaderboardClients[Revenue Key],A64),tblLeaderboardClients[Revenue Key],0)) | C64: =INDEX(tblLeaderboardClients[Revenue],MATCH(LARGE(tblLeaderboardClients[Revenue Key],A64),tblLeaderboardClients[Revenue Key],0)) | D64: =INDEX(tblLeaderboardClients[Events],MATCH(LARGE(tblLeaderboardClients[Revenue Key],A64),tblLeaderboardClients[Revenue Key],0)) | E64: =INDEX(tblLeaderboardClients[Avg/Event],MATCH(LARGE(tblLeaderboardClients[Revenue Key],A64),tblLeaderboardClients[Revenue Key],0)) | F64: =INDEX(tblLeaderboardClients[Work Orders],MATCH(LARGE(tblLeaderboardClients[Revenue Key],A64),tblLeaderboardClients[Revenue Key],0)) | H64: 3 | I64: =INDEX(tblLeaderboardClients[Client],MATCH(LARGE(tblLeaderboardClients[Repeat Key],H64),tblLeaderboardClients[Repeat Key],0)) | J64: =INDEX(tblLeaderboardClients[Events],MATCH(LARGE(tblLeaderboardClients[Repeat Key],H64),tblLeaderboardClients[Repeat Key],0)) | K64: =INDEX(tblLeaderboardClients[Revenue],MATCH(LARGE(tblLeaderboardClients[Repeat Key],H64),tblLeaderboardClients[Repeat Key],0)) | L64: =INDEX(tblLeaderboardClients[Avg/Event],MATCH(LARGE(tblLeaderboardClients[Repeat Key],H64),tblLeaderboardClients[Repeat Key],0)) | M64: =INDEX(tblLeaderboardClients[First Event],MATCH(LARGE(tblLeaderboardClients[Repeat Key],H64),tblLeaderboardClients[Repeat Key],0)) | O64: 3 | P64: =INDEX(tblLeaderboardClients[Client],MATCH(LARGE(tblLeaderboardClients[Avg Key],O64),tblLeaderboardClients[Avg Key],0)) | Q64: =INDEX(tblLeaderboardClients[Avg/Event],MATCH(LARGE(tblLeaderboardClients[Avg Key],O64),tblLeaderboardClients[Avg Key],0)) | R64: =INDEX(tblLeaderboardClients[Events],MATCH(LARGE(tblLeaderboardClients[Avg Key],O64),tblLeaderboardClients[Avg Key],0)) | S64: =INDEX(tblLeaderboardClients[Revenue],MATCH(LARGE(tblLeaderboardClients[Avg Key],O64),tblLeaderboardClients[Avg Key],0)) | T64: =INDEX(tblLeaderboardClients[Avg/WO],MATCH(LARGE(tblLeaderboardClients[Avg Key],O64),tblLeaderboardClients[Avg Key],0)) | V64: Aberdeen | W64: MD | X64: 2 | Y64: 2 | Z64: 433.74 | AA64: 216.87 | AB64: 433.74 | AI64: Repeat | AJ64: 19
A65: 4 | B65: =INDEX(tblLeaderboardClients[Client],MATCH(LARGE(tblLeaderboardClients[Revenue Key],A65),tblLeaderboardClients[Revenue Key],0)) | C65: =INDEX(tblLeaderboardClients[Revenue],MATCH(LARGE(tblLeaderboardClients[Revenue Key],A65),tblLeaderboardClients[Revenue Key],0)) | D65: =INDEX(tblLeaderboardClients[Events],MATCH(LARGE(tblLeaderboardClients[Revenue Key],A65),tblLeaderboardClients[Revenue Key],0)) | E65: =INDEX(tblLeaderboardClients[Avg/Event],MATCH(LARGE(tblLeaderboardClients[Revenue Key],A65),tblLeaderboardClients[Revenue Key],0)) | F65: =INDEX(tblLeaderboardClients[Work Orders],MATCH(LARGE(tblLeaderboardClients[Revenue Key],A65),tblLeaderboardClients[Revenue Key],0)) | H65: 4 | I65: =INDEX(tblLeaderboardClients[Client],MATCH(LARGE(tblLeaderboardClients[Repeat Key],H65),tblLeaderboardClients[Repeat Key],0)) | J65: =INDEX(tblLeaderboardClients[Events],MATCH(LARGE(tblLeaderboardClients[Repeat Key],H65),tblLeaderboardClients[Repeat Key],0)) | K65: =INDEX(tblLeaderboardClients[Revenue],MATCH(LARGE(tblLeaderboardClients[Repeat Key],H65),tblLeaderboardClients[Repeat Key],0)) | L65: =INDEX(tblLeaderboardClients[Avg/Event],MATCH(LARGE(tblLeaderboardClients[Repeat Key],H65),tblLeaderboardClients[Repeat Key],0)) | M65: =INDEX(tblLeaderboardClients[First Event],MATCH(LARGE(tblLeaderboardClients[Repeat Key],H65),tblLeaderboardClients[Repeat Key],0)) | O65: 4 | P65: =INDEX(tblLeaderboardClients[Client],MATCH(LARGE(tblLeaderboardClients[Avg Key],O65),tblLeaderboardClients[Avg Key],0)) | Q65: =INDEX(tblLeaderboardClients[Avg/Event],MATCH(LARGE(tblLeaderboardClients[Avg Key],O65),tblLeaderboardClients[Avg Key],0)) | R65: =INDEX(tblLeaderboardClients[Events],MATCH(LARGE(tblLeaderboardClients[Avg Key],O65),tblLeaderboardClients[Avg Key],0)) | S65: =INDEX(tblLeaderboardClients[Revenue],MATCH(LARGE(tblLeaderboardClients[Avg Key],O65),tblLeaderboardClients[Avg Key],0)) | T65: =INDEX(tblLeaderboardClients[Avg/WO],MATCH(LARGE(tblLeaderboardClients[Avg Key],O65),tblLeaderboardClients[Avg Key],0)) | V65: Germantown | W65: MD | X65: 1 | Y65: 1 | Z65: 194.99 | AA65: 194.99 | AB65: 194.99 | AI65: One-Time | AJ65: 8
A66: 5 | B66: =INDEX(tblLeaderboardClients[Client],MATCH(LARGE(tblLeaderboardClients[Revenue Key],A66),tblLeaderboardClients[Revenue Key],0)) | C66: =INDEX(tblLeaderboardClients[Revenue],MATCH(LARGE(tblLeaderboardClients[Revenue Key],A66),tblLeaderboardClients[Revenue Key],0)) | D66: =INDEX(tblLeaderboardClients[Events],MATCH(LARGE(tblLeaderboardClients[Revenue Key],A66),tblLeaderboardClients[Revenue Key],0)) | E66: =INDEX(tblLeaderboardClients[Avg/Event],MATCH(LARGE(tblLeaderboardClients[Revenue Key],A66),tblLeaderboardClients[Revenue Key],0)) | F66: =INDEX(tblLeaderboardClients[Work Orders],MATCH(LARGE(tblLeaderboardClients[Revenue Key],A66),tblLeaderboardClients[Revenue Key],0)) | H66: 5 | I66: =INDEX(tblLeaderboardClients[Client],MATCH(LARGE(tblLeaderboardClients[Repeat Key],H66),tblLeaderboardClients[Repeat Key],0)) | J66: =INDEX(tblLeaderboardClients[Events],MATCH(LARGE(tblLeaderboardClients[Repeat Key],H66),tblLeaderboardClients[Repeat Key],0)) | K66: =INDEX(tblLeaderboardClients[Revenue],MATCH(LARGE(tblLeaderboardClients[Repeat Key],H66),tblLeaderboardClients[Repeat Key],0)) | L66: =INDEX(tblLeaderboardClients[Avg/Event],MATCH(LARGE(tblLeaderboardClients[Repeat Key],H66),tblLeaderboardClients[Repeat Key],0)) | M66: =INDEX(tblLeaderboardClients[First Event],MATCH(LARGE(tblLeaderboardClients[Repeat Key],H66),tblLeaderboardClients[Repeat Key],0)) | O66: 5 | P66: =INDEX(tblLeaderboardClients[Client],MATCH(LARGE(tblLeaderboardClients[Avg Key],O66),tblLeaderboardClients[Avg Key],0)) | Q66: =INDEX(tblLeaderboardClients[Avg/Event],MATCH(LARGE(tblLeaderboardClients[Avg Key],O66),tblLeaderboardClients[Avg Key],0)) | R66: =INDEX(tblLeaderboardClients[Events],MATCH(LARGE(tblLeaderboardClients[Avg Key],O66),tblLeaderboardClients[Avg Key],0)) | S66: =INDEX(tblLeaderboardClients[Revenue],MATCH(LARGE(tblLeaderboardClients[Avg Key],O66),tblLeaderboardClients[Avg Key],0)) | T66: =INDEX(tblLeaderboardClients[Avg/WO],MATCH(LARGE(tblLeaderboardClients[Avg Key],O66),tblLeaderboardClients[Avg Key],0)) | V66: Martinsburg | W66: WV | X66: 1 | Y66: 1 | Z66: 100.83 | AA66: 100.83 | AB66: 100.83
A67: 6 | B67: =INDEX(tblLeaderboardClients[Client],MATCH(LARGE(tblLeaderboardClients[Revenue Key],A67),tblLeaderboardClients[Revenue Key],0)) | C67: =INDEX(tblLeaderboardClients[Revenue],MATCH(LARGE(tblLeaderboardClients[Revenue Key],A67),tblLeaderboardClients[Revenue Key],0)) | D67: =INDEX(tblLeaderboardClients[Events],MATCH(LARGE(tblLeaderboardClients[Revenue Key],A67),tblLeaderboardClients[Revenue Key],0)) | E67: =INDEX(tblLeaderboardClients[Avg/Event],MATCH(LARGE(tblLeaderboardClients[Revenue Key],A67),tblLeaderboardClients[Revenue Key],0)) | F67: =INDEX(tblLeaderboardClients[Work Orders],MATCH(LARGE(tblLeaderboardClients[Revenue Key],A67),tblLeaderboardClients[Revenue Key],0)) | H67: 6 | I67: =INDEX(tblLeaderboardClients[Client],MATCH(LARGE(tblLeaderboardClients[Repeat Key],H67),tblLeaderboardClients[Repeat Key],0)) | J67: =INDEX(tblLeaderboardClients[Events],MATCH(LARGE(tblLeaderboardClients[Repeat Key],H67),tblLeaderboardClients[Repeat Key],0)) | K67: =INDEX(tblLeaderboardClients[Revenue],MATCH(LARGE(tblLeaderboardClients[Repeat Key],H67),tblLeaderboardClients[Repeat Key],0)) | L67: =INDEX(tblLeaderboardClients[Avg/Event],MATCH(LARGE(tblLeaderboardClients[Repeat Key],H67),tblLeaderboardClients[Repeat Key],0)) | M67: =INDEX(tblLeaderboardClients[First Event],MATCH(LARGE(tblLeaderboardClients[Repeat Key],H67),tblLeaderboardClients[Repeat Key],0)) | O67: 6 | P67: =INDEX(tblLeaderboardClients[Client],MATCH(LARGE(tblLeaderboardClients[Avg Key],O67),tblLeaderboardClients[Avg Key],0)) | Q67: =INDEX(tblLeaderboardClients[Avg/Event],MATCH(LARGE(tblLeaderboardClients[Avg Key],O67),tblLeaderboardClients[Avg Key],0)) | R67: =INDEX(tblLeaderboardClients[Events],MATCH(LARGE(tblLeaderboardClients[Avg Key],O67),tblLeaderboardClients[Avg Key],0)) | S67: =INDEX(tblLeaderboardClients[Revenue],MATCH(LARGE(tblLeaderboardClients[Avg Key],O67),tblLeaderboardClients[Avg Key],0)) | T67: =INDEX(tblLeaderboardClients[Avg/WO],MATCH(LARGE(tblLeaderboardClients[Avg Key],O67),tblLeaderboardClients[Avg Key],0)) | V67: Cockeysville | W67: MD | X67: 1 | Y67: 0 | Z67: 0 | AA67: 0 | AB67: 1e-06
A68: 7 | B68: =INDEX(tblLeaderboardClients[Client],MATCH(LARGE(tblLeaderboardClients[Revenue Key],A68),tblLeaderboardClients[Revenue Key],0)) | C68: =INDEX(tblLeaderboardClients[Revenue],MATCH(LARGE(tblLeaderboardClients[Revenue Key],A68),tblLeaderboardClients[Revenue Key],0)) | D68: =INDEX(tblLeaderboardClients[Events],MATCH(LARGE(tblLeaderboardClients[Revenue Key],A68),tblLeaderboardClients[Revenue Key],0)) | E68: =INDEX(tblLeaderboardClients[Avg/Event],MATCH(LARGE(tblLeaderboardClients[Revenue Key],A68),tblLeaderboardClients[Revenue Key],0)) | F68: =INDEX(tblLeaderboardClients[Work Orders],MATCH(LARGE(tblLeaderboardClients[Revenue Key],A68),tblLeaderboardClients[Revenue Key],0)) | H68: 7 | I68: =INDEX(tblLeaderboardClients[Client],MATCH(LARGE(tblLeaderboardClients[Repeat Key],H68),tblLeaderboardClients[Repeat Key],0)) | J68: =INDEX(tblLeaderboardClients[Events],MATCH(LARGE(tblLeaderboardClients[Repeat Key],H68),tblLeaderboardClients[Repeat Key],0)) | K68: =INDEX(tblLeaderboardClients[Revenue],MATCH(LARGE(tblLeaderboardClients[Repeat Key],H68),tblLeaderboardClients[Repeat Key],0)) | L68: =INDEX(tblLeaderboardClients[Avg/Event],MATCH(LARGE(tblLeaderboardClients[Repeat Key],H68),tblLeaderboardClients[Repeat Key],0)) | M68: =INDEX(tblLeaderboardClients[First Event],MATCH(LARGE(tblLeaderboardClients[Repeat Key],H68),tblLeaderboardClients[Repeat Key],0)) | O68: 7 | P68: =INDEX(tblLeaderboardClients[Client],MATCH(LARGE(tblLeaderboardClients[Avg Key],O68),tblLeaderboardClients[Avg Key],0)) | Q68: =INDEX(tblLeaderboardClients[Avg/Event],MATCH(LARGE(tblLeaderboardClients[Avg Key],O68),tblLeaderboardClients[Avg Key],0)) | R68: =INDEX(tblLeaderboardClients[Events],MATCH(LARGE(tblLeaderboardClients[Avg Key],O68),tblLeaderboardClients[Avg Key],0)) | S68: =INDEX(tblLeaderboardClients[Revenue],MATCH(LARGE(tblLeaderboardClients[Avg Key],O68),tblLeaderboardClients[Avg Key],0)) | T68: =INDEX(tblLeaderboardClients[Avg/WO],MATCH(LARGE(tblLeaderboardClients[Avg Key],O68),tblLeaderboardClients[Avg Key],0)) | V68: Hagerstown | W68: MD | X68: 1 | Y68: 0 | Z68: 0 | AA68: 0 | AB68: 1e-06
A69: 8 | B69: =INDEX(tblLeaderboardClients[Client],MATCH(LARGE(tblLeaderboardClients[Revenue Key],A69),tblLeaderboardClients[Revenue Key],0)) | C69: =INDEX(tblLeaderboardClients[Revenue],MATCH(LARGE(tblLeaderboardClients[Revenue Key],A69),tblLeaderboardClients[Revenue Key],0)) | D69: =INDEX(tblLeaderboardClients[Events],MATCH(LARGE(tblLeaderboardClients[Revenue Key],A69),tblLeaderboardClients[Revenue Key],0)) | E69: =INDEX(tblLeaderboardClients[Avg/Event],MATCH(LARGE(tblLeaderboardClients[Revenue Key],A69),tblLeaderboardClients[Revenue Key],0)) | F69: =INDEX(tblLeaderboardClients[Work Orders],MATCH(LARGE(tblLeaderboardClients[Revenue Key],A69),tblLeaderboardClients[Revenue Key],0)) | H69: 8 | I69: =INDEX(tblLeaderboardClients[Client],MATCH(LARGE(tblLeaderboardClients[Repeat Key],H69),tblLeaderboardClients[Repeat Key],0)) | J69: =INDEX(tblLeaderboardClients[Events],MATCH(LARGE(tblLeaderboardClients[Repeat Key],H69),tblLeaderboardClients[Repeat Key],0)) | K69: =INDEX(tblLeaderboardClients[Revenue],MATCH(LARGE(tblLeaderboardClients[Repeat Key],H69),tblLeaderboardClients[Repeat Key],0)) | L69: =INDEX(tblLeaderboardClients[Avg/Event],MATCH(LARGE(tblLeaderboardClients[Repeat Key],H69),tblLeaderboardClients[Repeat Key],0)) | M69: =INDEX(tblLeaderboardClients[First Event],MATCH(LARGE(tblLeaderboardClients[Repeat Key],H69),tblLeaderboardClients[Repeat Key],0)) | O69: 8 | P69: =INDEX(tblLeaderboardClients[Client],MATCH(LARGE(tblLeaderboardClients[Avg Key],O69),tblLeaderboardClients[Avg Key],0)) | Q69: =INDEX(tblLeaderboardClients[Avg/Event],MATCH(LARGE(tblLeaderboardClients[Avg Key],O69),tblLeaderboardClients[Avg Key],0)) | R69: =INDEX(tblLeaderboardClients[Events],MATCH(LARGE(tblLeaderboardClients[Avg Key],O69),tblLeaderboardClients[Avg Key],0)) | S69: =INDEX(tblLeaderboardClients[Revenue],MATCH(LARGE(tblLeaderboardClients[Avg Key],O69),tblLeaderboardClients[Avg Key],0)) | T69: =INDEX(tblLeaderboardClients[Avg/WO],MATCH(LARGE(tblLeaderboardClients[Avg Key],O69),tblLeaderboardClients[Avg Key],0)) | V69: Hanover | W69: MD | X69: 2 | Y69: 2 | Z69: 260 | AA69: 130 | AB69: 260
A70: 9 | B70: =INDEX(tblLeaderboardClients[Client],MATCH(LARGE(tblLeaderboardClients[Revenue Key],A70),tblLeaderboardClients[Revenue Key],0)) | C70: =INDEX(tblLeaderboardClients[Revenue],MATCH(LARGE(tblLeaderboardClients[Revenue Key],A70),tblLeaderboardClients[Revenue Key],0)) | D70: =INDEX(tblLeaderboardClients[Events],MATCH(LARGE(tblLeaderboardClients[Revenue Key],A70),tblLeaderboardClients[Revenue Key],0)) | E70: =INDEX(tblLeaderboardClients[Avg/Event],MATCH(LARGE(tblLeaderboardClients[Revenue Key],A70),tblLeaderboardClients[Revenue Key],0)) | F70: =INDEX(tblLeaderboardClients[Work Orders],MATCH(LARGE(tblLeaderboardClients[Revenue Key],A70),tblLeaderboardClients[Revenue Key],0)) | H70: 9 | I70: =INDEX(tblLeaderboardClients[Client],MATCH(LARGE(tblLeaderboardClients[Repeat Key],H70),tblLeaderboardClients[Repeat Key],0)) | J70: =INDEX(tblLeaderboardClients[Events],MATCH(LARGE(tblLeaderboardClients[Repeat Key],H70),tblLeaderboardClients[Repeat Key],0)) | K70: =INDEX(tblLeaderboardClients[Revenue],MATCH(LARGE(tblLeaderboardClients[Repeat Key],H70),tblLeaderboardClients[Repeat Key],0)) | L70: =INDEX(tblLeaderboardClients[Avg/Event],MATCH(LARGE(tblLeaderboardClients[Repeat Key],H70),tblLeaderboardClients[Repeat Key],0)) | M70: =INDEX(tblLeaderboardClients[First Event],MATCH(LARGE(tblLeaderboardClients[Repeat Key],H70),tblLeaderboardClients[Repeat Key],0)) | O70: 9 | P70: =INDEX(tblLeaderboardClients[Client],MATCH(LARGE(tblLeaderboardClients[Avg Key],O70),tblLeaderboardClients[Avg Key],0)) | Q70: =INDEX(tblLeaderboardClients[Avg/Event],MATCH(LARGE(tblLeaderboardClients[Avg Key],O70),tblLeaderboardClients[Avg Key],0)) | R70: =INDEX(tblLeaderboardClients[Events],MATCH(LARGE(tblLeaderboardClients[Avg Key],O70),tblLeaderboardClients[Avg Key],0)) | S70: =INDEX(tblLeaderboardClients[Revenue],MATCH(LARGE(tblLeaderboardClients[Avg Key],O70),tblLeaderboardClients[Avg Key],0)) | T70: =INDEX(tblLeaderboardClients[Avg/WO],MATCH(LARGE(tblLeaderboardClients[Avg Key],O70),tblLeaderboardClients[Avg Key],0)) | V70: Bel Air | W70: MD | X70: 1 | Y70: 0 | Z70: 0 | AA70: 0 | AB70: 1e-06
A71: 10 | B71: =INDEX(tblLeaderboardClients[Client],MATCH(LARGE(tblLeaderboardClients[Revenue Key],A71),tblLeaderboardClients[Revenue Key],0)) | C71: =INDEX(tblLeaderboardClients[Revenue],MATCH(LARGE(tblLeaderboardClients[Revenue Key],A71),tblLeaderboardClients[Revenue Key],0)) | D71: =INDEX(tblLeaderboardClients[Events],MATCH(LARGE(tblLeaderboardClients[Revenue Key],A71),tblLeaderboardClients[Revenue Key],0)) | E71: =INDEX(tblLeaderboardClients[Avg/Event],MATCH(LARGE(tblLeaderboardClients[Revenue Key],A71),tblLeaderboardClients[Revenue Key],0)) | F71: =INDEX(tblLeaderboardClients[Work Orders],MATCH(LARGE(tblLeaderboardClients[Revenue Key],A71),tblLeaderboardClients[Revenue Key],0)) | H71: 10 | I71: =INDEX(tblLeaderboardClients[Client],MATCH(LARGE(tblLeaderboardClients[Repeat Key],H71),tblLeaderboardClients[Repeat Key],0)) | J71: =INDEX(tblLeaderboardClients[Events],MATCH(LARGE(tblLeaderboardClients[Repeat Key],H71),tblLeaderboardClients[Repeat Key],0)) | K71: =INDEX(tblLeaderboardClients[Revenue],MATCH(LARGE(tblLeaderboardClients[Repeat Key],H71),tblLeaderboardClients[Repeat Key],0)) | L71: =INDEX(tblLeaderboardClients[Avg/Event],MATCH(LARGE(tblLeaderboardClients[Repeat Key],H71),tblLeaderboardClients[Repeat Key],0)) | M71: =INDEX(tblLeaderboardClients[First Event],MATCH(LARGE(tblLeaderboardClients[Repeat Key],H71),tblLeaderboardClients[Repeat Key],0)) | O71: 10 | P71: =INDEX(tblLeaderboardClients[Client],MATCH(LARGE(tblLeaderboardClients[Avg Key],O71),tblLeaderboardClients[Avg Key],0)) | Q71: =INDEX(tblLeaderboardClients[Avg/Event],MATCH(LARGE(tblLeaderboardClients[Avg Key],O71),tblLeaderboardClients[Avg Key],0)) | R71: =INDEX(tblLeaderboardClients[Events],MATCH(LARGE(tblLeaderboardClients[Avg Key],O71),tblLeaderboardClients[Avg Key],0)) | S71: =INDEX(tblLeaderboardClients[Revenue],MATCH(LARGE(tblLeaderboardClients[Avg Key],O71),tblLeaderboardClients[Avg Key],0)) | T71: =INDEX(tblLeaderboardClients[Avg/WO],MATCH(LARGE(tblLeaderboardClients[Avg Key],O71),tblLeaderboardClients[Avg Key],0)) | V71: Workweek | W71: Events | X71: Eligible Events | Y71: Revenue | Z71: Avg/Event | AA71: Worked Days | AB71: Rank Key
V72: 1 | W72: 5 | X72: 5 | Y72: 1008 | Z72: 201.6 | AA72: 5 | AB72: 1008
V73: 2 | W73: 4 | X73: 3 | Y73: 275 | Z73: 91.666667 | AA73: 3 | AB73: 275
A74: Jurisdictions — Confirmed Revenue | H74: Cities — Confirmed Revenue | O74: Top Revenue Events | V74: 3 | W74: 1 | X74: 1 | Y74: 212.5 | Z74: 212.5 | AA74: 1 | AB74: 212.5
A75: Rank | B75: Jurisdiction | C75: Revenue | D75: Events | E75: Clients | F75: Avg/Event | H75: Rank | I75: City | J75: Jurisdiction | K75: Revenue | L75: Events | M75: Avg/Event | O75: Rank | P75: Event # | Q75: Client | R75: Date | S75: City | T75: Revenue | V75: 4 | W75: 6 | X75: 5 | Y75: 412.5 | Z75: 82.5 | AA75: 5 | AB75: 412.5
A76: =1 | B76: =INDEX(tblStateSummary[Jurisdiction],MATCH(LARGE(tblStateSummary[Confirmed Revenue],A76),tblStateSummary[Confirmed Revenue],0)) | C76: =LARGE(tblStateSummary[Confirmed Revenue],A76) | D76: =INDEX(tblStateSummary[Events],MATCH(C76,tblStateSummary[Confirmed Revenue],0)) | E76: =INDEX(tblStateSummary[Clients],MATCH(C76,tblStateSummary[Confirmed Revenue],0)) | F76: =INDEX(tblStateSummary[Avg Revenue / Eligible Event],MATCH(C76,tblStateSummary[Confirmed Revenue],0)) | H76: 1 | I76: =INDEX(tblCitySummary[City],MATCH(LARGE(tblCitySummary[Rank Key],H76),tblCitySummary[Rank Key],0)) | J76: =INDEX(tblCitySummary[Jurisdiction],MATCH(LARGE(tblCitySummary[Rank Key],H76),tblCitySummary[Rank Key],0)) | K76: =INDEX(tblCitySummary[Revenue],MATCH(LARGE(tblCitySummary[Rank Key],H76),tblCitySummary[Rank Key],0)) | L76: =INDEX(tblCitySummary[Events],MATCH(LARGE(tblCitySummary[Rank Key],H76),tblCitySummary[Rank Key],0)) | M76: =INDEX(tblCitySummary[Avg/Event],MATCH(LARGE(tblCitySummary[Rank Key],H76),tblCitySummary[Rank Key],0)) | O76: 1 | P76: =INDEX(tblEventLeaderboardSource[Event #],MATCH(LARGE(tblEventLeaderboardSource[Rank Key],O76),tblEventLeaderboardSource[Rank Key],0)) | Q76: =INDEX(tblEventLeaderboardSource[Client],MATCH(LARGE(tblEventLeaderboardSource[Rank Key],O76),tblEventLeaderboardSource[Rank Key],0)) | R76: =INDEX(tblEventLeaderboardSource[Date],MATCH(LARGE(tblEventLeaderboardSource[Rank Key],O76),tblEventLeaderboardSource[Rank Key],0)) | S76: =INDEX(tblEventLeaderboardSource[City],MATCH(LARGE(tblEventLeaderboardSource[Rank Key],O76),tblEventLeaderboardSource[Rank Key],0)) | T76: =INDEX(tblEventLeaderboardSource[Revenue],MATCH(LARGE(tblEventLeaderboardSource[Rank Key],O76),tblEventLeaderboardSource[Rank Key],0)) | V76: 5 | W76: 4 | X76: 4 | Y76: 422.5 | Z76: 105.625 | AA76: 3 | AB76: 422.5
A77: =2 | B77: =INDEX(tblStateSummary[Jurisdiction],MATCH(LARGE(tblStateSummary[Confirmed Revenue],A77),tblStateSummary[Confirmed Revenue],0)) | C77: =LARGE(tblStateSummary[Confirmed Revenue],A77) | D77: =INDEX(tblStateSummary[Events],MATCH(C77,tblStateSummary[Confirmed Revenue],0)) | E77: =INDEX(tblStateSummary[Clients],MATCH(C77,tblStateSummary[Confirmed Revenue],0)) | F77: =INDEX(tblStateSummary[Avg Revenue / Eligible Event],MATCH(C77,tblStateSummary[Confirmed Revenue],0)) | H77: 2 | I77: =INDEX(tblCitySummary[City],MATCH(LARGE(tblCitySummary[Rank Key],H77),tblCitySummary[Rank Key],0)) | J77: =INDEX(tblCitySummary[Jurisdiction],MATCH(LARGE(tblCitySummary[Rank Key],H77),tblCitySummary[Rank Key],0)) | K77: =INDEX(tblCitySummary[Revenue],MATCH(LARGE(tblCitySummary[Rank Key],H77),tblCitySummary[Rank Key],0)) | L77: =INDEX(tblCitySummary[Events],MATCH(LARGE(tblCitySummary[Rank Key],H77),tblCitySummary[Rank Key],0)) | M77: =INDEX(tblCitySummary[Avg/Event],MATCH(LARGE(tblCitySummary[Rank Key],H77),tblCitySummary[Rank Key],0)) | O77: 2 | P77: =INDEX(tblEventLeaderboardSource[Event #],MATCH(LARGE(tblEventLeaderboardSource[Rank Key],O77),tblEventLeaderboardSource[Rank Key],0)) | Q77: =INDEX(tblEventLeaderboardSource[Client],MATCH(LARGE(tblEventLeaderboardSource[Rank Key],O77),tblEventLeaderboardSource[Rank Key],0)) | R77: =INDEX(tblEventLeaderboardSource[Date],MATCH(LARGE(tblEventLeaderboardSource[Rank Key],O77),tblEventLeaderboardSource[Rank Key],0)) | S77: =INDEX(tblEventLeaderboardSource[City],MATCH(LARGE(tblEventLeaderboardSource[Rank Key],O77),tblEventLeaderboardSource[Rank Key],0)) | T77: =INDEX(tblEventLeaderboardSource[Revenue],MATCH(LARGE(tblEventLeaderboardSource[Rank Key],O77),tblEventLeaderboardSource[Rank Key],0)) | V77: 6 | W77: 6 | X77: 4 | Y77: 522.91 | Z77: 130.7275 | AA77: 3 | AB77: 522.91001
A78: =3 | B78: =INDEX(tblStateSummary[Jurisdiction],MATCH(LARGE(tblStateSummary[Confirmed Revenue],A78),tblStateSummary[Confirmed Revenue],0)) | C78: =LARGE(tblStateSummary[Confirmed Revenue],A78) | D78: =INDEX(tblStateSummary[Events],MATCH(C78,tblStateSummary[Confirmed Revenue],0)) | E78: =INDEX(tblStateSummary[Clients],MATCH(C78,tblStateSummary[Confirmed Revenue],0)) | F78: =INDEX(tblStateSummary[Avg Revenue / Eligible Event],MATCH(C78,tblStateSummary[Confirmed Revenue],0)) | H78: 3 | I78: =INDEX(tblCitySummary[City],MATCH(LARGE(tblCitySummary[Rank Key],H78),tblCitySummary[Rank Key],0)) | J78: =INDEX(tblCitySummary[Jurisdiction],MATCH(LARGE(tblCitySummary[Rank Key],H78),tblCitySummary[Rank Key],0)) | K78: =INDEX(tblCitySummary[Revenue],MATCH(LARGE(tblCitySummary[Rank Key],H78),tblCitySummary[Rank Key],0)) | L78: =INDEX(tblCitySummary[Events],MATCH(LARGE(tblCitySummary[Rank Key],H78),tblCitySummary[Rank Key],0)) | M78: =INDEX(tblCitySummary[Avg/Event],MATCH(LARGE(tblCitySummary[Rank Key],H78),tblCitySummary[Rank Key],0)) | O78: 3 | P78: =INDEX(tblEventLeaderboardSource[Event #],MATCH(LARGE(tblEventLeaderboardSource[Rank Key],O78),tblEventLeaderboardSource[Rank Key],0)) | Q78: =INDEX(tblEventLeaderboardSource[Client],MATCH(LARGE(tblEventLeaderboardSource[Rank Key],O78),tblEventLeaderboardSource[Rank Key],0)) | R78: =INDEX(tblEventLeaderboardSource[Date],MATCH(LARGE(tblEventLeaderboardSource[Rank Key],O78),tblEventLeaderboardSource[Rank Key],0)) | S78: =INDEX(tblEventLeaderboardSource[City],MATCH(LARGE(tblEventLeaderboardSource[Rank Key],O78),tblEventLeaderboardSource[Rank Key],0)) | T78: =INDEX(tblEventLeaderboardSource[Revenue],MATCH(LARGE(tblEventLeaderboardSource[Rank Key],O78),tblEventLeaderboardSource[Rank Key],0)) | V78: 7 | W78: 8 | X78: 8 | Y78: 1221.66 | Z78: 152.7075 | AA78: 5 | AB78: 1221.66
A79: =4 | B79: =INDEX(tblStateSummary[Jurisdiction],MATCH(LARGE(tblStateSummary[Confirmed Revenue],A79),tblStateSummary[Confirmed Revenue],0)) | C79: =LARGE(tblStateSummary[Confirmed Revenue],A79) | D79: =INDEX(tblStateSummary[Events],MATCH(C79,tblStateSummary[Confirmed Revenue],0)) | E79: =INDEX(tblStateSummary[Clients],MATCH(C79,tblStateSummary[Confirmed Revenue],0)) | F79: =INDEX(tblStateSummary[Avg Revenue / Eligible Event],MATCH(C79,tblStateSummary[Confirmed Revenue],0)) | H79: 4 | I79: =INDEX(tblCitySummary[City],MATCH(LARGE(tblCitySummary[Rank Key],H79),tblCitySummary[Rank Key],0)) | J79: =INDEX(tblCitySummary[Jurisdiction],MATCH(LARGE(tblCitySummary[Rank Key],H79),tblCitySummary[Rank Key],0)) | K79: =INDEX(tblCitySummary[Revenue],MATCH(LARGE(tblCitySummary[Rank Key],H79),tblCitySummary[Rank Key],0)) | L79: =INDEX(tblCitySummary[Events],MATCH(LARGE(tblCitySummary[Rank Key],H79),tblCitySummary[Rank Key],0)) | M79: =INDEX(tblCitySummary[Avg/Event],MATCH(LARGE(tblCitySummary[Rank Key],H79),tblCitySummary[Rank Key],0)) | O79: 4 | P79: =INDEX(tblEventLeaderboardSource[Event #],MATCH(LARGE(tblEventLeaderboardSource[Rank Key],O79),tblEventLeaderboardSource[Rank Key],0)) | Q79: =INDEX(tblEventLeaderboardSource[Client],MATCH(LARGE(tblEventLeaderboardSource[Rank Key],O79),tblEventLeaderboardSource[Rank Key],0)) | R79: =INDEX(tblEventLeaderboardSource[Date],MATCH(LARGE(tblEventLeaderboardSource[Rank Key],O79),tblEventLeaderboardSource[Rank Key],0)) | S79: =INDEX(tblEventLeaderboardSource[City],MATCH(LARGE(tblEventLeaderboardSource[Rank Key],O79),tblEventLeaderboardSource[Rank Key],0)) | T79: =INDEX(tblEventLeaderboardSource[Revenue],MATCH(LARGE(tblEventLeaderboardSource[Rank Key],O79),tblEventLeaderboardSource[Rank Key],0)) | V79: 8 | W79: 9 | X79: 9 | Y79: 760 | Z79: 84.444444 | AA79: 5 | AB79: 760.00001
A80: =5 | B80: =INDEX(tblStateSummary[Jurisdiction],MATCH(LARGE(tblStateSummary[Confirmed Revenue],A80),tblStateSummary[Confirmed Revenue],0)) | C80: =LARGE(tblStateSummary[Confirmed Revenue],A80) | D80: =INDEX(tblStateSummary[Events],MATCH(C80,tblStateSummary[Confirmed Revenue],0)) | E80: =INDEX(tblStateSummary[Clients],MATCH(C80,tblStateSummary[Confirmed Revenue],0)) | F80: =INDEX(tblStateSummary[Avg Revenue / Eligible Event],MATCH(C80,tblStateSummary[Confirmed Revenue],0)) | H80: 5 | I80: =INDEX(tblCitySummary[City],MATCH(LARGE(tblCitySummary[Rank Key],H80),tblCitySummary[Rank Key],0)) | J80: =INDEX(tblCitySummary[Jurisdiction],MATCH(LARGE(tblCitySummary[Rank Key],H80),tblCitySummary[Rank Key],0)) | K80: =INDEX(tblCitySummary[Revenue],MATCH(LARGE(tblCitySummary[Rank Key],H80),tblCitySummary[Rank Key],0)) | L80: =INDEX(tblCitySummary[Events],MATCH(LARGE(tblCitySummary[Rank Key],H80),tblCitySummary[Rank Key],0)) | M80: =INDEX(tblCitySummary[Avg/Event],MATCH(LARGE(tblCitySummary[Rank Key],H80),tblCitySummary[Rank Key],0)) | O80: 5 | P80: =INDEX(tblEventLeaderboardSource[Event #],MATCH(LARGE(tblEventLeaderboardSource[Rank Key],O80),tblEventLeaderboardSource[Rank Key],0)) | Q80: =INDEX(tblEventLeaderboardSource[Client],MATCH(LARGE(tblEventLeaderboardSource[Rank Key],O80),tblEventLeaderboardSource[Rank Key],0)) | R80: =INDEX(tblEventLeaderboardSource[Date],MATCH(LARGE(tblEventLeaderboardSource[Rank Key],O80),tblEventLeaderboardSource[Rank Key],0)) | S80: =INDEX(tblEventLeaderboardSource[City],MATCH(LARGE(tblEventLeaderboardSource[Rank Key],O80),tblEventLeaderboardSource[Rank Key],0)) | T80: =INDEX(tblEventLeaderboardSource[Revenue],MATCH(LARGE(tblEventLeaderboardSource[Rank Key],O80),tblEventLeaderboardSource[Rank Key],0)) | V80: 9 | W80: 7 | X80: 7 | Y80: 681.75 | Z80: 97.392857 | AA80: 4 | AB80: 681.75001
H81: 6 | I81: =INDEX(tblCitySummary[City],MATCH(LARGE(tblCitySummary[Rank Key],H81),tblCitySummary[Rank Key],0)) | J81: =INDEX(tblCitySummary[Jurisdiction],MATCH(LARGE(tblCitySummary[Rank Key],H81),tblCitySummary[Rank Key],0)) | K81: =INDEX(tblCitySummary[Revenue],MATCH(LARGE(tblCitySummary[Rank Key],H81),tblCitySummary[Rank Key],0)) | L81: =INDEX(tblCitySummary[Events],MATCH(LARGE(tblCitySummary[Rank Key],H81),tblCitySummary[Rank Key],0)) | M81: =INDEX(tblCitySummary[Avg/Event],MATCH(LARGE(tblCitySummary[Rank Key],H81),tblCitySummary[Rank Key],0)) | O81: 6 | P81: =INDEX(tblEventLeaderboardSource[Event #],MATCH(LARGE(tblEventLeaderboardSource[Rank Key],O81),tblEventLeaderboardSource[Rank Key],0)) | Q81: =INDEX(tblEventLeaderboardSource[Client],MATCH(LARGE(tblEventLeaderboardSource[Rank Key],O81),tblEventLeaderboardSource[Rank Key],0)) | R81: =INDEX(tblEventLeaderboardSource[Date],MATCH(LARGE(tblEventLeaderboardSource[Rank Key],O81),tblEventLeaderboardSource[Rank Key],0)) | S81: =INDEX(tblEventLeaderboardSource[City],MATCH(LARGE(tblEventLeaderboardSource[Rank Key],O81),tblEventLeaderboardSource[Rank Key],0)) | T81: =INDEX(tblEventLeaderboardSource[Revenue],MATCH(LARGE(tblEventLeaderboardSource[Rank Key],O81),tblEventLeaderboardSource[Rank Key],0)) | V81: 10 | W81: 3 | X81: 3 | Y81: 308.27 | Z81: 102.75667 | AA81: 3 | AB81: 308.27001
H82: 7 | I82: =INDEX(tblCitySummary[City],MATCH(LARGE(tblCitySummary[Rank Key],H82),tblCitySummary[Rank Key],0)) | J82: =INDEX(tblCitySummary[Jurisdiction],MATCH(LARGE(tblCitySummary[Rank Key],H82),tblCitySummary[Rank Key],0)) | K82: =INDEX(tblCitySummary[Revenue],MATCH(LARGE(tblCitySummary[Rank Key],H82),tblCitySummary[Rank Key],0)) | L82: =INDEX(tblCitySummary[Events],MATCH(LARGE(tblCitySummary[Rank Key],H82),tblCitySummary[Rank Key],0)) | M82: =INDEX(tblCitySummary[Avg/Event],MATCH(LARGE(tblCitySummary[Rank Key],H82),tblCitySummary[Rank Key],0)) | O82: 7 | P82: =INDEX(tblEventLeaderboardSource[Event #],MATCH(LARGE(tblEventLeaderboardSource[Rank Key],O82),tblEventLeaderboardSource[Rank Key],0)) | Q82: =INDEX(tblEventLeaderboardSource[Client],MATCH(LARGE(tblEventLeaderboardSource[Rank Key],O82),tblEventLeaderboardSource[Rank Key],0)) | R82: =INDEX(tblEventLeaderboardSource[Date],MATCH(LARGE(tblEventLeaderboardSource[Rank Key],O82),tblEventLeaderboardSource[Rank Key],0)) | S82: =INDEX(tblEventLeaderboardSource[City],MATCH(LARGE(tblEventLeaderboardSource[Rank Key],O82),tblEventLeaderboardSource[Rank Key],0)) | T82: =INDEX(tblEventLeaderboardSource[Revenue],MATCH(LARGE(tblEventLeaderboardSource[Rank Key],O82),tblEventLeaderboardSource[Rank Key],0)) | V82: 11 | W82: 3 | X82: 3 | Y82: 410.66 | Z82: 136.88667 | AA82: 3 | AB82: 410.66001
H83: 8 | I83: =INDEX(tblCitySummary[City],MATCH(LARGE(tblCitySummary[Rank Key],H83),tblCitySummary[Rank Key],0)) | J83: =INDEX(tblCitySummary[Jurisdiction],MATCH(LARGE(tblCitySummary[Rank Key],H83),tblCitySummary[Rank Key],0)) | K83: =INDEX(tblCitySummary[Revenue],MATCH(LARGE(tblCitySummary[Rank Key],H83),tblCitySummary[Rank Key],0)) | L83: =INDEX(tblCitySummary[Events],MATCH(LARGE(tblCitySummary[Rank Key],H83),tblCitySummary[Rank Key],0)) | M83: =INDEX(tblCitySummary[Avg/Event],MATCH(LARGE(tblCitySummary[Rank Key],H83),tblCitySummary[Rank Key],0)) | O83: 8 | P83: =INDEX(tblEventLeaderboardSource[Event #],MATCH(LARGE(tblEventLeaderboardSource[Rank Key],O83),tblEventLeaderboardSource[Rank Key],0)) | Q83: =INDEX(tblEventLeaderboardSource[Client],MATCH(LARGE(tblEventLeaderboardSource[Rank Key],O83),tblEventLeaderboardSource[Rank Key],0)) | R83: =INDEX(tblEventLeaderboardSource[Date],MATCH(LARGE(tblEventLeaderboardSource[Rank Key],O83),tblEventLeaderboardSource[Rank Key],0)) | S83: =INDEX(tblEventLeaderboardSource[City],MATCH(LARGE(tblEventLeaderboardSource[Rank Key],O83),tblEventLeaderboardSource[Rank Key],0)) | T83: =INDEX(tblEventLeaderboardSource[Revenue],MATCH(LARGE(tblEventLeaderboardSource[Rank Key],O83),tblEventLeaderboardSource[Rank Key],0)) | V83: 12 | W83: 6 | X83: 5 | Y83: 815.06 | Z83: 163.012 | AA83: 4 | AB83: 815.06001
H84: 9 | I84: =INDEX(tblCitySummary[City],MATCH(LARGE(tblCitySummary[Rank Key],H84),tblCitySummary[Rank Key],0)) | J84: =INDEX(tblCitySummary[Jurisdiction],MATCH(LARGE(tblCitySummary[Rank Key],H84),tblCitySummary[Rank Key],0)) | K84: =INDEX(tblCitySummary[Revenue],MATCH(LARGE(tblCitySummary[Rank Key],H84),tblCitySummary[Rank Key],0)) | L84: =INDEX(tblCitySummary[Events],MATCH(LARGE(tblCitySummary[Rank Key],H84),tblCitySummary[Rank Key],0)) | M84: =INDEX(tblCitySummary[Avg/Event],MATCH(LARGE(tblCitySummary[Rank Key],H84),tblCitySummary[Rank Key],0)) | O84: 9 | P84: =INDEX(tblEventLeaderboardSource[Event #],MATCH(LARGE(tblEventLeaderboardSource[Rank Key],O84),tblEventLeaderboardSource[Rank Key],0)) | Q84: =INDEX(tblEventLeaderboardSource[Client],MATCH(LARGE(tblEventLeaderboardSource[Rank Key],O84),tblEventLeaderboardSource[Rank Key],0)) | R84: =INDEX(tblEventLeaderboardSource[Date],MATCH(LARGE(tblEventLeaderboardSource[Rank Key],O84),tblEventLeaderboardSource[Rank Key],0)) | S84: =INDEX(tblEventLeaderboardSource[City],MATCH(LARGE(tblEventLeaderboardSource[Rank Key],O84),tblEventLeaderboardSource[Rank Key],0)) | T84: =INDEX(tblEventLeaderboardSource[Revenue],MATCH(LARGE(tblEventLeaderboardSource[Rank Key],O84),tblEventLeaderboardSource[Rank Key],0)) | V84: 13 | W84: 5 | X84: 1 | Y84: 183.74 | Z84: 183.74 | AA84: 2 | AB84: 183.74001
H85: 10 | I85: =INDEX(tblCitySummary[City],MATCH(LARGE(tblCitySummary[Rank Key],H85),tblCitySummary[Rank Key],0)) | J85: =INDEX(tblCitySummary[Jurisdiction],MATCH(LARGE(tblCitySummary[Rank Key],H85),tblCitySummary[Rank Key],0)) | K85: =INDEX(tblCitySummary[Revenue],MATCH(LARGE(tblCitySummary[Rank Key],H85),tblCitySummary[Rank Key],0)) | L85: =INDEX(tblCitySummary[Events],MATCH(LARGE(tblCitySummary[Rank Key],H85),tblCitySummary[Rank Key],0)) | M85: =INDEX(tblCitySummary[Avg/Event],MATCH(LARGE(tblCitySummary[Rank Key],H85),tblCitySummary[Rank Key],0)) | O85: 10 | P85: =INDEX(tblEventLeaderboardSource[Event #],MATCH(LARGE(tblEventLeaderboardSource[Rank Key],O85),tblEventLeaderboardSource[Rank Key],0)) | Q85: =INDEX(tblEventLeaderboardSource[Client],MATCH(LARGE(tblEventLeaderboardSource[Rank Key],O85),tblEventLeaderboardSource[Rank Key],0)) | R85: =INDEX(tblEventLeaderboardSource[Date],MATCH(LARGE(tblEventLeaderboardSource[Rank Key],O85),tblEventLeaderboardSource[Rank Key],0)) | S85: =INDEX(tblEventLeaderboardSource[City],MATCH(LARGE(tblEventLeaderboardSource[Rank Key],O85),tblEventLeaderboardSource[Rank Key],0)) | T85: =INDEX(tblEventLeaderboardSource[Revenue],MATCH(LARGE(tblEventLeaderboardSource[Rank Key],O85),tblEventLeaderboardSource[Rank Key],0))
V86: Service Date | W86: Weekday | X86: Events | Y86: Eligible Events | Z86: Revenue | AA86: Avg/Event | AB86: Rank Key
V87: 46132 | W87: Monday | X87: 1 | Y87: 1 | Z87: 90 | AA87: 90 | AB87: 90.000046
A88: Top Workweeks | H88: MY_MONTH Ranking | O88: Top Worked Dates | V88: 46133 | W88: Tuesday | X88: 1 | Y88: 1 | Z88: 344 | AA88: 344 | AB88: 344.00005
A89: Rank | B89: Workweek | C89: Revenue | D89: Events | E89: Worked Days | F89: Avg/Event | H89: Rank | I89: MY_MONTH | J89: Revenue | K89: Events | L89: Clients | M89: Avg/Event | O89: Rank | P89: Date | Q89: Weekday | R89: Revenue | S89: Events | T89: Avg/Event | V89: 46134 | W89: Wednesday | X89: 1 | Y89: 1 | Z89: 344 | AA89: 344 | AB89: 344.00005
A90: 1 | B90: =INDEX(tblWeekSummary[Workweek],MATCH(LARGE(tblWeekSummary[Rank Key],A90),tblWeekSummary[Rank Key],0)) | C90: =INDEX(tblWeekSummary[Revenue],MATCH(LARGE(tblWeekSummary[Rank Key],A90),tblWeekSummary[Rank Key],0)) | D90: =INDEX(tblWeekSummary[Events],MATCH(LARGE(tblWeekSummary[Rank Key],A90),tblWeekSummary[Rank Key],0)) | E90: =INDEX(tblWeekSummary[Worked Days],MATCH(LARGE(tblWeekSummary[Rank Key],A90),tblWeekSummary[Rank Key],0)) | F90: =INDEX(tblWeekSummary[Avg/Event],MATCH(LARGE(tblWeekSummary[Rank Key],A90),tblWeekSummary[Rank Key],0)) | H90: 1 | I90: =INDEX(tblMonthSummary[MY_MONTH],MATCH(LARGE(tblMonthSummary[Confirmed Revenue],H90),tblMonthSummary[Confirmed Revenue],0)) | J90: =LARGE(tblMonthSummary[Confirmed Revenue],H90) | K90: =INDEX(tblMonthSummary[Events],MATCH(J90,tblMonthSummary[Confirmed Revenue],0)) | L90: =INDEX(tblMonthSummary[Clients],MATCH(J90,tblMonthSummary[Confirmed Revenue],0)) | M90: =INDEX(tblMonthSummary[Avg Revenue / Eligible Event],MATCH(J90,tblMonthSummary[Confirmed Revenue],0)) | O90: 1 | P90: =INDEX(tblDateSummary[Service Date],MATCH(LARGE(tblDateSummary[Rank Key],O90),tblDateSummary[Rank Key],0)) | Q90: =INDEX(tblDateSummary[Weekday],MATCH(LARGE(tblDateSummary[Rank Key],O90),tblDateSummary[Rank Key],0)) | R90: =INDEX(tblDateSummary[Revenue],MATCH(LARGE(tblDateSummary[Rank Key],O90),tblDateSummary[Rank Key],0)) | S90: =INDEX(tblDateSummary[Events],MATCH(LARGE(tblDateSummary[Rank Key],O90),tblDateSummary[Rank Key],0)) | T90: =INDEX(tblDateSummary[Avg/Event],MATCH(LARGE(tblDateSummary[Rank Key],O90),tblDateSummary[Rank Key],0)) | V90: 46135 | W90: Thursday | X90: 1 | Y90: 1 | Z90: 180 | AA90: 180 | AB90: 180.00005
A91: 2 | B91: =INDEX(tblWeekSummary[Workweek],MATCH(LARGE(tblWeekSummary[Rank Key],A91),tblWeekSummary[Rank Key],0)) | C91: =INDEX(tblWeekSummary[Revenue],MATCH(LARGE(tblWeekSummary[Rank Key],A91),tblWeekSummary[Rank Key],0)) | D91: =INDEX(tblWeekSummary[Events],MATCH(LARGE(tblWeekSummary[Rank Key],A91),tblWeekSummary[Rank Key],0)) | E91: =INDEX(tblWeekSummary[Worked Days],MATCH(LARGE(tblWeekSummary[Rank Key],A91),tblWeekSummary[Rank Key],0)) | F91: =INDEX(tblWeekSummary[Avg/Event],MATCH(LARGE(tblWeekSummary[Rank Key],A91),tblWeekSummary[Rank Key],0)) | H91: 2 | I91: =INDEX(tblMonthSummary[MY_MONTH],MATCH(LARGE(tblMonthSummary[Confirmed Revenue],H91),tblMonthSummary[Confirmed Revenue],0)) | J91: =LARGE(tblMonthSummary[Confirmed Revenue],H91) | K91: =INDEX(tblMonthSummary[Events],MATCH(J91,tblMonthSummary[Confirmed Revenue],0)) | L91: =INDEX(tblMonthSummary[Clients],MATCH(J91,tblMonthSummary[Confirmed Revenue],0)) | M91: =INDEX(tblMonthSummary[Avg Revenue / Eligible Event],MATCH(J91,tblMonthSummary[Confirmed Revenue],0)) | O91: 2 | P91: =INDEX(tblDateSummary[Service Date],MATCH(LARGE(tblDateSummary[Rank Key],O91),tblDateSummary[Rank Key],0)) | Q91: =INDEX(tblDateSummary[Weekday],MATCH(LARGE(tblDateSummary[Rank Key],O91),tblDateSummary[Rank Key],0)) | R91: =INDEX(tblDateSummary[Revenue],MATCH(LARGE(tblDateSummary[Rank Key],O91),tblDateSummary[Rank Key],0)) | S91: =INDEX(tblDateSummary[Events],MATCH(LARGE(tblDateSummary[Rank Key],O91),tblDateSummary[Rank Key],0)) | T91: =INDEX(tblDateSummary[Avg/Event],MATCH(LARGE(tblDateSummary[Rank Key],O91),tblDateSummary[Rank Key],0)) | V91: 46136 | W91: Friday | X91: 1 | Y91: 1 | Z91: 50 | AA91: 50 | AB91: 50.000046
A92: 3 | B92: =INDEX(tblWeekSummary[Workweek],MATCH(LARGE(tblWeekSummary[Rank Key],A92),tblWeekSummary[Rank Key],0)) | C92: =INDEX(tblWeekSummary[Revenue],MATCH(LARGE(tblWeekSummary[Rank Key],A92),tblWeekSummary[Rank Key],0)) | D92: =INDEX(tblWeekSummary[Events],MATCH(LARGE(tblWeekSummary[Rank Key],A92),tblWeekSummary[Rank Key],0)) | E92: =INDEX(tblWeekSummary[Worked Days],MATCH(LARGE(tblWeekSummary[Rank Key],A92),tblWeekSummary[Rank Key],0)) | F92: =INDEX(tblWeekSummary[Avg/Event],MATCH(LARGE(tblWeekSummary[Rank Key],A92),tblWeekSummary[Rank Key],0)) | H92: 3 | I92: =INDEX(tblMonthSummary[MY_MONTH],MATCH(LARGE(tblMonthSummary[Confirmed Revenue],H92),tblMonthSummary[Confirmed Revenue],0)) | J92: =LARGE(tblMonthSummary[Confirmed Revenue],H92) | K92: =INDEX(tblMonthSummary[Events],MATCH(J92,tblMonthSummary[Confirmed Revenue],0)) | L92: =INDEX(tblMonthSummary[Clients],MATCH(J92,tblMonthSummary[Confirmed Revenue],0)) | M92: =INDEX(tblMonthSummary[Avg Revenue / Eligible Event],MATCH(J92,tblMonthSummary[Confirmed Revenue],0)) | O92: 3 | P92: =INDEX(tblDateSummary[Service Date],MATCH(LARGE(tblDateSummary[Rank Key],O92),tblDateSummary[Rank Key],0)) | Q92: =INDEX(tblDateSummary[Weekday],MATCH(LARGE(tblDateSummary[Rank Key],O92),tblDateSummary[Rank Key],0)) | R92: =INDEX(tblDateSummary[Revenue],MATCH(LARGE(tblDateSummary[Rank Key],O92),tblDateSummary[Rank Key],0)) | S92: =INDEX(tblDateSummary[Events],MATCH(LARGE(tblDateSummary[Rank Key],O92),tblDateSummary[Rank Key],0)) | T92: =INDEX(tblDateSummary[Avg/Event],MATCH(LARGE(tblDateSummary[Rank Key],O92),tblDateSummary[Rank Key],0)) | V92: 46139 | W92: Monday | X92: 1 | Y92: 1 | Z92: 180 | AA92: 180 | AB92: 180.00005
A93: 4 | B93: =INDEX(tblWeekSummary[Workweek],MATCH(LARGE(tblWeekSummary[Rank Key],A93),tblWeekSummary[Rank Key],0)) | C93: =INDEX(tblWeekSummary[Revenue],MATCH(LARGE(tblWeekSummary[Rank Key],A93),tblWeekSummary[Rank Key],0)) | D93: =INDEX(tblWeekSummary[Events],MATCH(LARGE(tblWeekSummary[Rank Key],A93),tblWeekSummary[Rank Key],0)) | E93: =INDEX(tblWeekSummary[Worked Days],MATCH(LARGE(tblWeekSummary[Rank Key],A93),tblWeekSummary[Rank Key],0)) | F93: =INDEX(tblWeekSummary[Avg/Event],MATCH(LARGE(tblWeekSummary[Rank Key],A93),tblWeekSummary[Rank Key],0)) | O93: 4 | P93: =INDEX(tblDateSummary[Service Date],MATCH(LARGE(tblDateSummary[Rank Key],O93),tblDateSummary[Rank Key],0)) | Q93: =INDEX(tblDateSummary[Weekday],MATCH(LARGE(tblDateSummary[Rank Key],O93),tblDateSummary[Rank Key],0)) | R93: =INDEX(tblDateSummary[Revenue],MATCH(LARGE(tblDateSummary[Rank Key],O93),tblDateSummary[Rank Key],0)) | S93: =INDEX(tblDateSummary[Events],MATCH(LARGE(tblDateSummary[Rank Key],O93),tblDateSummary[Rank Key],0)) | T93: =INDEX(tblDateSummary[Avg/Event],MATCH(LARGE(tblDateSummary[Rank Key],O93),tblDateSummary[Rank Key],0)) | V93: 46141 | W93: Wednesday | X93: 2 | Y93: 2 | Z93: 95 | AA93: 47.5 | AB93: 95.000046
A94: 5 | B94: =INDEX(tblWeekSummary[Workweek],MATCH(LARGE(tblWeekSummary[Rank Key],A94),tblWeekSummary[Rank Key],0)) | C94: =INDEX(tblWeekSummary[Revenue],MATCH(LARGE(tblWeekSummary[Rank Key],A94),tblWeekSummary[Rank Key],0)) | D94: =INDEX(tblWeekSummary[Events],MATCH(LARGE(tblWeekSummary[Rank Key],A94),tblWeekSummary[Rank Key],0)) | E94: =INDEX(tblWeekSummary[Worked Days],MATCH(LARGE(tblWeekSummary[Rank Key],A94),tblWeekSummary[Rank Key],0)) | F94: =INDEX(tblWeekSummary[Avg/Event],MATCH(LARGE(tblWeekSummary[Rank Key],A94),tblWeekSummary[Rank Key],0)) | O94: 5 | P94: =INDEX(tblDateSummary[Service Date],MATCH(LARGE(tblDateSummary[Rank Key],O94),tblDateSummary[Rank Key],0)) | Q94: =INDEX(tblDateSummary[Weekday],MATCH(LARGE(tblDateSummary[Rank Key],O94),tblDateSummary[Rank Key],0)) | R94: =INDEX(tblDateSummary[Revenue],MATCH(LARGE(tblDateSummary[Rank Key],O94),tblDateSummary[Rank Key],0)) | S94: =INDEX(tblDateSummary[Events],MATCH(LARGE(tblDateSummary[Rank Key],O94),tblDateSummary[Rank Key],0)) | T94: =INDEX(tblDateSummary[Avg/Event],MATCH(LARGE(tblDateSummary[Rank Key],O94),tblDateSummary[Rank Key],0)) | V94: 46142 | W94: Thursday | X94: 1 | Y94: 0 | Z94: 0 | AA94: 0 | AB94: 4.6142e-05
A95: 6 | B95: =INDEX(tblWeekSummary[Workweek],MATCH(LARGE(tblWeekSummary[Rank Key],A95),tblWeekSummary[Rank Key],0)) | C95: =INDEX(tblWeekSummary[Revenue],MATCH(LARGE(tblWeekSummary[Rank Key],A95),tblWeekSummary[Rank Key],0)) | D95: =INDEX(tblWeekSummary[Events],MATCH(LARGE(tblWeekSummary[Rank Key],A95),tblWeekSummary[Rank Key],0)) | E95: =INDEX(tblWeekSummary[Worked Days],MATCH(LARGE(tblWeekSummary[Rank Key],A95),tblWeekSummary[Rank Key],0)) | F95: =INDEX(tblWeekSummary[Avg/Event],MATCH(LARGE(tblWeekSummary[Rank Key],A95),tblWeekSummary[Rank Key],0)) | O95: 6 | P95: =INDEX(tblDateSummary[Service Date],MATCH(LARGE(tblDateSummary[Rank Key],O95),tblDateSummary[Rank Key],0)) | Q95: =INDEX(tblDateSummary[Weekday],MATCH(LARGE(tblDateSummary[Rank Key],O95),tblDateSummary[Rank Key],0)) | R95: =INDEX(tblDateSummary[Revenue],MATCH(LARGE(tblDateSummary[Rank Key],O95),tblDateSummary[Rank Key],0)) | S95: =INDEX(tblDateSummary[Events],MATCH(LARGE(tblDateSummary[Rank Key],O95),tblDateSummary[Rank Key],0)) | T95: =INDEX(tblDateSummary[Avg/Event],MATCH(LARGE(tblDateSummary[Rank Key],O95),tblDateSummary[Rank Key],0)) | V95: 46147 | W95: Tuesday | X95: 1 | Y95: 1 | Z95: 212.5 | AA95: 212.5 | AB95: 212.50005
A96: 7 | B96: =INDEX(tblWeekSummary[Workweek],MATCH(LARGE(tblWeekSummary[Rank Key],A96),tblWeekSummary[Rank Key],0)) | C96: =INDEX(tblWeekSummary[Revenue],MATCH(LARGE(tblWeekSummary[Rank Key],A96),tblWeekSummary[Rank Key],0)) | D96: =INDEX(tblWeekSummary[Events],MATCH(LARGE(tblWeekSummary[Rank Key],A96),tblWeekSummary[Rank Key],0)) | E96: =INDEX(tblWeekSummary[Worked Days],MATCH(LARGE(tblWeekSummary[Rank Key],A96),tblWeekSummary[Rank Key],0)) | F96: =INDEX(tblWeekSummary[Avg/Event],MATCH(LARGE(tblWeekSummary[Rank Key],A96),tblWeekSummary[Rank Key],0)) | O96: 7 | P96: =INDEX(tblDateSummary[Service Date],MATCH(LARGE(tblDateSummary[Rank Key],O96),tblDateSummary[Rank Key],0)) | Q96: =INDEX(tblDateSummary[Weekday],MATCH(LARGE(tblDateSummary[Rank Key],O96),tblDateSummary[Rank Key],0)) | R96: =INDEX(tblDateSummary[Revenue],MATCH(LARGE(tblDateSummary[Rank Key],O96),tblDateSummary[Rank Key],0)) | S96: =INDEX(tblDateSummary[Events],MATCH(LARGE(tblDateSummary[Rank Key],O96),tblDateSummary[Rank Key],0)) | T96: =INDEX(tblDateSummary[Avg/Event],MATCH(LARGE(tblDateSummary[Rank Key],O96),tblDateSummary[Rank Key],0)) | V96: 46153 | W96: Monday | X96: 1 | Y96: 1 | Z96: 157.5 | AA96: 157.5 | AB96: 157.50005
A97: 8 | B97: =INDEX(tblWeekSummary[Workweek],MATCH(LARGE(tblWeekSummary[Rank Key],A97),tblWeekSummary[Rank Key],0)) | C97: =INDEX(tblWeekSummary[Revenue],MATCH(LARGE(tblWeekSummary[Rank Key],A97),tblWeekSummary[Rank Key],0)) | D97: =INDEX(tblWeekSummary[Events],MATCH(LARGE(tblWeekSummary[Rank Key],A97),tblWeekSummary[Rank Key],0)) | E97: =INDEX(tblWeekSummary[Worked Days],MATCH(LARGE(tblWeekSummary[Rank Key],A97),tblWeekSummary[Rank Key],0)) | F97: =INDEX(tblWeekSummary[Avg/Event],MATCH(LARGE(tblWeekSummary[Rank Key],A97),tblWeekSummary[Rank Key],0)) | O97: 8 | P97: =INDEX(tblDateSummary[Service Date],MATCH(LARGE(tblDateSummary[Rank Key],O97),tblDateSummary[Rank Key],0)) | Q97: =INDEX(tblDateSummary[Weekday],MATCH(LARGE(tblDateSummary[Rank Key],O97),tblDateSummary[Rank Key],0)) | R97: =INDEX(tblDateSummary[Revenue],MATCH(LARGE(tblDateSummary[Rank Key],O97),tblDateSummary[Rank Key],0)) | S97: =INDEX(tblDateSummary[Events],MATCH(LARGE(tblDateSummary[Rank Key],O97),tblDateSummary[Rank Key],0)) | T97: =INDEX(tblDateSummary[Avg/Event],MATCH(LARGE(tblDateSummary[Rank Key],O97),tblDateSummary[Rank Key],0)) | V97: 46154 | W97: Tuesday | X97: 1 | Y97: 1 | Z97: 85 | AA97: 85 | AB97: 85.000046
A98: 9 | B98: =INDEX(tblWeekSummary[Workweek],MATCH(LARGE(tblWeekSummary[Rank Key],A98),tblWeekSummary[Rank Key],0)) | C98: =INDEX(tblWeekSummary[Revenue],MATCH(LARGE(tblWeekSummary[Rank Key],A98),tblWeekSummary[Rank Key],0)) | D98: =INDEX(tblWeekSummary[Events],MATCH(LARGE(tblWeekSummary[Rank Key],A98),tblWeekSummary[Rank Key],0)) | E98: =INDEX(tblWeekSummary[Worked Days],MATCH(LARGE(tblWeekSummary[Rank Key],A98),tblWeekSummary[Rank Key],0)) | F98: =INDEX(tblWeekSummary[Avg/Event],MATCH(LARGE(tblWeekSummary[Rank Key],A98),tblWeekSummary[Rank Key],0)) | O98: 9 | P98: =INDEX(tblDateSummary[Service Date],MATCH(LARGE(tblDateSummary[Rank Key],O98),tblDateSummary[Rank Key],0)) | Q98: =INDEX(tblDateSummary[Weekday],MATCH(LARGE(tblDateSummary[Rank Key],O98),tblDateSummary[Rank Key],0)) | R98: =INDEX(tblDateSummary[Revenue],MATCH(LARGE(tblDateSummary[Rank Key],O98),tblDateSummary[Rank Key],0)) | S98: =INDEX(tblDateSummary[Events],MATCH(LARGE(tblDateSummary[Rank Key],O98),tblDateSummary[Rank Key],0)) | T98: =INDEX(tblDateSummary[Avg/Event],MATCH(LARGE(tblDateSummary[Rank Key],O98),tblDateSummary[Rank Key],0)) | V98: 46155 | W98: Wednesday | X98: 2 | Y98: 1 | Z98: 50 | AA98: 50 | AB98: 50.000046
A99: 10 | B99: =INDEX(tblWeekSummary[Workweek],MATCH(LARGE(tblWeekSummary[Rank Key],A99),tblWeekSummary[Rank Key],0)) | C99: =INDEX(tblWeekSummary[Revenue],MATCH(LARGE(tblWeekSummary[Rank Key],A99),tblWeekSummary[Rank Key],0)) | D99: =INDEX(tblWeekSummary[Events],MATCH(LARGE(tblWeekSummary[Rank Key],A99),tblWeekSummary[Rank Key],0)) | E99: =INDEX(tblWeekSummary[Worked Days],MATCH(LARGE(tblWeekSummary[Rank Key],A99),tblWeekSummary[Rank Key],0)) | F99: =INDEX(tblWeekSummary[Avg/Event],MATCH(LARGE(tblWeekSummary[Rank Key],A99),tblWeekSummary[Rank Key],0)) | O99: 10 | P99: =INDEX(tblDateSummary[Service Date],MATCH(LARGE(tblDateSummary[Rank Key],O99),tblDateSummary[Rank Key],0)) | Q99: =INDEX(tblDateSummary[Weekday],MATCH(LARGE(tblDateSummary[Rank Key],O99),tblDateSummary[Rank Key],0)) | R99: =INDEX(tblDateSummary[Revenue],MATCH(LARGE(tblDateSummary[Rank Key],O99),tblDateSummary[Rank Key],0)) | S99: =INDEX(tblDateSummary[Events],MATCH(LARGE(tblDateSummary[Rank Key],O99),tblDateSummary[Rank Key],0)) | T99: =INDEX(tblDateSummary[Avg/Event],MATCH(LARGE(tblDateSummary[Rank Key],O99),tblDateSummary[Rank Key],0)) | V99: 46156 | W99: Thursday | X99: 1 | Y99: 1 | Z99: 75 | AA99: 75 | AB99: 75.000046
A100: 11 | B100: =INDEX(tblWeekSummary[Workweek],MATCH(LARGE(tblWeekSummary[Rank Key],A100),tblWeekSummary[Rank Key],0)) | C100: =INDEX(tblWeekSummary[Revenue],MATCH(LARGE(tblWeekSummary[Rank Key],A100),tblWeekSummary[Rank Key],0)) | D100: =INDEX(tblWeekSummary[Events],MATCH(LARGE(tblWeekSummary[Rank Key],A100),tblWeekSummary[Rank Key],0)) | E100: =INDEX(tblWeekSummary[Worked Days],MATCH(LARGE(tblWeekSummary[Rank Key],A100),tblWeekSummary[Rank Key],0)) | F100: =INDEX(tblWeekSummary[Avg/Event],MATCH(LARGE(tblWeekSummary[Rank Key],A100),tblWeekSummary[Rank Key],0)) | O100: 11 | P100: =INDEX(tblDateSummary[Service Date],MATCH(LARGE(tblDateSummary[Rank Key],O100),tblDateSummary[Rank Key],0)) | Q100: =INDEX(tblDateSummary[Weekday],MATCH(LARGE(tblDateSummary[Rank Key],O100),tblDateSummary[Rank Key],0)) | R100: =INDEX(tblDateSummary[Revenue],MATCH(LARGE(tblDateSummary[Rank Key],O100),tblDateSummary[Rank Key],0)) | S100: =INDEX(tblDateSummary[Events],MATCH(LARGE(tblDateSummary[Rank Key],O100),tblDateSummary[Rank Key],0)) | T100: =INDEX(tblDateSummary[Avg/Event],MATCH(LARGE(tblDateSummary[Rank Key],O100),tblDateSummary[Rank Key],0)) | V100: 46157 | W100: Friday | X100: 1 | Y100: 1 | Z100: 45 | AA100: 45 | AB100: 45.000046
A101: 12 | B101: =INDEX(tblWeekSummary[Workweek],MATCH(LARGE(tblWeekSummary[Rank Key],A101),tblWeekSummary[Rank Key],0)) | C101: =INDEX(tblWeekSummary[Revenue],MATCH(LARGE(tblWeekSummary[Rank Key],A101),tblWeekSummary[Rank Key],0)) | D101: =INDEX(tblWeekSummary[Events],MATCH(LARGE(tblWeekSummary[Rank Key],A101),tblWeekSummary[Rank Key],0)) | E101: =INDEX(tblWeekSummary[Worked Days],MATCH(LARGE(tblWeekSummary[Rank Key],A101),tblWeekSummary[Rank Key],0)) | F101: =INDEX(tblWeekSummary[Avg/Event],MATCH(LARGE(tblWeekSummary[Rank Key],A101),tblWeekSummary[Rank Key],0)) | O101: 12 | P101: =INDEX(tblDateSummary[Service Date],MATCH(LARGE(tblDateSummary[Rank Key],O101),tblDateSummary[Rank Key],0)) | Q101: =INDEX(tblDateSummary[Weekday],MATCH(LARGE(tblDateSummary[Rank Key],O101),tblDateSummary[Rank Key],0)) | R101: =INDEX(tblDateSummary[Revenue],MATCH(LARGE(tblDateSummary[Rank Key],O101),tblDateSummary[Rank Key],0)) | S101: =INDEX(tblDateSummary[Events],MATCH(LARGE(tblDateSummary[Rank Key],O101),tblDateSummary[Rank Key],0)) | T101: =INDEX(tblDateSummary[Avg/Event],MATCH(LARGE(tblDateSummary[Rank Key],O101),tblDateSummary[Rank Key],0)) | V101: 46161 | W101: Tuesday | X101: 1 | Y101: 1 | Z101: 50 | AA101: 50 | AB101: 50.000046
V102: 46162 | W102: Wednesday | X102: 1 | Y102: 1 | Z102: 106.67 | AA102: 106.67 | AB102: 106.67005
V103: 46163 | W103: Thursday | X103: 2 | Y103: 2 | Z103: 265.83 | AA103: 132.915 | AB103: 265.83005
V104: 46168 | W104: Tuesday | X104: 2 | Y104: 2 | Z104: 147.91 | AA104: 73.955 | AB104: 147.91005
...

Sheet Exceptions & Audit
A1: Barrister Exception & Integrity Engine — Phase 3H
A3: Formula-driven operational, financial, cross-table, and structural integrity controls
A5: Critical Exceptions | D5: Warnings | G5: Pending Items | J5: Mapping Holds | M5: Duplicate WO Flags | P5: Missing Event Links | S5: Variance Exposure
A6: =COUNTIF(S31:S98,"Critical")+COUNTIF(Q100:Q166,"Critical") | D6: =COUNTIF(S31:S98,"Warning")+COUNTIF(Q100:Q166,"Warning") | G6: =COUNTIF(S31:S98,"Informational")+COUNTIF(Q100:Q166,"Informational") | J6: =COUNTIF(J31:J98,"Yes") | M6: =COUNTIF(H31:H98,"Yes") | P6: =COUNTIF(I31:I98,"Yes") | S6: =SUM(V31:V98)
A9: Current Open Exceptions — Snapshot
A10: Severity | B10: Issue | C10: Event # | D10: WO # | E10: Client | F10: City | G10: Jurisdiction | H10: Amount | I10: Status | J10: Required Action | K10: Source | L10: Notes
A11: Informational | B11: Pending ACH | C11: 52 | D11: 5906380 | E11: Food Lion | F11: Upper Marlboro | G11: MD | H11: 116.24 | I11: ACH missing | J11: Await ACH processing | K11: WO Alias Index + Canonical Ledger | L11: Food Lion payment breakdown confirmed.
A12: Informational | B12: Pending ACH | C12: 55 | D12: 5898645 | E12: Office of MD Senator Angela Alsobrooks | F12: Largo | G12: MD | H12: 120 | I12: ACH missing | J12: Await ACH processing | K12: WO Alias Index + Canonical Ledger | L12: Payment breakdown $120 received; ACH pending.
A13: Informational | B13: Pending ACH | C13: 56 | D13: 5900784 | E13: Dunkin | F13: Reisterstown | G13: MD | H13: 170.66 | I13: ACH missing | J13: Await ACH processing | K13: WO Alias Index + Canonical Ledger | L13: Dunkin Reisterstown payment breakdown confirmed.
A14: Informational | B14: Pending ACH | C14: 57 | D14: 5911577 | E14: Montpelier Liquors | F14: Laurel | G14: MD | H14: 66.74 | I14: ACH missing | J14: Await ACH processing | K14: WO Alias Index + Canonical Ledger | L14: No-access visit paid breakdown.
A15: Informational | B15: Pending ACH | C15: 58 | D15: 5900780 | E15: Dunkin | F15: Lutherville | G15: MD | H15: 202.5 | I15: ACH missing | J15: Await ACH processing | K15: WO Alias Index + Canonical Ledger | L15: Dunkin Lutherville payment breakdown confirmed.
A16: Informational | B16: Pending ACH | C16: 59 | D16: 5900830 | E16: Dunkin | F16: Aberdeen | G16: MD | H16: 250 | I16: ACH missing | J16: Await ACH processing | K16: WO Alias Index + Canonical Ledger | L16: First Aberdeen visit payment breakdown confirmed.
A17: Informational | B17: Pending Breakdown | C17: 60 | D17: 5912364 | E17: Carvana | F17: Baltimore | G17: MD | I17: Combined visit / partial breakdown | J17: Await payment breakdown | K17: WO Alias Index + Canonical Ledger | L17: Alias maps to combined one-visit Carvana event; 5912364 closed by user, breakdown pending.
A18: Warning | B18: Partial Breakdown | C18: 60 | D18: 5914049 | E18: Carvana | F18: Baltimore | G18: MD | H18: 65 | I18: Combined visit / partial breakdown | J18: Confirm remaining work-order breakdown | K18: WO Alias Index + Canonical Ledger | L18: Alias maps to combined one-visit Carvana event; 5914049 breakdown $65 received.
A19: Informational | B19: Pending ACH | C19: 61 | D19: 5909344 | E19: TJ Maxx | F19: Germantown | G19: MD | H19: 194.99 | I19: ACH missing | J19: Await ACH processing | K19: Gmail payment breakdown 2026-07-11 | L19: Payment breakdown confirmed at $194.99; expected payment 2026-07-23; ACH pending.
A20: Warning | B20: Revenue Variance | C20: 62 | D20: 5913868 | E20: TJ Maxx | F20: Martinsburg | G20: WV | H20: 49.17 | I20: BREAKDOWN_MISMATCH | J20: Review and dispute or reconcile the variance | K20: Gmail payment breakdown 2026-07-10 + Phase 1 ledger | L20: Negotiated amount $150.00; payment breakdown received for $100.83; variance -$49.17; expected payment 2026-07-23.
A21: Critical | B21: Mapping Hold | D21: 5905579 | E21: Hebrew Home of Greater Washington | F21: North Bethesda | G21: MD | H21: 35 | I21: MAPPING_HOLD | J21: Resolve WO-to-event ownership before financial closure | K21: Phase 1 duplicate rows consolidated | L21: Duplicate WO collision preserved without guessing. Event 48 legacy breakdown $70; Event 51 legacy breakdown $60; ACH $35. Human mapping required before assigning this WO.
A22: Informational | B22: Pending Breakdown | C22: 63 | D22: 5909368 | E22: Marshalls | F22: Cockeysville | G22: MD | I22: Breakdown pending | J22: Await payment breakdown | K22: WO 5909368 + user completion | L22: Hourly rate $40.00; final payable hours and breakdown pending.
A23: Informational | B23: Pending Breakdown | C23: 64 | D23: 5916961 | E23: Marshalls | F23: Hagerstown | G23: MD | I23: Breakdown pending | J23: Await payment breakdown | K23: WO 5916961 + onsite timeline | L23: Hourly rate $55.00; documented support-driven extended onsite time; final breakdown pending.
A24: Informational | B24: Pending Breakdown | C24: 65 | D24: 5917407 | E24: HomeGoods | F24: Gaithersburg | G24: MD | I24: Breakdown pending | J24: Await payment breakdown | K24: User completion + ticket/photo evidence | L24: Hourly rate $50.00; power cable and pin pad replaced; final breakdown pending.
A25: Informational | B25: Pending Breakdown | C25: 66 | D25: 5909385 | E25: TJ Maxx | F25: Bel Air | G25: MD | I25: Breakdown pending | J25: Await payment breakdown | K25: WO 5909385 + user completion | L25: Hourly rate $45.00; NextGen 11 server refresh completed; final breakdown pending.
A26: Informational | B26: Pending ACH | C26: 67 | D26: 5914898 | E26: Dunkin | F26: Aberdeen | G26: MD | H26: 183.74 | I26: ACH missing | J26: Await ACH processing | K26: Gmail payment breakdown 2026-07-14 + user completion | L26: Return visit completed; $183.74 breakdown confirmed; expected payment 2026-07-28; ACH pending.
A29: Ledger Exception Matrix — Dynamic
A30: Ledger Record ID | B30: WO # | C30: Event # | D30: Client | E30: Breakdown Status | F30: ACH Status | G30: Variance | H30: Duplicate WO | I30: Missing Event Link | J30: Mapping Hold | K30: Missing Breakdown | L30: Pending ACH | M30: Revenue Variance | N30: Missing Client | O30: Missing Location | P30: Unknown Breakdown Status | Q30: Unknown ACH Status | R30: Primary Issue | S30: Severity | T30: Required Action | U30: Open? | V30: Absolute Variance
A31: LED-0001 | B31: =INDEX(tblLedger[Work Order #],MATCH($A31,tblLedger[Ledger Record ID],0)) | C31: =INDEX(tblLedger[Event #],MATCH($A31,tblLedger[Ledger Record ID],0)) | D31: =INDEX(tblLedger[Client],MATCH($A31,tblLedger[Ledger Record ID],0)) | E31: =INDEX(tblLedger[Breakdown Confirmed],MATCH($A31,tblLedger[Ledger Record ID],0)) | F31: =INDEX(tblLedger[ACH Confirmed],MATCH($A31,tblLedger[Ledger Record ID],0)) | G31: =INDEX(tblLedger[Variance],MATCH($A31,tblLedger[Ledger Record ID],0)) | H31: =IF(COUNTIF(tblLedger[Work Order #],B31)>1,"Yes","No") | I31: =IF(C31="","Yes","No") | J31: =IF(INDEX(tblLedger[Mapping Status],MATCH($A31,tblLedger[Ledger Record ID],0))="MAPPING_HOLD","Yes","No") | K31: =IF(AND(OR(E31="No",E31="Pending"),IFERROR(INDEX(tblServiceEvents[Financial Scope],MATCH(C31,tblServiceEvents[Event #],0)),"Included")="Included"),"Yes","No") | L31: =IF(AND(E31="Yes",OR(F31="No",F31="Pending")),"Yes","No") | M31: =IF(OR(ABS(N(G31))>0,INDEX(tblLedger[Reconciliation Status],MATCH($A31,tblLedger[Ledger Record ID],0))="BREAKDOWN_MISMATCH",INDEX(tblLedger[Reconciliation Status],MATCH($A31,tblLedger[Ledger Record ID],0))="ACH_MISMATCH"),"Yes","No") | N31: =IF(D31="","Yes","No") | O31: =IF(OR(INDEX(tblLedger[City],MATCH($A31,tblLedger[Ledger Record ID],0))="",INDEX(tblLedger[Jurisdiction],MATCH($A31,tblLedger[Ledger Record ID],0))=""),"Yes","No") | P31: =IF(COUNTIF({"Yes","No","Partial","Pending","Mapping Hold"},E31)=0,"Yes","No") | Q31: =IF(COUNTIF({"Yes","No","Partial","Pending","Mapping Review"},F31)=0,"Yes","No") | R31: =IF(J31="Yes","Mapping Hold",IF(I31="Yes","Missing Event Link",IF(H31="Yes","Duplicate WO",IF(M31="Yes","Revenue Variance",IF(K31="Yes","Missing Breakdown",IF(L31="Yes","Pending ACH",IF(E31="Partial","Partial Breakdown",IF(N31="Yes","Missing Client",IF(O31="Yes","Missing Location",IF(P31="Yes","Unknown Breakdown Status",IF(Q31="Yes","Unknown ACH Status","OK"))))))))))) | S31: =IF(OR(J31="Yes",I31="Yes",H31="Yes"),"Critical",IF(OR(M31="Yes",E31="Partial",N31="Yes",O31="Yes",P31="Yes",Q31="Yes"),"Warning",IF(OR(K31="Yes",L31="Yes"),"Informational","OK"))) | T31: =IF(R31="Mapping Hold","Resolve mapping before update",IF(R31="Missing Event Link","Map to one authoritative event",IF(R31="Duplicate WO","Review duplicate identity",IF(R31="Revenue Variance","Reconcile or dispute amount",IF(R31="Missing Breakdown","Await breakdown",IF(R31="Pending ACH","Await ACH",IF(R31="Partial Breakdown","Confirm remaining breakdown",IF(R31="Missing Client","Add canonical client",IF(R31="Missing Location","Complete location fields",IF(R31="OK","No action","Review invalid status")))))))))) | U31: =IF(R31="OK","No","Yes") | V31: =ABS(N(G31))
A32: LED-0002 | B32: =INDEX(tblLedger[Work Order #],MATCH($A32,tblLedger[Ledger Record ID],0)) | C32: =INDEX(tblLedger[Event #],MATCH($A32,tblLedger[Ledger Record ID],0)) | D32: =INDEX(tblLedger[Client],MATCH($A32,tblLedger[Ledger Record ID],0)) | E32: =INDEX(tblLedger[Breakdown Confirmed],MATCH($A32,tblLedger[Ledger Record ID],0)) | F32: =INDEX(tblLedger[ACH Confirmed],MATCH($A32,tblLedger[Ledger Record ID],0)) | G32: =INDEX(tblLedger[Variance],MATCH($A32,tblLedger[Ledger Record ID],0)) | H32: =IF(COUNTIF(tblLedger[Work Order #],B32)>1,"Yes","No") | I32: =IF(C32="","Yes","No") | J32: =IF(INDEX(tblLedger[Mapping Status],MATCH($A32,tblLedger[Ledger Record ID],0))="MAPPING_HOLD","Yes","No") | K32: =IF(AND(OR(E32="No",E32="Pending"),IFERROR(INDEX(tblServiceEvents[Financial Scope],MATCH(C32,tblServiceEvents[Event #],0)),"Included")="Included"),"Yes","No") | L32: =IF(AND(E32="Yes",OR(F32="No",F32="Pending")),"Yes","No") | M32: =IF(OR(ABS(N(G32))>0,INDEX(tblLedger[Reconciliation Status],MATCH($A32,tblLedger[Ledger Record ID],0))="BREAKDOWN_MISMATCH",INDEX(tblLedger[Reconciliation Status],MATCH($A32,tblLedger[Ledger Record ID],0))="ACH_MISMATCH"),"Yes","No") | N32: =IF(D32="","Yes","No") | O32: =IF(OR(INDEX(tblLedger[City],MATCH($A32,tblLedger[Ledger Record ID],0))="",INDEX(tblLedger[Jurisdiction],MATCH($A32,tblLedger[Ledger Record ID],0))=""),"Yes","No") | P32: =IF(COUNTIF({"Yes","No","Partial","Pending","Mapping Hold"},E32)=0,"Yes","No") | Q32: =IF(COUNTIF({"Yes","No","Partial","Pending","Mapping Review"},F32)=0,"Yes","No") | R32: =IF(J32="Yes","Mapping Hold",IF(I32="Yes","Missing Event Link",IF(H32="Yes","Duplicate WO",IF(M32="Yes","Revenue Variance",IF(K32="Yes","Missing Breakdown",IF(L32="Yes","Pending ACH",IF(E32="Partial","Partial Breakdown",IF(N32="Yes","Missing Client",IF(O32="Yes","Missing Location",IF(P32="Yes","Unknown Breakdown Status",IF(Q32="Yes","Unknown ACH Status","OK"))))))))))) | S32: =IF(OR(J32="Yes",I32="Yes",H32="Yes"),"Critical",IF(OR(M32="Yes",E32="Partial",N32="Yes",O32="Yes",P32="Yes",Q32="Yes"),"Warning",IF(OR(K32="Yes",L32="Yes"),"Informational","OK"))) | T32: =IF(R32="Mapping Hold","Resolve mapping before update",IF(R32="Missing Event Link","Map to one authoritative event",IF(R32="Duplicate WO","Review duplicate identity",IF(R32="Revenue Variance","Reconcile or dispute amount",IF(R32="Missing Breakdown","Await breakdown",IF(R32="Pending ACH","Await ACH",IF(R32="Partial Breakdown","Confirm remaining breakdown",IF(R32="Missing Client","Add canonical client",IF(R32="Missing Location","Complete location fields",IF(R32="OK","No action","Review invalid status")))))))))) | U32: =IF(R32="OK","No","Yes") | V32: =ABS(N(G32))
A33: LED-0003 | B33: =INDEX(tblLedger[Work Order #],MATCH($A33,tblLedger[Ledger Record ID],0)) | C33: =INDEX(tblLedger[Event #],MATCH($A33,tblLedger[Ledger Record ID],0)) | D33: =INDEX(tblLedger[Client],MATCH($A33,tblLedger[Ledger Record ID],0)) | E33: =INDEX(tblLedger[Breakdown Confirmed],MATCH($A33,tblLedger[Ledger Record ID],0)) | F33: =INDEX(tblLedger[ACH Confirmed],MATCH($A33,tblLedger[Ledger Record ID],0)) | G33: =INDEX(tblLedger[Variance],MATCH($A33,tblLedger[Ledger Record ID],0)) | H33: =IF(COUNTIF(tblLedger[Work Order #],B33)>1,"Yes","No") | I33: =IF(C33="","Yes","No") | J33: =IF(INDEX(tblLedger[Mapping Status],MATCH($A33,tblLedger[Ledger Record ID],0))="MAPPING_HOLD","Yes","No") | K33: =IF(AND(OR(E33="No",E33="Pending"),IFERROR(INDEX(tblServiceEvents[Financial Scope],MATCH(C33,tblServiceEvents[Event #],0)),"Included")="Included"),"Yes","No") | L33: =IF(AND(E33="Yes",OR(F33="No",F33="Pending")),"Yes","No") | M33: =IF(OR(ABS(N(G33))>0,INDEX(tblLedger[Reconciliation Status],MATCH($A33,tblLedger[Ledger Record ID],0))="BREAKDOWN_MISMATCH",INDEX(tblLedger[Reconciliation Status],MATCH($A33,tblLedger[Ledger Record ID],0))="ACH_MISMATCH"),"Yes","No") | N33: =IF(D33="","Yes","No") | O33: =IF(OR(INDEX(tblLedger[City],MATCH($A33,tblLedger[Ledger Record ID],0))="",INDEX(tblLedger[Jurisdiction],MATCH($A33,tblLedger[Ledger Record ID],0))=""),"Yes","No") | P33: =IF(COUNTIF({"Yes","No","Partial","Pending","Mapping Hold"},E33)=0,"Yes","No") | Q33: =IF(COUNTIF({"Yes","No","Partial","Pending","Mapping Review"},F33)=0,"Yes","No") | R33: =IF(J33="Yes","Mapping Hold",IF(I33="Yes","Missing Event Link",IF(H33="Yes","Duplicate WO",IF(M33="Yes","Revenue Variance",IF(K33="Yes","Missing Breakdown",IF(L33="Yes","Pending ACH",IF(E33="Partial","Partial Breakdown",IF(N33="Yes","Missing Client",IF(O33="Yes","Missing Location",IF(P33="Yes","Unknown Breakdown Status",IF(Q33="Yes","Unknown ACH Status","OK"))))))))))) | S33: =IF(OR(J33="Yes",I33="Yes",H33="Yes"),"Critical",IF(OR(M33="Yes",E33="Partial",N33="Yes",O33="Yes",P33="Yes",Q33="Yes"),"Warning",IF(OR(K33="Yes",L33="Yes"),"Informational","OK"))) | T33: =IF(R33="Mapping Hold","Resolve mapping before update",IF(R33="Missing Event Link","Map to one authoritative event",IF(R33="Duplicate WO","Review duplicate identity",IF(R33="Revenue Variance","Reconcile or dispute amount",IF(R33="Missing Breakdown","Await breakdown",IF(R33="Pending ACH","Await ACH",IF(R33="Partial Breakdown","Confirm remaining breakdown",IF(R33="Missing Client","Add canonical client",IF(R33="Missing Location","Complete location fields",IF(R33="OK","No action","Review invalid status")))))))))) | U33: =IF(R33="OK","No","Yes") | V33: =ABS(N(G33))
A34: LED-0004 | B34: =INDEX(tblLedger[Work Order #],MATCH($A34,tblLedger[Ledger Record ID],0)) | C34: =INDEX(tblLedger[Event #],MATCH($A34,tblLedger[Ledger Record ID],0)) | D34: =INDEX(tblLedger[Client],MATCH($A34,tblLedger[Ledger Record ID],0)) | E34: =INDEX(tblLedger[Breakdown Confirmed],MATCH($A34,tblLedger[Ledger Record ID],0)) | F34: =INDEX(tblLedger[ACH Confirmed],MATCH($A34,tblLedger[Ledger Record ID],0)) | G34: =INDEX(tblLedger[Variance],MATCH($A34,tblLedger[Ledger Record ID],0)) | H34: =IF(COUNTIF(tblLedger[Work Order #],B34)>1,"Yes","No") | I34: =IF(C34="","Yes","No") | J34: =IF(INDEX(tblLedger[Mapping Status],MATCH($A34,tblLedger[Ledger Record ID],0))="MAPPING_HOLD","Yes","No") | K34: =IF(AND(OR(E34="No",E34="Pending"),IFERROR(INDEX(tblServiceEvents[Financial Scope],MATCH(C34,tblServiceEvents[Event #],0)),"Included")="Included"),"Yes","No") | L34: =IF(AND(E34="Yes",OR(F34="No",F34="Pending")),"Yes","No") | M34: =IF(OR(ABS(N(G34))>0,INDEX(tblLedger[Reconciliation Status],MATCH($A34,tblLedger[Ledger Record ID],0))="BREAKDOWN_MISMATCH",INDEX(tblLedger[Reconciliation Status],MATCH($A34,tblLedger[Ledger Record ID],0))="ACH_MISMATCH"),"Yes","No") | N34: =IF(D34="","Yes","No") | O34: =IF(OR(INDEX(tblLedger[City],MATCH($A34,tblLedger[Ledger Record ID],0))="",INDEX(tblLedger[Jurisdiction],MATCH($A34,tblLedger[Ledger Record ID],0))=""),"Yes","No") | P34: =IF(COUNTIF({"Yes","No","Partial","Pending","Mapping Hold"},E34)=0,"Yes","No") | Q34: =IF(COUNTIF({"Yes","No","Partial","Pending","Mapping Review"},F34)=0,"Yes","No") | R34: =IF(J34="Yes","Mapping Hold",IF(I34="Yes","Missing Event Link",IF(H34="Yes","Duplicate WO",IF(M34="Yes","Revenue Variance",IF(K34="Yes","Missing Breakdown",IF(L34="Yes","Pending ACH",IF(E34="Partial","Partial Breakdown",IF(N34="Yes","Missing Client",IF(O34="Yes","Missing Location",IF(P34="Yes","Unknown Breakdown Status",IF(Q34="Yes","Unknown ACH Status","OK"))))))))))) | S34: =IF(OR(J34="Yes",I34="Yes",H34="Yes"),"Critical",IF(OR(M34="Yes",E34="Partial",N34="Yes",O34="Yes",P34="Yes",Q34="Yes"),"Warning",IF(OR(K34="Yes",L34="Yes"),"Informational","OK"))) | T34: =IF(R34="Mapping Hold","Resolve mapping before update",IF(R34="Missing Event Link","Map to one authoritative event",IF(R34="Duplicate WO","Review duplicate identity",IF(R34="Revenue Variance","Reconcile or dispute amount",IF(R34="Missing Breakdown","Await breakdown",IF(R34="Pending ACH","Await ACH",IF(R34="Partial Breakdown","Confirm remaining breakdown",IF(R34="Missing Client","Add canonical client",IF(R34="Missing Location","Complete location fields",IF(R34="OK","No action","Review invalid status")))))))))) | U34: =IF(R34="OK","No","Yes") | V34: =ABS(N(G34))
A35: LED-0005 | B35: =INDEX(tblLedger[Work Order #],MATCH($A35,tblLedger[Ledger Record ID],0)) | C35: =INDEX(tblLedger[Event #],MATCH($A35,tblLedger[Ledger Record ID],0)) | D35: =INDEX(tblLedger[Client],MATCH($A35,tblLedger[Ledger Record ID],0)) | E35: =INDEX(tblLedger[Breakdown Confirmed],MATCH($A35,tblLedger[Ledger Record ID],0)) | F35: =INDEX(tblLedger[ACH Confirmed],MATCH($A35,tblLedger[Ledger Record ID],0)) | G35: =INDEX(tblLedger[Variance],MATCH($A35,tblLedger[Ledger Record ID],0)) | H35: =IF(COUNTIF(tblLedger[Work Order #],B35)>1,"Yes","No") | I35: =IF(C35="","Yes","No") | J35: =IF(INDEX(tblLedger[Mapping Status],MATCH($A35,tblLedger[Ledger Record ID],0))="MAPPING_HOLD","Yes","No") | K35: =IF(AND(OR(E35="No",E35="Pending"),IFERROR(INDEX(tblServiceEvents[Financial Scope],MATCH(C35,tblServiceEvents[Event #],0)),"Included")="Included"),"Yes","No") | L35: =IF(AND(E35="Yes",OR(F35="No",F35="Pending")),"Yes","No") | M35: =IF(OR(ABS(N(G35))>0,INDEX(tblLedger[Reconciliation Status],MATCH($A35,tblLedger[Ledger Record ID],0))="BREAKDOWN_MISMATCH",INDEX(tblLedger[Reconciliation Status],MATCH($A35,tblLedger[Ledger Record ID],0))="ACH_MISMATCH"),"Yes","No") | N35: =IF(D35="","Yes","No") | O35: =IF(OR(INDEX(tblLedger[City],MATCH($A35,tblLedger[Ledger Record ID],0))="",INDEX(tblLedger[Jurisdiction],MATCH($A35,tblLedger[Ledger Record ID],0))=""),"Yes","No") | P35: =IF(COUNTIF({"Yes","No","Partial","Pending","Mapping Hold"},E35)=0,"Yes","No") | Q35: =IF(COUNTIF({"Yes","No","Partial","Pending","Mapping Review"},F35)=0,"Yes","No") | R35: =IF(J35="Yes","Mapping Hold",IF(I35="Yes","Missing Event Link",IF(H35="Yes","Duplicate WO",IF(M35="Yes","Revenue Variance",IF(K35="Yes","Missing Breakdown",IF(L35="Yes","Pending ACH",IF(E35="Partial","Partial Breakdown",IF(N35="Yes","Missing Client",IF(O35="Yes","Missing Location",IF(P35="Yes","Unknown Breakdown Status",IF(Q35="Yes","Unknown ACH Status","OK"))))))))))) | S35: =IF(OR(J35="Yes",I35="Yes",H35="Yes"),"Critical",IF(OR(M35="Yes",E35="Partial",N35="Yes",O35="Yes",P35="Yes",Q35="Yes"),"Warning",IF(OR(K35="Yes",L35="Yes"),"Informational","OK"))) | T35: =IF(R35="Mapping Hold","Resolve mapping before update",IF(R35="Missing Event Link","Map to one authoritative event",IF(R35="Duplicate WO","Review duplicate identity",IF(R35="Revenue Variance","Reconcile or dispute amount",IF(R35="Missing Breakdown","Await breakdown",IF(R35="Pending ACH","Await ACH",IF(R35="Partial Breakdown","Confirm remaining breakdown",IF(R35="Missing Client","Add canonical client",IF(R35="Missing Location","Complete location fields",IF(R35="OK","No action","Review invalid status")))))))))) | U35: =IF(R35="OK","No","Yes") | V35: =ABS(N(G35))
A36: LED-0006 | B36: =INDEX(tblLedger[Work Order #],MATCH($A36,tblLedger[Ledger Record ID],0)) | C36: =INDEX(tblLedger[Event #],MATCH($A36,tblLedger[Ledger Record ID],0)) | D36: =INDEX(tblLedger[Client],MATCH($A36,tblLedger[Ledger Record ID],0)) | E36: =INDEX(tblLedger[Breakdown Confirmed],MATCH($A36,tblLedger[Ledger Record ID],0)) | F36: =INDEX(tblLedger[ACH Confirmed],MATCH($A36,tblLedger[Ledger Record ID],0)) | G36: =INDEX(tblLedger[Variance],MATCH($A36,tblLedger[Ledger Record ID],0)) | H36: =IF(COUNTIF(tblLedger[Work Order #],B36)>1,"Yes","No") | I36: =IF(C36="","Yes","No") | J36: =IF(INDEX(tblLedger[Mapping Status],MATCH($A36,tblLedger[Ledger Record ID],0))="MAPPING_HOLD","Yes","No") | K36: =IF(AND(OR(E36="No",E36="Pending"),IFERROR(INDEX(tblServiceEvents[Financial Scope],MATCH(C36,tblServiceEvents[Event #],0)),"Included")="Included"),"Yes","No") | L36: =IF(AND(E36="Yes",OR(F36="No",F36="Pending")),"Yes","No") | M36: =IF(OR(ABS(N(G36))>0,INDEX(tblLedger[Reconciliation Status],MATCH($A36,tblLedger[Ledger Record ID],0))="BREAKDOWN_MISMATCH",INDEX(tblLedger[Reconciliation Status],MATCH($A36,tblLedger[Ledger Record ID],0))="ACH_MISMATCH"),"Yes","No") | N36: =IF(D36="","Yes","No") | O36: =IF(OR(INDEX(tblLedger[City],MATCH($A36,tblLedger[Ledger Record ID],0))="",INDEX(tblLedger[Jurisdiction],MATCH($A36,tblLedger[Ledger Record ID],0))=""),"Yes","No") | P36: =IF(COUNTIF({"Yes","No","Partial","Pending","Mapping Hold"},E36)=0,"Yes","No") | Q36: =IF(COUNTIF({"Yes","No","Partial","Pending","Mapping Review"},F36)=0,"Yes","No") | R36: =IF(J36="Yes","Mapping Hold",IF(I36="Yes","Missing Event Link",IF(H36="Yes","Duplicate WO",IF(M36="Yes","Revenue Variance",IF(K36="Yes","Missing Breakdown",IF(L36="Yes","Pending ACH",IF(E36="Partial","Partial Breakdown",IF(N36="Yes","Missing Client",IF(O36="Yes","Missing Location",IF(P36="Yes","Unknown Breakdown Status",IF(Q36="Yes","Unknown ACH Status","OK"))))))))))) | S36: =IF(OR(J36="Yes",I36="Yes",H36="Yes"),"Critical",IF(OR(M36="Yes",E36="Partial",N36="Yes",O36="Yes",P36="Yes",Q36="Yes"),"Warning",IF(OR(K36="Yes",L36="Yes"),"Informational","OK"))) | T36: =IF(R36="Mapping Hold","Resolve mapping before update",IF(R36="Missing Event Link","Map to one authoritative event",IF(R36="Duplicate WO","Review duplicate identity",IF(R36="Revenue Variance","Reconcile or dispute amount",IF(R36="Missing Breakdown","Await breakdown",IF(R36="Pending ACH","Await ACH",IF(R36="Partial Breakdown","Confirm remaining breakdown",IF(R36="Missing Client","Add canonical client",IF(R36="Missing Location","Complete location fields",IF(R36="OK","No action","Review invalid status")))))))))) | U36: =IF(R36="OK","No","Yes") | V36: =ABS(N(G36))
A37: LED-0007 | B37: =INDEX(tblLedger[Work Order #],MATCH($A37,tblLedger[Ledger Record ID],0)) | C37: =INDEX(tblLedger[Event #],MATCH($A37,tblLedger[Ledger Record ID],0)) | D37: =INDEX(tblLedger[Client],MATCH($A37,tblLedger[Ledger Record ID],0)) | E37: =INDEX(tblLedger[Breakdown Confirmed],MATCH($A37,tblLedger[Ledger Record ID],0)) | F37: =INDEX(tblLedger[ACH Confirmed],MATCH($A37,tblLedger[Ledger Record ID],0)) | G37: =INDEX(tblLedger[Variance],MATCH($A37,tblLedger[Ledger Record ID],0)) | H37: =IF(COUNTIF(tblLedger[Work Order #],B37)>1,"Yes","No") | I37: =IF(C37="","Yes","No") | J37: =IF(INDEX(tblLedger[Mapping Status],MATCH($A37,tblLedger[Ledger Record ID],0))="MAPPING_HOLD","Yes","No") | K37: =IF(AND(OR(E37="No",E37="Pending"),IFERROR(INDEX(tblServiceEvents[Financial Scope],MATCH(C37,tblServiceEvents[Event #],0)),"Included")="Included"),"Yes","No") | L37: =IF(AND(E37="Yes",OR(F37="No",F37="Pending")),"Yes","No") | M37: =IF(OR(ABS(N(G37))>0,INDEX(tblLedger[Reconciliation Status],MATCH($A37,tblLedger[Ledger Record ID],0))="BREAKDOWN_MISMATCH",INDEX(tblLedger[Reconciliation Status],MATCH($A37,tblLedger[Ledger Record ID],0))="ACH_MISMATCH"),"Yes","No") | N37: =IF(D37="","Yes","No") | O37: =IF(OR(INDEX(tblLedger[City],MATCH($A37,tblLedger[Ledger Record ID],0))="",INDEX(tblLedger[Jurisdiction],MATCH($A37,tblLedger[Ledger Record ID],0))=""),"Yes","No") | P37: =IF(COUNTIF({"Yes","No","Partial","Pending","Mapping Hold"},E37)=0,"Yes","No") | Q37: =IF(COUNTIF({"Yes","No","Partial","Pending","Mapping Review"},F37)=0,"Yes","No") | R37: =IF(J37="Yes","Mapping Hold",IF(I37="Yes","Missing Event Link",IF(H37="Yes","Duplicate WO",IF(M37="Yes","Revenue Variance",IF(K37="Yes","Missing Breakdown",IF(L37="Yes","Pending ACH",IF(E37="Partial","Partial Breakdown",IF(N37="Yes","Missing Client",IF(O37="Yes","Missing Location",IF(P37="Yes","Unknown Breakdown Status",IF(Q37="Yes","Unknown ACH Status","OK"))))))))))) | S37: =IF(OR(J37="Yes",I37="Yes",H37="Yes"),"Critical",IF(OR(M37="Yes",E37="Partial",N37="Yes",O37="Yes",P37="Yes",Q37="Yes"),"Warning",IF(OR(K37="Yes",L37="Yes"),"Informational","OK"))) | T37: =IF(R37="Mapping Hold","Resolve mapping before update",IF(R37="Missing Event Link","Map to one authoritative event",IF(R37="Duplicate WO","Review duplicate identity",IF(R37="Revenue Variance","Reconcile or dispute amount",IF(R37="Missing Breakdown","Await breakdown",IF(R37="Pending ACH","Await ACH",IF(R37="Partial Breakdown","Confirm remaining breakdown",IF(R37="Missing Client","Add canonical client",IF(R37="Missing Location","Complete location fields",IF(R37="OK","No action","Review invalid status")))))))))) | U37: =IF(R37="OK","No","Yes") | V37: =ABS(N(G37))
A38: LED-0008 | B38: =INDEX(tblLedger[Work Order #],MATCH($A38,tblLedger[Ledger Record ID],0)) | C38: =INDEX(tblLedger[Event #],MATCH($A38,tblLedger[Ledger Record ID],0)) | D38: =INDEX(tblLedger[Client],MATCH($A38,tblLedger[Ledger Record ID],0)) | E38: =INDEX(tblLedger[Breakdown Confirmed],MATCH($A38,tblLedger[Ledger Record ID],0)) | F38: =INDEX(tblLedger[ACH Confirmed],MATCH($A38,tblLedger[Ledger Record ID],0)) | G38: =INDEX(tblLedger[Variance],MATCH($A38,tblLedger[Ledger Record ID],0)) | H38: =IF(COUNTIF(tblLedger[Work Order #],B38)>1,"Yes","No") | I38: =IF(C38="","Yes","No") | J38: =IF(INDEX(tblLedger[Mapping Status],MATCH($A38,tblLedger[Ledger Record ID],0))="MAPPING_HOLD","Yes","No") | K38: =IF(AND(OR(E38="No",E38="Pending"),IFERROR(INDEX(tblServiceEvents[Financial Scope],MATCH(C38,tblServiceEvents[Event #],0)),"Included")="Included"),"Yes","No") | L38: =IF(AND(E38="Yes",OR(F38="No",F38="Pending")),"Yes","No") | M38: =IF(OR(ABS(N(G38))>0,INDEX(tblLedger[Reconciliation Status],MATCH($A38,tblLedger[Ledger Record ID],0))="BREAKDOWN_MISMATCH",INDEX(tblLedger[Reconciliation Status],MATCH($A38,tblLedger[Ledger Record ID],0))="ACH_MISMATCH"),"Yes","No") | N38: =IF(D38="","Yes","No") | O38: =IF(OR(INDEX(tblLedger[City],MATCH($A38,tblLedger[Ledger Record ID],0))="",INDEX(tblLedger[Jurisdiction],MATCH($A38,tblLedger[Ledger Record ID],0))=""),"Yes","No") | P38: =IF(COUNTIF({"Yes","No","Partial","Pending","Mapping Hold"},E38)=0,"Yes","No") | Q38: =IF(COUNTIF({"Yes","No","Partial","Pending","Mapping Review"},F38)=0,"Yes","No") | R38: =IF(J38="Yes","Mapping Hold",IF(I38="Yes","Missing Event Link",IF(H38="Yes","Duplicate WO",IF(M38="Yes","Revenue Variance",IF(K38="Yes","Missing Breakdown",IF(L38="Yes","Pending ACH",IF(E38="Partial","Partial Breakdown",IF(N38="Yes","Missing Client",IF(O38="Yes","Missing Location",IF(P38="Yes","Unknown Breakdown Status",IF(Q38="Yes","Unknown ACH Status","OK"))))))))))) | S38: =IF(OR(J38="Yes",I38="Yes",H38="Yes"),"Critical",IF(OR(M38="Yes",E38="Partial",N38="Yes",O38="Yes",P38="Yes",Q38="Yes"),"Warning",IF(OR(K38="Yes",L38="Yes"),"Informational","OK"))) | T38: =IF(R38="Mapping Hold","Resolve mapping before update",IF(R38="Missing Event Link","Map to one authoritative event",IF(R38="Duplicate WO","Review duplicate identity",IF(R38="Revenue Variance","Reconcile or dispute amount",IF(R38="Missing Breakdown","Await breakdown",IF(R38="Pending ACH","Await ACH",IF(R38="Partial Breakdown","Confirm remaining breakdown",IF(R38="Missing Client","Add canonical client",IF(R38="Missing Location","Complete location fields",IF(R38="OK","No action","Review invalid status")))))))))) | U38: =IF(R38="OK","No","Yes") | V38: =ABS(N(G38))
A39: LED-0009 | B39: =INDEX(tblLedger[Work Order #],MATCH($A39,tblLedger[Ledger Record ID],0)) | C39: =INDEX(tblLedger[Event #],MATCH($A39,tblLedger[Ledger Record ID],0)) | D39: =INDEX(tblLedger[Client],MATCH($A39,tblLedger[Ledger Record ID],0)) | E39: =INDEX(tblLedger[Breakdown Confirmed],MATCH($A39,tblLedger[Ledger Record ID],0)) | F39: =INDEX(tblLedger[ACH Confirmed],MATCH($A39,tblLedger[Ledger Record ID],0)) | G39: =INDEX(tblLedger[Variance],MATCH($A39,tblLedger[Ledger Record ID],0)) | H39: =IF(COUNTIF(tblLedger[Work Order #],B39)>1,"Yes","No") | I39: =IF(C39="","Yes","No") | J39: =IF(INDEX(tblLedger[Mapping Status],MATCH($A39,tblLedger[Ledger Record ID],0))="MAPPING_HOLD","Yes","No") | K39: =IF(AND(OR(E39="No",E39="Pending"),IFERROR(INDEX(tblServiceEvents[Financial Scope],MATCH(C39,tblServiceEvents[Event #],0)),"Included")="Included"),"Yes","No") | L39: =IF(AND(E39="Yes",OR(F39="No",F39="Pending")),"Yes","No") | M39: =IF(OR(ABS(N(G39))>0,INDEX(tblLedger[Reconciliation Status],MATCH($A39,tblLedger[Ledger Record ID],0))="BREAKDOWN_MISMATCH",INDEX(tblLedger[Reconciliation Status],MATCH($A39,tblLedger[Ledger Record ID],0))="ACH_MISMATCH"),"Yes","No") | N39: =IF(D39="","Yes","No") | O39: =IF(OR(INDEX(tblLedger[City],MATCH($A39,tblLedger[Ledger Record ID],0))="",INDEX(tblLedger[Jurisdiction],MATCH($A39,tblLedger[Ledger Record ID],0))=""),"Yes","No") | P39: =IF(COUNTIF({"Yes","No","Partial","Pending","Mapping Hold"},E39)=0,"Yes","No") | Q39: =IF(COUNTIF({"Yes","No","Partial","Pending","Mapping Review"},F39)=0,"Yes","No") | R39: =IF(J39="Yes","Mapping Hold",IF(I39="Yes","Missing Event Link",IF(H39="Yes","Duplicate WO",IF(M39="Yes","Revenue Variance",IF(K39="Yes","Missing Breakdown",IF(L39="Yes","Pending ACH",IF(E39="Partial","Partial Breakdown",IF(N39="Yes","Missing Client",IF(O39="Yes","Missing Location",IF(P39="Yes","Unknown Breakdown Status",IF(Q39="Yes","Unknown ACH Status","OK"))))))))))) | S39: =IF(OR(J39="Yes",I39="Yes",H39="Yes"),"Critical",IF(OR(M39="Yes",E39="Partial",N39="Yes",O39="Yes",P39="Yes",Q39="Yes"),"Warning",IF(OR(K39="Yes",L39="Yes"),"Informational","OK"))) | T39: =IF(R39="Mapping Hold","Resolve mapping before update",IF(R39="Missing Event Link","Map to one authoritative event",IF(R39="Duplicate WO","Review duplicate identity",IF(R39="Revenue Variance","Reconcile or dispute amount",IF(R39="Missing Breakdown","Await breakdown",IF(R39="Pending ACH","Await ACH",IF(R39="Partial Breakdown","Confirm remaining breakdown",IF(R39="Missing Client","Add canonical client",IF(R39="Missing Location","Complete location fields",IF(R39="OK","No action","Review invalid status")))))))))) | U39: =IF(R39="OK","No","Yes") | V39: =ABS(N(G39))
A40: LED-0010 | B40: =INDEX(tblLedger[Work Order #],MATCH($A40,tblLedger[Ledger Record ID],0)) | C40: =INDEX(tblLedger[Event #],MATCH($A40,tblLedger[Ledger Record ID],0)) | D40: =INDEX(tblLedger[Client],MATCH($A40,tblLedger[Ledger Record ID],0)) | E40: =INDEX(tblLedger[Breakdown Confirmed],MATCH($A40,tblLedger[Ledger Record ID],0)) | F40: =INDEX(tblLedger[ACH Confirmed],MATCH($A40,tblLedger[Ledger Record ID],0)) | G40: =INDEX(tblLedger[Variance],MATCH($A40,tblLedger[Ledger Record ID],0)) | H40: =IF(COUNTIF(tblLedger[Work Order #],B40)>1,"Yes","No") | I40: =IF(C40="","Yes","No") | J40: =IF(INDEX(tblLedger[Mapping Status],MATCH($A40,tblLedger[Ledger Record ID],0))="MAPPING_HOLD","Yes","No") | K40: =IF(AND(OR(E40="No",E40="Pending"),IFERROR(INDEX(tblServiceEvents[Financial Scope],MATCH(C40,tblServiceEvents[Event #],0)),"Included")="Included"),"Yes","No") | L40: =IF(AND(E40="Yes",OR(F40="No",F40="Pending")),"Yes","No") | M40: =IF(OR(ABS(N(G40))>0,INDEX(tblLedger[Reconciliation Status],MATCH($A40,tblLedger[Ledger Record ID],0))="BREAKDOWN_MISMATCH",INDEX(tblLedger[Reconciliation Status],MATCH($A40,tblLedger[Ledger Record ID],0))="ACH_MISMATCH"),"Yes","No") | N40: =IF(D40="","Yes","No") | O40: =IF(OR(INDEX(tblLedger[City],MATCH($A40,tblLedger[Ledger Record ID],0))="",INDEX(tblLedger[Jurisdiction],MATCH($A40,tblLedger[Ledger Record ID],0))=""),"Yes","No") | P40: =IF(COUNTIF({"Yes","No","Partial","Pending","Mapping Hold"},E40)=0,"Yes","No") | Q40: =IF(COUNTIF({"Yes","No","Partial","Pending","Mapping Review"},F40)=0,"Yes","No") | R40: =IF(J40="Yes","Mapping Hold",IF(I40="Yes","Missing Event Link",IF(H40="Yes","Duplicate WO",IF(M40="Yes","Revenue Variance",IF(K40="Yes","Missing Breakdown",IF(L40="Yes","Pending ACH",IF(E40="Partial","Partial Breakdown",IF(N40="Yes","Missing Client",IF(O40="Yes","Missing Location",IF(P40="Yes","Unknown Breakdown Status",IF(Q40="Yes","Unknown ACH Status","OK"))))))))))) | S40: =IF(OR(J40="Yes",I40="Yes",H40="Yes"),"Critical",IF(OR(M40="Yes",E40="Partial",N40="Yes",O40="Yes",P40="Yes",Q40="Yes"),"Warning",IF(OR(K40="Yes",L40="Yes"),"Informational","OK"))) | T40: =IF(R40="Mapping Hold","Resolve mapping before update",IF(R40="Missing Event Link","Map to one authoritative event",IF(R40="Duplicate WO","Review duplicate identity",IF(R40="Revenue Variance","Reconcile or dispute amount",IF(R40="Missing Breakdown","Await breakdown",IF(R40="Pending ACH","Await ACH",IF(R40="Partial Breakdown","Confirm remaining breakdown",IF(R40="Missing Client","Add canonical client",IF(R40="Missing Location","Complete location fields",IF(R40="OK","No action","Review invalid status")))))))))) | U40: =IF(R40="OK","No","Yes") | V40: =ABS(N(G40))
A41: LED-0011 | B41: =INDEX(tblLedger[Work Order #],MATCH($A41,tblLedger[Ledger Record ID],0)) | C41: =INDEX(tblLedger[Event #],MATCH($A41,tblLedger[Ledger Record ID],0)) | D41: =INDEX(tblLedger[Client],MATCH($A41,tblLedger[Ledger Record ID],0)) | E41: =INDEX(tblLedger[Breakdown Confirmed],MATCH($A41,tblLedger[Ledger Record ID],0)) | F41: =INDEX(tblLedger[ACH Confirmed],MATCH($A41,tblLedger[Ledger Record ID],0)) | G41: =INDEX(tblLedger[Variance],MATCH($A41,tblLedger[Ledger Record ID],0)) | H41: =IF(COUNTIF(tblLedger[Work Order #],B41)>1,"Yes","No") | I41: =IF(C41="","Yes","No") | J41: =IF(INDEX(tblLedger[Mapping Status],MATCH($A41,tblLedger[Ledger Record ID],0))="MAPPING_HOLD","Yes","No") | K41: =IF(AND(OR(E41="No",E41="Pending"),IFERROR(INDEX(tblServiceEvents[Financial Scope],MATCH(C41,tblServiceEvents[Event #],0)),"Included")="Included"),"Yes","No") | L41: =IF(AND(E41="Yes",OR(F41="No",F41="Pending")),"Yes","No") | M41: =IF(OR(ABS(N(G41))>0,INDEX(tblLedger[Reconciliation Status],MATCH($A41,tblLedger[Ledger Record ID],0))="BREAKDOWN_MISMATCH",INDEX(tblLedger[Reconciliation Status],MATCH($A41,tblLedger[Ledger Record ID],0))="ACH_MISMATCH"),"Yes","No") | N41: =IF(D41="","Yes","No") | O41: =IF(OR(INDEX(tblLedger[City],MATCH($A41,tblLedger[Ledger Record ID],0))="",INDEX(tblLedger[Jurisdiction],MATCH($A41,tblLedger[Ledger Record ID],0))=""),"Yes","No") | P41: =IF(COUNTIF({"Yes","No","Partial","Pending","Mapping Hold"},E41)=0,"Yes","No") | Q41: =IF(COUNTIF({"Yes","No","Partial","Pending","Mapping Review"},F41)=0,"Yes","No") | R41: =IF(J41="Yes","Mapping Hold",IF(I41="Yes","Missing Event Link",IF(H41="Yes","Duplicate WO",IF(M41="Yes","Revenue Variance",IF(K41="Yes","Missing Breakdown",IF(L41="Yes","Pending ACH",IF(E41="Partial","Partial Breakdown",IF(N41="Yes","Missing Client",IF(O41="Yes","Missing Location",IF(P41="Yes","Unknown Breakdown Status",IF(Q41="Yes","Unknown ACH Status","OK"))))))))))) | S41: =IF(OR(J41="Yes",I41="Yes",H41="Yes"),"Critical",IF(OR(M41="Yes",E41="Partial",N41="Yes",O41="Yes",P41="Yes",Q41="Yes"),"Warning",IF(OR(K41="Yes",L41="Yes"),"Informational","OK"))) | T41: =IF(R41="Mapping Hold","Resolve mapping before update",IF(R41="Missing Event Link","Map to one authoritative event",IF(R41="Duplicate WO","Review duplicate identity",IF(R41="Revenue Variance","Reconcile or dispute amount",IF(R41="Missing Breakdown","Await breakdown",IF(R41="Pending ACH","Await ACH",IF(R41="Partial Breakdown","Confirm remaining breakdown",IF(R41="Missing Client","Add canonical client",IF(R41="Missing Location","Complete location fields",IF(R41="OK","No action","Review invalid status")))))))))) | U41: =IF(R41="OK","No","Yes") | V41: =ABS(N(G41))
A42: LED-0012 | B42: =INDEX(tblLedger[Work Order #],MATCH($A42,tblLedger[Ledger Record ID],0)) | C42: =INDEX(tblLedger[Event #],MATCH($A42,tblLedger[Ledger Record ID],0)) | D42: =INDEX(tblLedger[Client],MATCH($A42,tblLedger[Ledger Record ID],0)) | E42: =INDEX(tblLedger[Breakdown Confirmed],MATCH($A42,tblLedger[Ledger Record ID],0)) | F42: =INDEX(tblLedger[ACH Confirmed],MATCH($A42,tblLedger[Ledger Record ID],0)) | G42: =INDEX(tblLedger[Variance],MATCH($A42,tblLedger[Ledger Record ID],0)) | H42: =IF(COUNTIF(tblLedger[Work Order #],B42)>1,"Yes","No") | I42: =IF(C42="","Yes","No") | J42: =IF(INDEX(tblLedger[Mapping Status],MATCH($A42,tblLedger[Ledger Record ID],0))="MAPPING_HOLD","Yes","No") | K42: =IF(AND(OR(E42="No",E42="Pending"),IFERROR(INDEX(tblServiceEvents[Financial Scope],MATCH(C42,tblServiceEvents[Event #],0)),"Included")="Included"),"Yes","No") | L42: =IF(AND(E42="Yes",OR(F42="No",F42="Pending")),"Yes","No") | M42: =IF(OR(ABS(N(G42))>0,INDEX(tblLedger[Reconciliation Status],MATCH($A42,tblLedger[Ledger Record ID],0))="BREAKDOWN_MISMATCH",INDEX(tblLedger[Reconciliation Status],MATCH($A42,tblLedger[Ledger Record ID],0))="ACH_MISMATCH"),"Yes","No") | N42: =IF(D42="","Yes","No") | O42: =IF(OR(INDEX(tblLedger[City],MATCH($A42,tblLedger[Ledger Record ID],0))="",INDEX(tblLedger[Jurisdiction],MATCH($A42,tblLedger[Ledger Record ID],0))=""),"Yes","No") | P42: =IF(COUNTIF({"Yes","No","Partial","Pending","Mapping Hold"},E42)=0,"Yes","No") | Q42: =IF(COUNTIF({"Yes","No","Partial","Pending","Mapping Review"},F42)=0,"Yes","No") | R42: =IF(J42="Yes","Mapping Hold",IF(I42="Yes","Missing Event Link",IF(H42="Yes","Duplicate WO",IF(M42="Yes","Revenue Variance",IF(K42="Yes","Missing Breakdown",IF(L42="Yes","Pending ACH",IF(E42="Partial","Partial Breakdown",IF(N42="Yes","Missing Client",IF(O42="Yes","Missing Location",IF(P42="Yes","Unknown Breakdown Status",IF(Q42="Yes","Unknown ACH Status","OK"))))))))))) | S42: =IF(OR(J42="Yes",I42="Yes",H42="Yes"),"Critical",IF(OR(M42="Yes",E42="Partial",N42="Yes",O42="Yes",P42="Yes",Q42="Yes"),"Warning",IF(OR(K42="Yes",L42="Yes"),"Informational","OK"))) | T42: =IF(R42="Mapping Hold","Resolve mapping before update",IF(R42="Missing Event Link","Map to one authoritative event",IF(R42="Duplicate WO","Review duplicate identity",IF(R42="Revenue Variance","Reconcile or dispute amount",IF(R42="Missing Breakdown","Await breakdown",IF(R42="Pending ACH","Await ACH",IF(R42="Partial Breakdown","Confirm remaining breakdown",IF(R42="Missing Client","Add canonical client",IF(R42="Missing Location","Complete location fields",IF(R42="OK","No action","Review invalid status")))))))))) | U42: =IF(R42="OK","No","Yes") | V42: =ABS(N(G42))
... A95: LED-0065 | B95: =INDEX(tblLedger[Work Order #],MATCH($A95,tblLedger[Ledger Record ID],0)) | C95: =INDEX(tblLedger[Event #],MATCH($A95,tblLedger[Ledger Record ID],0)) | D95: =INDEX(tblLedger[Client],MATCH($A95,tblLedger[Ledger Record ID],0)) | E95: =INDEX(tblLedger[Breakdown Confirmed],MATCH($A95,tblLedger[Ledger Record ID],0)) | F95: =INDEX(tblLedger[ACH Confirmed],MATCH($A95,tblLedger[Ledger Record ID],0)) | G95: =INDEX(tblLedger[Variance],MATCH($A95,tblLedger[Ledger Record ID],0)) | H95: =IF(COUNTIF(tblLedger[Work Order #],B95)>1,"Yes","No") | I95: =IF(C95="","Yes","No") | J95: =IF(INDEX(tblLedger[Mapping Status],MATCH($A95,tblLedger[Ledger Record ID],0))="MAPPING_HOLD","Yes","No") | K95: =IF(AND(OR(E95="No",E95="Pending"),IFERROR(INDEX(tblServiceEvents[Financial Scope],MATCH(C95,tblServiceEvents[Event #],0)),"Included")="Included"),"Yes","No") | L95: =IF(AND(E95="Yes",OR(F95="No",F95="Pending")),"Yes","No") | M95: =IF(OR(ABS(N(G95))>0,INDEX(tblLedger[Reconciliation Status],MATCH($A95,tblLedger[Ledger Record ID],0))="BREAKDOWN_MISMATCH",INDEX(tblLedger[Reconciliation Status],MATCH($A95,tblLedger[Ledger Record ID],0))="ACH_MISMATCH"),"Yes","No") | N95: =IF(D95="","Yes","No") | O95: =IF(OR(INDEX(tblLedger[City],MATCH($A95,tblLedger[Ledger Record ID],0))="",INDEX(tblLedger[Jurisdiction],MATCH($A95,tblLedger[Ledger Record ID],0))=""),"Yes","No") | P95: =IF(COUNTIF({"Yes","No","Partial","Pending","Mapping Hold"},E95)=0,"Yes","No") | Q95: =IF(COUNTIF({"Yes","No","Partial","Pending","Mapping Review"},F95)=0,"Yes","No") | R95: =IF(J95="Yes","Mapping Hold",IF(I95="Yes","Missing Event Link",IF(H95="Yes","Duplicate WO",IF(M95="Yes","Revenue Variance",IF(K95="Yes","Missing Breakdown",IF(L95="Yes","Pending ACH",IF(E95="Partial","Partial Breakdown",IF(N95="Yes","Missing Client",IF(O95="Yes","Missing Location",IF(P95="Yes","Unknown Breakdown Status",IF(Q95="Yes","Unknown ACH Status","OK"))))))))))) | S95: =IF(OR(J95="Yes",I95="Yes",H95="Yes"),"Critical",IF(OR(M95="Yes",E95="Partial",N95="Yes",O95="Yes",P95="Yes",Q95="Yes"),"Warning",IF(OR(K95="Yes",L95="Yes"),"Informational","OK"))) | T95: =IF(R95="Mapping Hold","Resolve mapping before update",IF(R95="Missing Event Link","Map to one authoritative event",IF(R95="Duplicate WO","Review duplicate identity",IF(R95="Revenue Variance","Reconcile or dispute amount",IF(R95="Missing Breakdown","Await breakdown",IF(R95="Pending ACH","Await ACH",IF(R95="Partial Breakdown","Confirm remaining breakdown",IF(R95="Missing Client","Add canonical client",IF(R95="Missing Location","Complete location fields",IF(R95="OK","No action","Review invalid status")))))))))) | U95: =IF(R95="OK","No","Yes") | V95: =ABS(N(G95))
A96: LED-0066 | S96: =IF(OR(J96="Yes",I96="Yes",H96="Yes"),"Critical",IF(OR(M96="Yes",E96="Partial",N96="Yes",O96="Yes",P96="Yes",Q96="Yes"),"Warning",IF(OR(K96="Yes",L96="Yes"),"Informational","OK"))) | T96: =IF(R96="Mapping Hold","Resolve mapping before update",IF(R96="Missing Event Link","Map to one authoritative event",IF(R96="Duplicate WO","Review duplicate identity",IF(R96="Revenue Variance","Reconcile or dispute amount",IF(R96="Missing Breakdown","Await breakdown",IF(R96="Pending ACH","Await ACH",IF(R96="Partial Breakdown","Confirm remaining breakdown",IF(R96="Missing Client","Add canonical client",IF(R96="Missing Location","Complete location fields",IF(R96="OK","No action","Review invalid status")))))))))) | U96: =IF(R96="OK","No","Yes") | V96: =ABS(N(G96))
A97: LED-0067 | B97: =INDEX(tblLedger[Work Order #],MATCH($A97,tblLedger[Ledger Record ID],0)) | C97: =INDEX(tblLedger[Event #],MATCH($A97,tblLedger[Ledger Record ID],0)) | D97: =INDEX(tblLedger[Client],MATCH($A97,tblLedger[Ledger Record ID],0)) | E97: =INDEX(tblLedger[Breakdown Confirmed],MATCH($A97,tblLedger[Ledger Record ID],0)) | F97: =INDEX(tblLedger[ACH Confirmed],MATCH($A97,tblLedger[Ledger Record ID],0)) | G97: =INDEX(tblLedger[Variance],MATCH($A97,tblLedger[Ledger Record ID],0)) | H97: =IF(COUNTIF(tblLedger[Work Order #],B97)>1,"Yes","No") | I97: =IF(C97="","Yes","No") | J97: =IF(INDEX(tblLedger[Mapping Status],MATCH($A97,tblLedger[Ledger Record ID],0))="MAPPING_HOLD","Yes","No") | K97: =IF(AND(OR(E97="No",E97="Pending"),IFERROR(INDEX(tblServiceEvents[Financial Scope],MATCH(C97,tblServiceEvents[Event #],0)),"Included")="Included"),"Yes","No") | L97: =IF(AND(E97="Yes",OR(F97="No",F97="Pending")),"Yes","No") | M97: =IF(OR(ABS(N(G97))>0,INDEX(tblLedger[Reconciliation Status],MATCH($A97,tblLedger[Ledger Record ID],0))="BREAKDOWN_MISMATCH",INDEX(tblLedger[Reconciliation Status],MATCH($A97,tblLedger[Ledger Record ID],0))="ACH_MISMATCH"),"Yes","No") | N97: =IF(D97="","Yes","No") | O97: =IF(OR(INDEX(tblLedger[City],MATCH($A97,tblLedger[Ledger Record ID],0))="",INDEX(tblLedger[Jurisdiction],MATCH($A97,tblLedger[Ledger Record ID],0))=""),"Yes","No") | P97: =IF(COUNTIF({"Yes","No","Partial","Pending","Mapping Hold"},E97)=0,"Yes","No") | Q97: =IF(COUNTIF({"Yes","No","Partial","Pending","Mapping Review"},F97)=0,"Yes","No") | R97: =IF(J97="Yes","Mapping Hold",IF(I97="Yes","Missing Event Link",IF(H97="Yes","Duplicate WO",IF(M97="Yes","Revenue Variance",IF(K97="Yes","Missing Breakdown",IF(L97="Yes","Pending ACH",IF(E97="Partial","Partial Breakdown",IF(N97="Yes","Missing Client",IF(O97="Yes","Missing Location",IF(P97="Yes","Unknown Breakdown Status",IF(Q97="Yes","Unknown ACH Status","OK"))))))))))) | S97: =IF(OR(J97="Yes",I97="Yes",H97="Yes"),"Critical",IF(OR(M97="Yes",E97="Partial",N97="Yes",O97="Yes",P97="Yes",Q97="Yes"),"Warning",IF(OR(K97="Yes",L97="Yes"),"Informational","OK"))) | T97: =IF(R97="Mapping Hold","Resolve mapping before update",IF(R97="Missing Event Link","Map to one authoritative event",IF(R97="Duplicate WO","Review duplicate identity",IF(R97="Revenue Variance","Reconcile or dispute amount",IF(R97="Missing Breakdown","Await breakdown",IF(R97="Pending ACH","Await ACH",IF(R97="Partial Breakdown","Confirm remaining breakdown",IF(R97="Missing Client","Add canonical client",IF(R97="Missing Location","Complete location fields",IF(R97="OK","No action","Review invalid status")))))))))) | U97: =IF(R97="OK","No","Yes") | V97: =ABS(N(G97))
